Workbook

Sheet README
A1: Private credit, AI-SPV and repo contagion stress model
A2: Built for the Proteo Markets post The Six-Point Cliff. 24 institutions (13 US, 10 non-US, Jefferies). USD bn. Inputs as of 19 Oct 2026: CET1 and RWA of the 12 US banks that had reported at 30-Sep-2026, other balance-sheet items at 30-Jun-2026 unless noted; listed BDC P/NAV at 19-Oct-2026 prices.
A3: What it does
A4: 1. Models each risk on its own (11 modules, Modules sheet), per bank, from filings: back-leverage to private-credit intermediaries with a look-through to the junk loans they hold (M1, BDC + BDC_EAD + CreditEngine), fund finance (M2), structured-entity / ABF lending (M3), PE-owned insurers (M4), AI / GPU / data-centre SPVs with chip obsolescence (M5, AI_Deals), trading and HFS marks (M6), CRE (M7), rates incl. forced HTM sales (M8), loss of SRT relief (M9), written sub-IG TRS (M10), prime / margin gap risk (M11).
A5: 2. Connects banks through the repo and funding markets (Contagion sheet, 8 rounds): capital loss -> rating notches -> contractual triggers, deposit / wholesale / MMF CP run-off, repo haircut add-ons and non-rollover of inventory repo -> liquidity shortfall -> forced asset sales; MMF withdrawal of private-collateral repo -> matched-book clients forced to sell; BDC / private-credit funds and insurers sell into the same markets -> price impact by asset class -> re-marks of every bank's holdings and of private-credit pools behind back-leverage -> interbank losses when a bank defaults (max-entropy network).
A6: 2b. Panic / information contagion: every round the street reads public news (BDC coverage breaches, private-credit price discount, G-SIB downgrades and MDA breaches, any failure) and sets a panic intensity S (0-1). S pushes the credit factor down (credit crunch), widens spreads, moves private-credit marks to market, makes funds sell and redeem, triggers runs on the weakest-ranked banks and in wholesale / CP / repo funding, and applies a common panic discount to every risky asset class at once (correlations -> 1). Flight-to-quality deposits go to the strongest half.
A7: 3. Rerating tests: rating migration of the underlying loans (S&P average vs Moody's 2009 matrices) cuts borrowing bases and forces BDC sales; BDCs losing IG draw their bank revolvers in full; bank downgrades drive runs.
A8: 4. Monte Carlo (10,000 joint draws, Student-t fat tails with a crisis regime in which correlations go to 0.95, panic on, conditioned on today), probability ladder and trigger-conditional probabilities (Fat_Tails), reverse stress and an each-module-alone grid, computed by engine.py (Python mirror of these formulas) and written to MC_Summary, MC_Distribution, Reverse_Stress and Standalone_Grid as values. Checks proves the Excel formulas reproduce the Python engine for the active scenario.
A9: How to use
A10: Dashboard!C4: pick a scenario. Scenarios sheet: edit the yellow Custom column (or any blue value); sw_M1..sw_M11 switch modules off; fs_on / ib_on / liq_on switch contagion channels off. Every bank input is on Inputs_Banks / Holdings / BDC / BDC_EAD / AI_Deals with its source on Sources.
A11: To refresh Monte Carlo / reverse stress after changing inputs: save in Excel, then run python engine.py Private_Credit_Contagion_Model.xlsx (prints all scenarios) or python post.py <file> (rewrites the value sheets). post.py needs LibreOffice for its recalculation step.
A12: Sheet map
... A15: Bank-level private-credit, AI and BDC facility holdings are partly estimates (orange). Call-report business-credit-intermediary (BCI) loans are treated as back-leverage on junk pools: conservative for banks whose book is mostly IG fund lending (State Street in particular). BofA's $49.9bn written sub-IG TRS is treated as financing with an 80% advance (interpretation unresolved). Price-impact coefficients for illiquid credit, run-off rates and the Monte Carlo lever mappings are judgment, documented on Scenarios / Holdings / MC_Summary. No PPNR credit in named scenarios (instantaneous marks). Probabilities are model-conditional, not forecasts.

Sheet Dashboard
A1: Private credit, AI-SPV and repo contagion stress model - 24 banks
A2: As of 19 Oct 2026. Pick a scenario in C4 (or edit the Custom column on Scenarios). USD bn.
B4: Active scenario | C4: 2008-combined | E4: <- choose: Baseline, Software/AI repricing, GPU obsolescence, Credit 2009, Rerating cascade, Repo run, Rates shock, 2008-combined, Panic cascade, Custom
B6: SYSTEM | H6: MONTE CARLO, 3-yr horizon: fat tails + panic, conditioned on today (see MC_Summary, Fat_Tails) | L6: Backstop ON | M6: Backstop OFF
B7: Standalone loss, all banks ($bn) | F7: =Results!B33 -> 748.90712 | H7: =MC_Summary!A5 -> P(systemic: >=3 G-SIBs < MDA or any G-SIB default) | L7: =MC_Summary!B5 -> 0.0997 | M7: =MC_Summary!C5 -> 0.12
B8: Final loss, all banks ($bn) | F8: =Results!B34 -> 1465.0937 | H8: =MC_Summary!A6 -> P(>=1 G-SIB below MDA) | L8: =MC_Summary!B6 -> 0.1014 | M8: =MC_Summary!C6 -> 0.1251
B9: Contagion amplification (final / standalone) | F9: =Results!B35 -> 1.956309 | H9: =MC_Summary!A7 -> P(>=3 G-SIBs below MDA) | L9: =MC_Summary!B7 -> 0.0997 | M9: =MC_Summary!C7 -> 0.12
B10: G-SIBs below MDA | F10: =Results!B36 -> 18 | H10: =MC_Summary!A8 -> P(>=1 G-SIB below 4.5% minimum) | L10: =MC_Summary!B8 -> 0.0767 | M10: =MC_Summary!C8 -> 0.1053
B11: G-SIBs below 4.5% minimum | F11: =Results!B37 -> 11 | H11: =MC_Summary!A9 -> P(any institution in default / resolution) | L11: =MC_Summary!B9 -> 0.0766 | M11: =MC_Summary!C9 -> 0.1098
B12: Institutions in default / resolution | F12: =Results!B38 -> 14
B13: Capital shortfall to MDA, all banks ($bn) | F13: =Results!B39 -> 1192.2265 | H13: REVERSE STRESS (joint factor, no earnings credit; see Reverse_Stress) | L13: z | M13: Pool mark
B14: Liquidity shortfall, all banks ($bn) | F14: =Results!B40 -> 1693.2005 | H14: First G-SIB below MDA | L14: =Reverse_Stress!B108 -> -0.875 | M14: =Reverse_Stress!C108 -> 0.84612651
B15: SYSTEMIC (>=3 G-SIBs below MDA or any G-SIB in default) | F15: =Results!B41 -> YES | H15: Systemic (>=3 G-SIBs below MDA) | L15: =Reverse_Stress!D108 -> -1 | M15: =Reverse_Stress!E108 -> 0.8206049
B16: Total forced sales, all sellers ($bn) | F16: =Results!B42 -> 2113.5618 | H16: First G-SIB below 4.5% minimum | L16: =Reverse_Stress!F108 -> -1.125 | M16: =Reverse_Stress!G108 -> 0.7943519
B17: BDCs losing IG / below 150% coverage (standalone) | F17: =Results!B43 -> 34 / 33 | H17: First default / resolution | L17: =Reverse_Stress!H108 -> -1.125 | M17: =Reverse_Stress!I108 -> 0.7943519
B18: Generic private-credit pool value, final round (hold) | F18: =Results!B44 -> 0.40814662 | H18: Backstop ON row shown; OFF row on Reverse_Stress.
B19: Pool 3-yr PD, generic / software (final round) | F19: =Results!B45 -> 79.1% / 92.4% | H19: P(>=1 G-SIB below 4.5%) by horizon (constant hazard)
B20: PANIC INTENSITY S, final round (0-1) | F20: =Results!B46 -> 1 | H20: 1 year | L20: =1-(1-MC_Summary!B8)^(1/3) -> 0.026249683 | M20: =1-(1-MC_Summary!C8)^(1/3) -> 0.036409568
B21: Panic path, rounds 1..8 | F21: =Results!B47 -> 100% > 100% > 100% > 100% > 100% > 100% > 100% > 100% | H21: 3 months | L21: =1-(1-MC_Summary!B8)^(1/12) -> 0.0066280263 | M21: =1-(1-MC_Summary!C8)^(1/12) -> 0.0092293798
B23: Legend: blue = input, black = formula, green = link to another sheet, orange fill = estimate / proxy, yellow = choose / edit. USD bn. Ratios = CET1 / stressed RWA.
B25: Id | C25: Institution | D25: CET1 now | E25: Req. | F25: After standalone | G25: Final | H25: Status | I25: Standalone loss | J25: Final loss | K25: Liquidity shortfall | L25: Notches
B26: =Results!A6 -> JPM | C26: =Results!B6 -> JPMorgan | D26: =Results!D6 -> 0.13927181 | E26: =Results!E6 -> 0.115 | F26: =Results!G6 -> 0.090560708 | G26: =Results!I6 -> 0.057992627 | H26: =Results!L6 -> MDA breach | I26: =Results!F6 -> 90.54155 | J26: =Results!H6 -> 167.34295 | K26: =Results!O6 -> 0 | L26: =Results!M6 -> 4
B27: =Results!A7 -> BAC | C27: =Results!B7 -> Bank of America | D27: =Results!D7 -> 0.10877789 | E27: =Results!E7 -> 0.1 | F27: =Results!G7 -> 0.063912327 | G27: =Results!I7 -> 0.026950106 | H27: =Results!L7 -> Below minimum | I27: =Results!F7 -> 72.504731 | J27: =Results!H7 -> 145.31336 | K27: =Results!O7 -> 280.44922 | L27: =Results!M7 -> 6
B28: =Results!A8 -> C | C28: =Results!B8 -> Citigroup | D28: =Results!D8 -> 0.12777011 | E28: =Results!E8 -> 0.116 | F28: =Results!G8 -> 0.074774286 | G28: =Results!I8 -> 0.040234798 | H28: =Results!L8 -> Below minimum | I28: =Results!F8 -> 57.916402 | J28: =Results!H8 -> 103.86953 | K28: =Results!O8 -> 263.57463 | L28: =Results!M8 -> 6
B29: =Results!A9 -> WFC | C29: =Results!B9 -> Wells Fargo | D29: =Results!D9 -> 0.10046276 | E29: =Results!E9 -> 0.085 | F29: =Results!G9 -> 0.042444949 | G29: =Results!I9 -> 0.0020739028 | H29: =Results!L9 -> Below minimum | I29: =Results!F9 -> 73.182838 | J29: =Results!H9 -> 131.5991 | K29: =Results!O9 -> 326.58085 | L29: =Results!M9 -> 6
B30: =Results!A10 -> GS | C30: =Results!B10 -> Goldman Sachs | D30: =Results!D10 -> 0.12411261 | E30: =Results!E10 -> 0.114 | F30: =Results!G10 -> 0.060409672 | G30: =Results!I10 -> 0.010515679 | H30: =Results!L10 -> Below minimum | I30: =Results!F10 -> 48.096922 | J30: =Results!H10 -> 92.121385 | K30: =Results!O10 -> 0 | L30: =Results!M10 -> 6
B31: =Results!A11 -> MS | C31: =Results!B11 -> Morgan Stanley | D31: =Results!D11 -> 0.1490433 | E31: =Results!E11 -> 0.118 | F31: =Results!G11 -> 0.07461862 | G31: =Results!I11 -> 0.018967748 | H31: =Results!L11 -> Below minimum | I31: =Results!F11 -> 40.785604 | J31: =Results!H11 -> 76.594937 | K31: =Results!O11 -> 0 | L31: =Results!M11 -> 6
B32: =Results!A12 -> PNC | C32: =Results!B12 -> PNC | D32: =Results!D12 -> 0.098043131 | E32: =Results!E12 -> 0.07 | F32: =Results!G12 -> 0.037635245 | G32: =Results!I12 -> 0.0036018265 | H32: =Results!L12 -> Below minimum | I32: =Results!F12 -> 28.744451 | J32: =Results!H12 -> 47.151902 | K32: =Results!O12 -> 71.598487 | L32: =Results!M12 -> 6
B33: =Results!A13 -> USB | C33: =Results!B13 -> U.S. Bancorp | D33: =Results!D13 -> 0.10822511 | E33: =Results!E13 -> 0.071 | F33: =Results!G13 -> 0.074607178 | G33: =Results!I13 -> 0.050903962 | H33: =Results!L13 -> MDA breach | I33: =Results!F13 -> 14.051402 | J33: =Results!H13 -> 27.061055 | K33: =Results!O13 -> 0 | L33: =Results!M13 -> 3
B34: =Results!A14 -> TFC | C34: =Results!B14 -> Truist | D34: =Results!D14 -> 0.10722557 | E34: =Results!E14 -> 0.07 | F34: =Results!G14 -> 0.051950612 | G34: =Results!I14 -> 0.015729221 | H34: =Results!L14 -> Below minimum | I34: =Results!F14 -> 22.073144 | J34: =Results!H14 -> 38.964772 | K34: =Results!O14 -> 74.570633 | L34: =Results!M14 -> 6
B35: =Results!A15 -> STT | C35: =Results!B15 -> State Street | D35: =Results!D15 -> 0.10953058 | E35: =Results!E15 -> 0.08 | F35: =Results!G15 -> -0.011077412 | G35: =Results!I15 -> -0.11290916 | H35: =Results!L15 -> Insolvent | I35: =Results!F15 -> 17.082083 | J35: =Results!H15 -> 32.54503 | K35: =Results!O15 -> 116.96806 | L35: =Results!M15 -> 6
B36: =Results!A16 -> BK | C36: =Results!B16 -> BNY | D36: =Results!D16 -> 0.10948905 | E36: =Results!E16 -> 0.085 | F36: =Results!G16 -> 0.07119447 | G36: =Results!I16 -> 0.033469555 | H36: =Results!L16 -> Below minimum | I36: =Results!F16 -> 6.2524927 | J36: =Results!H16 -> 14.066982 | K36: =Results!O16 -> 85.534064 | L36: =Results!M16 -> 6
B37: =Results!A17 -> FCNCA | C37: =Results!B17 -> First Citizens | D37: =Results!D17 -> 0.10771939 | E37: =Results!E17 -> 0.07 | F37: =Results!G17 -> 0.067473721 | G37: =Results!I17 -> 0.059496066 | H37: =Results!L17 -> MDA breach | I37: =Results!F17 -> 6.4328991 | J37: =Results!H17 -> 8.0233884 | K37: =Results!O17 -> 0 | L37: =Results!M17 -> 2
... B49: =Results!A29 -> JEF | C49: =Results!B29 -> Jefferies | D49: =Results!D29 -> 0.09 | E49: =Results!E29 -> 0.0675 | F49: =Results!G29 -> 0.072274665 | G49: =Results!I29 -> 0.054936025 | H49: =Results!L29 -> MDA breach | I49: =Results!F29 -> 1.1569136 | J49: =Results!H29 -> 2.9708128 | K49: =Results!O29 -> 1.8886978 | L49: =Results!M29 -> 2

Sheet Scenarios
A1: Scenario parameters
A2: Columns E-N = scenario values (blue inputs; Custom in yellow is free to edit). Column O = active value used by every formula (named p_<key>). Select the scenario on Dashboard!C4.
A4: Key | B4: Group | C4: Description | D4: Unit | E4: Baseline | F4: Software/AI repricing | G4: GPU obsolescence | H4: Credit 2009 | I4: Rerating cascade | J4: Repo run | K4: Rates shock | L4: 2008-combined | M4: Panic cascade | N4: Custom | O4: ACTIVE | P4: Basis / source
A5: z | B5: Credit pool | C5: Systematic credit factor (3-yr horizon; negative = bad) | D5: z | E5: 0 | F5: -1 | G5: -0.5 | H5: -2 | I5: -1 | J5: -0.5 | K5: -0.5 | L5: -2.5 | M5: -1 | N5: -2.5 | O5: =INDEX($E5:$N5,1,MATCH(sel_scen,$E$4:$N$4,0)) -> -2.5 | P5: Vasicek one-factor. z=-2.0 reproduces S&P 2000-02 3-yr cumulative B/B- defaults (32.7%/45.0%) with rho=0.20
A6: hid | B6: Credit pool | C6: Hidden-default add-on to 3-yr PD (shadow defaults not yet recognised) | D6: frac | E6: 0 | F6: 0.02 | G6: 0 | H6: 0.03 | I6: 0.02 | J6: 0 | K6: 0 | L6: 0.062 | M6: 0.02 | N6: 0.062 | O6: =INDEX($E6:$N6,1,MATCH(sel_scen,$E$4:$N$4,0)) -> 0.062 | P6: Lincoln bad-PIK 6.2% of loans (Q2-26) = upper bound of defaults masked by PIK/extensions
A7: m_sw | B7: Credit pool | C7: Software sub-pool PD multiplier (AI disruption) | D7: x | E7: 1 | F7: 2 | G7: 1.5 | H7: 1.25 | I7: 1.5 | J7: 1 | K7: 1 | L7: 2 | M7: 1.5 | N7: 2 | O7: =INDEX($E7:$N7,1,MATCH(sel_scen,$E$4:$N$4,0)) -> 2 | P7: Judgment; Fitch software PCDR only 0.6% today but distressed software marks 50-65
A8: lgd_gen | B8: Credit pool | C8: LGD, generic direct-lending loans | D8: frac | E8: 0.35 | F8: 0.4 | G8: 0.35 | H8: 0.5 | I8: 0.4 | J8: 0.35 | K8: 0.35 | L8: 0.5 | M8: 0.4 | N8: 0.5 | O8: =INDEX($E8:$N8,1,MATCH(sel_scen,$E$4:$N$4,0)) -> 0.5 | P8: 1L/unitranche recovery 65% base, 50% stress (Moody's 2009 1L price 54%)
A9: lgd_sw | B9: Credit pool | C9: LGD, software / ARR loans | D9: frac | E9: 0.5 | F9: 0.65 | G9: 0.55 | H9: 0.65 | I9: 0.6 | J9: 0.5 | K9: 0.5 | L9: 0.7 | M9: 0.6 | N9: 0.7 | O9: =INDEX($E9:$N9,1,MATCH(sel_scen,$E$4:$N$4,0)) -> 0.7 | P9: Small/mid software recovery 20-40% in stress (Zito via WSJ/Bloomberg)
A10: ds | B10: Credit pool | C10: Spread widening on performing loans | D10: bp | E10: 0 | F10: 150 | G10: 75 | H10: 600 | I10: 250 | J10: 150 | K10: 50 | L10: 700 | M10: 250 | N10: 700 | O10: =INDEX($E10:$N10,1,MATCH(sel_scen,$E$4:$N$4,0)) -> 700 | P10: Software sub-index -7.5 pts YTD Feb-26; 2008 LLI low 60.33. Spread duration 3 yrs (CDLI life 3.2)
A11: ds_sw | B11: Credit pool | C11: Extra spread widening, software loans | D11: bp | E11: 0 | F11: 300 | G11: 150 | H11: 200 | I11: 150 | J11: 0 | K11: 0 | L11: 300 | M11: 150 | N11: 300 | O11: =INDEX($E11:$N11,1,MATCH(sel_scen,$E$4:$N$4,0)) -> 300 | P11: Judgment: software performing bids 87.6 (Feb-26) vs index 94.6
A12: gap | B12: Credit pool | C12: Valuation gap: carrying marks overstate value by | D12: frac | E12: 0 | F12: 0.03 | G12: 0 | H12: 0.05 | I12: 0.03 | J12: 0.02 | K12: 0 | L12: 0.1 | M12: 0.03 | N12: 0.1 | O12: =INDEX($E12:$N12,1,MATCH(sel_scen,$E$4:$N$4,0)) -> 0.1 | P12: Same loan marked ~10 vs ~100 across lenders; market-implied marks 78-98
A13: w_mkt | B13: Credit pool | C13: Weight on market-implied BDC marks (P/NAV) | D13: frac | E13: 0 | F13: 0.5 | G13: 0.25 | H13: 1 | I13: 0.5 | J13: 1 | K13: 0.25 | L13: 1 | M13: 0.5 | N13: 1 | O13: =INDEX($E13:$N13,1,MATCH(sel_scen,$E$4:$N$4,0)) -> 1 | P13: Listed BDC P/NAV 6-Oct-26; non-traded use listed asset-weighted average
A14: phi | B14: Credit pool | C14: Share of SPV facilities enforced / liquidated now (vs worked out) | D14: frac | E14: 0.1 | F14: 0.3 | G14: 0.2 | H14: 0.5 | I14: 0.4 | J14: 0.6 | K14: 0.2 | L14: 0.8 | M14: 0.4 | N14: 0.8 | O14: =INDEX($E14:$N14,1,MATCH(sel_scen,$E$4:$N$4,0)) -> 0.8 | P14: JPM market-value SPVs cure in 2 business days (OSCF EX-10)
A15: c_liq | B15: Credit pool | C15: Liquidation cost on enforced pools | D15: frac | E15: 0.02 | F15: 0.03 | G15: 0.02 | H15: 0.05 | I15: 0.03 | J15: 0.05 | K15: 0.02 | L15: 0.05 | M15: 0.03 | N15: 0.05 | O15: =INDEX($E15:$N15,1,MATCH(sel_scen,$E$4:$N$4,0)) -> 0.05 | P15: Judgment
A16: a_spv | B16: Credit pool | C16: SPV advance rate (back-leverage, vs current pool value) | D16: frac | E16: 0.7 | F16: 0.7 | G16: 0.7 | H16: 0.7 | I16: 0.7 | J16: 0.7 | K16: 0.7 | L16: 0.7 | M16: 0.7 | N16: 0.75 | O16: =INDEX($E16:$N16,1,MATCH(sel_scen,$E$4:$N$4,0)) -> 0.7 | P16: SPV EX-10 first-lien 60-75%, MM 1L 65-72.5%
... A70: lgd_ib | B70: Contagion | C70: Loss on unsecured interbank claims to a failed bank | D70: frac | E70: 0.05 | F70: 0.05 | G70: 0.05 | H70: 0.1 | I70: 0.1 | J70: 0.2 | K70: 0.1 | L70: 0.4 | M70: 0.1 | N70: 0.4 | O70: =INDEX($E70:$N70,1,MATCH(sel_scen,$E$4:$N$4,0)) -> 0.4 | P70: SPOE resolution ~0-5%; Lehman-style 40%+
A71: fs_on | B71: Switches | C71: Fire-sale contagion on (1/0) | D71: 0/1 | E71: 1 | F71: 1 | G71: 1 | H71: 1 | I71: 1 | J71: 1 | K71: 1 | L71: 1 | M71: 1 | N71: 1 | O71: =INDEX($E71:$N71,1,MATCH(sel_scen,$E$4:$N$4,0)) -> 1
A72: ib_on | B72: Switches | C72: Interbank default contagion on (1/0) | D72: 0/1 | E72: 1 | F72: 1 | G72: 1 | H72: 1 | I72: 1 | J72: 1 | K72: 1 | L72: 1 | M72: 1 | N72: 1 | O72: =INDEX($E72:$N72,1,MATCH(sel_scen,$E$4:$N$4,0)) -> 1
A73: liq_on | B73: Switches | C73: Liquidity / run channel on (1/0) | D73: 0/1 | E73: 1 | F73: 1 | G73: 1 | H73: 1 | I73: 1 | J73: 1 | K73: 1 | L73: 1 | M73: 1 | N73: 1 | O73: =INDEX($E73:$N73,1,MATCH(sel_scen,$E$4:$N$4,0)) -> 1
A74: sw_M1 | B74: Switches | C74: Module M1 on (1/0) | D74: 0/1 | E74: 1 | F74: 1 | G74: 1 | H74: 1 | I74: 1 | J74: 1 | K74: 1 | L74: 1 | M74: 1 | N74: 1 | O74: =INDEX($E74:$N74,1,MATCH(sel_scen,$E$4:$N$4,0)) -> 1
A75: sw_M2 | B75: Switches | C75: Module M2 on (1/0) | D75: 0/1 | E75: 1 | F75: 1 | G75: 1 | H75: 1 | I75: 1 | J75: 1 | K75: 1 | L75: 1 | M75: 1 | N75: 1 | O75: =INDEX($E75:$N75,1,MATCH(sel_scen,$E$4:$N$4,0)) -> 1
A76: sw_M3 | B76: Switches | C76: Module M3 on (1/0) | D76: 0/1 | E76: 1 | F76: 1 | G76: 1 | H76: 1 | I76: 1 | J76: 1 | K76: 1 | L76: 1 | M76: 1 | N76: 1 | O76: =INDEX($E76:$N76,1,MATCH(sel_scen,$E$4:$N$4,0)) -> 1
A77: sw_M4 | B77: Switches | C77: Module M4 on (1/0) | D77: 0/1 | E77: 1 | F77: 1 | G77: 1 | H77: 1 | I77: 1 | J77: 1 | K77: 1 | L77: 1 | M77: 1 | N77: 1 | O77: =INDEX($E77:$N77,1,MATCH(sel_scen,$E$4:$N$4,0)) -> 1
A78: sw_M5 | B78: Switches | C78: Module M5 on (1/0) | D78: 0/1 | E78: 1 | F78: 1 | G78: 1 | H78: 1 | I78: 1 | J78: 1 | K78: 1 | L78: 1 | M78: 1 | N78: 1 | O78: =INDEX($E78:$N78,1,MATCH(sel_scen,$E$4:$N$4,0)) -> 1
A79: sw_M6 | B79: Switches | C79: Module M6 on (1/0) | D79: 0/1 | E79: 1 | F79: 1 | G79: 1 | H79: 1 | I79: 1 | J79: 1 | K79: 1 | L79: 1 | M79: 1 | N79: 1 | O79: =INDEX($E79:$N79,1,MATCH(sel_scen,$E$4:$N$4,0)) -> 1
A80: sw_M7 | B80: Switches | C80: Module M7 on (1/0) | D80: 0/1 | E80: 1 | F80: 1 | G80: 1 | H80: 1 | I80: 1 | J80: 1 | K80: 1 | L80: 1 | M80: 1 | N80: 1 | O80: =INDEX($E80:$N80,1,MATCH(sel_scen,$E$4:$N$4,0)) -> 1
A81: sw_M8 | B81: Switches | C81: Module M8 on (1/0) | D81: 0/1 | E81: 1 | F81: 1 | G81: 1 | H81: 1 | I81: 1 | J81: 1 | K81: 1 | L81: 1 | M81: 1 | N81: 1 | O81: =INDEX($E81:$N81,1,MATCH(sel_scen,$E$4:$N$4,0)) -> 1
A82: sw_M9 | B82: Switches | C82: Module M9 on (1/0) | D82: 0/1 | E82: 1 | F82: 1 | G82: 1 | H82: 1 | I82: 1 | J82: 1 | K82: 1 | L82: 1 | M82: 1 | N82: 1 | O82: =INDEX($E82:$N82,1,MATCH(sel_scen,$E$4:$N$4,0)) -> 1
... A84: sw_M11 | B84: Switches | C84: Module M11 on (1/0) | D84: 0/1 | E84: 1 | F84: 1 | G84: 1 | H84: 1 | I84: 1 | J84: 1 | K84: 1 | L84: 1 | M84: 1 | N84: 1 | O84: =INDEX($E84:$N84,1,MATCH(sel_scen,$E$4:$N$4,0)) -> 1
A85: panic_on | B85: Panic | C85: Panic / information contagion on (1/0) | D85: 0/1 | E85: 1 | F85: 1 | G85: 1 | H85: 1 | I85: 1 | J85: 1 | K85: 1 | L85: 1 | M85: 1 | N85: 1 | O85: =INDEX($E85:$N85,1,MATCH(sel_scen,$E$4:$N$4,0)) -> 1 | P85: Off reproduces the version without panic
A86: S0 | B86: Panic | C86: Panic intensity at the start (0-1): the market state today | D86: frac | E86: 0.1 | F86: 0.15 | G86: 0.15 | H86: 0.2 | I86: 0.15 | J86: 0.3 | K86: 0.15 | L86: 0.3 | M86: 0.25 | N86: 0.3 | O86: =INDEX($E86:$N86,1,MATCH(sel_scen,$E$4:$N$4,0)) -> 0.3 | P86: 7-Oct-26: European banks -4 to -6% on the day, US bank and alt-manager stocks -10 to -28% from 3-month highs, but VIX 15.7, HY and loan ETFs within 1-3% of highs (Yahoo prices)
A87: news0 | B87: Panic | C87: Exogenous news already public (gate breaches, headlines), news units | D87: x | E87: 0.05 | F87: 0.05 | G87: 0.05 | H87: 0.05 | I87: 0.05 | J87: 0.1 | K87: 0.05 | L87: 0.1 | M87: 0.25 | N87: 0.25 | O87: =INDEX($E87:$N87,1,MATCH(sel_scen,$E$4:$N$4,0)) -> 0.1 | P87: Q3 tender requests above 2x the 5% gate at OCIC, ADS, HLEND, ASIF, OTIC (39%), NHPIF; Panic cascade adds a gate break + bank downgrade headlines
A88: zc | B88: Panic | C88: Credit-crunch feedback: fall in the credit factor at full panic | D88: z | E88: 0.75 | F88: 0.75 | G88: 0.75 | H88: 0.75 | I88: 0.75 | J88: 0.75 | K88: 0.75 | L88: 0.75 | M88: 0.75 | N88: 0.75 | O88: =INDEX($E88:$N88,1,MATCH(sel_scen,$E$4:$N$4,0)) -> 0.75 | P88: Judgment: refinancing window shuts for B/CCC borrowers in panic
A89: ds_pan | B89: Panic | C89: Extra spread widening on performing loans at full panic | D89: bp | E89: 400 | F89: 400 | G89: 400 | H89: 400 | I89: 400 | J89: 400 | K89: 400 | L89: 400 | M89: 400 | N89: 400 | O89: =INDEX($E89:$N89,1,MATCH(sel_scen,$E$4:$N$4,0)) -> 400 | P89: Judgment: March 2020 loan index fell to 76.23
A90: u_pan_all | B90: Panic | C90: Extra uninsured-deposit run-off at full panic, all banks | D90: frac | E90: 0.05 | F90: 0.05 | G90: 0.05 | H90: 0.05 | I90: 0.05 | J90: 0.05 | K90: 0.05 | L90: 0.05 | M90: 0.05 | N90: 0.05 | O90: =INDEX($E90:$N90,1,MATCH(sel_scen,$E$4:$N$4,0)) -> 0.05 | P90: Judgment
A91: u_pan_weak | B91: Panic | C91: Extra run-off at full panic for banks the street sees as weak | D91: frac | E91: 0.2 | F91: 0.2 | G91: 0.2 | H91: 0.2 | I91: 0.2 | J91: 0.2 | K91: 0.2 | L91: 0.2 | M91: 0.2 | N91: 0.2 | O91: =INDEX($E91:$N91,1,MATCH(sel_scen,$E$4:$N$4,0)) -> 0.2 | P91: SVB ~25% of deposits in one day; Twitter attention amplified run severity (Cookson et al. 2023)
A92: w_pan | B92: Panic | C92: Extra wholesale non-rollover at full panic | D92: frac | E92: 0.4 | F92: 0.4 | G92: 0.4 | H92: 0.4 | I92: 0.4 | J92: 0.4 | K92: 0.4 | L92: 0.4 | M92: 0.4 | N92: 0.4 | O92: =INDEX($E92:$N92,1,MATCH(sel_scen,$E$4:$N$4,0)) -> 0.4 | P92: Judgment
A93: cp_pan | B93: Panic | C93: Extra prime-MMF CP/CD non-rollover at full panic | D93: frac | E93: 0.5 | F93: 0.5 | G93: 0.5 | H93: 0.5 | I93: 0.5 | J93: 0.5 | K93: 0.5 | L93: 0.5 | M93: 0.5 | N93: 0.5 | O93: =INDEX($E93:$N93,1,MATCH(sel_scen,$E$4:$N$4,0)) -> 0.5 | P93: Judgment
A94: pull_pan | B94: Panic | C94: Extra MMF withdrawal of other-collateral repo at full panic | D94: frac | E94: 0.5 | F94: 0.5 | G94: 0.5 | H94: 0.5 | I94: 0.5 | J94: 0.5 | K94: 0.5 | L94: 0.5 | M94: 0.5 | N94: 0.5 | O94: =INDEX($E94:$N94,1,MATCH(sel_scen,$E$4:$N$4,0)) -> 0.5 | P94: Judgment (2008 tri-party run on quantity)
A95: dh_pan | B95: Panic | C95: Extra haircut on non-govt repo at full panic | D95: frac | E95: 0.1 | F95: 0.1 | G95: 0.1 | H95: 0.1 | I95: 0.1 | J95: 0.1 | K95: 0.1 | L95: 0.1 | M95: 0.1 | N95: 0.1 | O95: =INDEX($E95:$N95,1,MATCH(sel_scen,$E$4:$N$4,0)) -> 0.1 | P95: CGFS 36 2007-09 haircut rises
A96: rec_pan | B96: Panic | C96: Cut in flight-to-quality redeposits at full panic (cash goes to T-bills / govt MMFs) | D96: frac | E96: 0.25 | F96: 0.25 | G96: 0.25 | H96: 0.25 | I96: 0.25 | J96: 0.25 | K96: 0.25 | L96: 0.25 | M96: 0.25 | N96: 0.25 | O96: =INDEX($E96:$N96,1,MATCH(sel_scen,$E$4:$N$4,0)) -> 0.25 | P96: Judgment: large banks gained deposits in 2008, 2020 and 2023
... A100: ins_pan | B100: Panic | C100: Extra insurer run-able funding not rolled at full panic | D100: frac | E100: 0.3 | F100: 0.3 | G100: 0.3 | H100: 0.3 | I100: 0.3 | J100: 0.3 | K100: 0.3 | L100: 0.3 | M100: 0.3 | N100: 0.3 | O100: =INDEX($E100:$N100,1,MATCH(sel_scen,$E$4:$N$4,0)) -> 0.3 | P100: Judgment

Sheet Globals
A1: Global constants (not scenario-dependent)
A2: Blue = input. Each constant is a named range g_<key> used in formulas.
A4: Key | B4: Value | C4: Description / basis
A5: rho | B5: 0.2 | C5: Asset correlation, private-credit pool (Basel corporate range 0.12-0.24)
A6: rho_ai | B6: 0.3 | C6: Asset correlation, AI names (concentrated sector) - judgment
A7: lgd_gen_b | B7: 0.35 | C7: Base-case LGD embedded in carrying values (generic)
A8: lgd_sw_b | B8: 0.5 | C8: Base-case LGD embedded in carrying values (software)
A9: dur_s | B9: 3 | C9: Spread duration of performing direct loans (CDLI effective life 3.2 yrs)
A10: lgd_lp | B10: 0.3 | C10: LGD on defaulted LP commitments (sub lines) - judgment
A11: nav_share | B11: 0.15 | C11: NAV-loan share of fund finance - judgment (FSB: sub lines dominate)
A12: nav_ltv | B12: 0.2 | C12: NAV-loan LTV (Nodem avg ~14%, mostly <=20%; FSB <=30%)
A13: tail_share | B13: 0.2 | C13: Share of NAV loans to tail funds
A14: tail_mult | B14: 2.5 | C14: NAV decline multiple for tail funds
A15: a_abf | B15: 0.8 | C15: Advance rate on ABF / SE senior warehouses - judgment
A16: lgd_ins | B16: 0.4 | C16: LGD on insurer facilities / FA-backed repo (wrong-way) - judgment
... A43: fabr | B43: 27.3 | C43: FA-backed repo outstanding Jun-26 (Fed EFA)

Sheet Inputs_Banks
A1: Per-bank inputs (USD bn; CET1 and RWA of US banks at 30-Sep-2026, other items 30-Jun-2026 unless noted)
A2: Blue = sourced input; orange fill = estimate / proxy (see Sources sheet for every cell); black = formula. FX: EUR 1.1417, GBP 1.3259, JPY 1/162.61, CAD 1/1.4205.
A5: Id | B5: Institution | C5: Report ccy | D5: G-SIB (1/0) | E5: AFS/OCI in CET1 (1/0) | F5: Notches to HY | G5: CET1 ($bn) | H5: RWA ($bn) | I5: CET1 req. incl. buffers (MDA) | J5: PPNR / quarter ($bn) | K5: AFS / FVOCI debt FV ($bn) | L5: AFS unrealised loss ($bn) | M5: HTM / AC book ($bn) | N5: HTM unrealised loss ($bn) | O5: AFS net duration (yrs) | P5: Strategic equities ($bn) | Q5: Back-leverage drawn ($bn) | R5: Back-leverage undrawn ($bn) | S5: Fund finance drawn ($bn) | T5: Fund finance undrawn ($bn) | U5: ABF / SE residual drawn ($bn) | V5: ABF / SE residual undrawn ($bn) | W5: Named-BDC facilities drawn ($bn) | X5: Named-BDC facilities committed ($bn) | Y5: Generic back-leverage drawn ($bn) | Z5: Generic back-leverage undrawn ($bn) | AA5: SRT CET1 relief (bp) | AB5: Prime / margin lending ($bn) | AC5: Written sub-IG TRS ($bn) | AD5: Facilities to insurers ($bn) | AE5: FA-backed repo ($bn) | AF5: CRE loans ($bn) | AG5: HQLA ($bn) | AH5: LCR | AI5: Uninsured / wholesale deposits ($bn) | AJ5: Total deposits ($bn) | AK5: ST unsecured wholesale ($bn) | AL5: Repo + sec. loaned ($bn) | AM5: Non-govt share of repo | AN5: Non-govt repo funding ($bn) | AO5: Prime-MMF CP/CD ($bn) | AP5: MMF repo, other collateral ($bn) | AQ5: CB-eligible capacity ($bn) | AR5: Downgrade outflow 0 notch ($bn) | AS5: Downgrade outflow 1 notch ($bn) | AT5: Downgrade outflow 2 notch ($bn) | AU5: Downgrade outflow 3 notch ($bn) | AV5: Downgrade outflow 4 notch ($bn) | AW5: Downgrade outflow 5 notch ($bn) | AX5: Downgrade outflow 6 notch ($bn) | AY5: Intra-fin. assets ($bn) | AZ5: Intra-fin. liabilities ($bn) | BA5: CET1 ratio now | BB5: Saleable non-HQLA holdings ($bn)
A6: JPM | B6: JPMorgan | C6: USD | D6: 1 | E6: 1 | F6: 5 | G6: 304.1 | H6: 2183.5 | I6: 0.115 | J6: 30.031 | K6: 536.048 | L6: -2.641 | M6: 268.474 | N6: -18.164 | O6: 2.5 | P6: 0 | Q6: 56.5 | R6: 23.1 | S6: 68 | T6: 37.6 | U6: 0 | V6: 0 | W6: =SUM(BDC_EAD!C$31:C$52)+SUM(BDC_EAD!C$81:C$102) -> 2.015715 | X6: =SUM(BDC_EAD!C$6:C$27)+SUM(BDC_EAD!C$56:C$77) -> 4.303613 | Y6: =MAX(0,Q6-W6) -> 54.484285 | Z6: =MAX(0,R6-(X6-W6)) -> 20.812102 | AA6: 0 | AB6: 82.203 | AC6: 0 | AD6: 0 | AE6: 4.55 | AF6: 180.31 | AG6: 975.412 | AH6: 1.1 | AI6: 1743.9 | AJ6: 2713.7 | AK6: 30.166 | AL6: 704.704 | AM6: 0.26699021 | AN6: =AL6*AM6 -> 188.14907 | AO6: 5.45 | AP6: 34.48 | AQ6: 457 | AR6: 0 | AS6: 0.104 | AT6: 0.408 | AU6: 0.612 | AV6: 0.918 | AW6: 1.224 | AX6: 1.53 | AY6: 533.281 | AZ6: 633.693 | BA6: =G6/H6 -> 0.13927181 | BB6: =Holdings!$P6 -> 480.27
A7: BAC | B7: Bank of America | C7: USD | D7: 1 | E7: 1 | F7: 4 | G7: 198.4 | H7: 1823.9 | I7: 0.1 | J7: 12.931 | K7: 348.54 | L7: -2.374 | M7: 505.799 | N7: -82.094 | O7: 2.5 | P7: 0 | Q7: 31.5 | R7: 6.1 | S7: 37.3 | T7: 31.5 | U7: 0 | V7: 0 | W7: =SUM(BDC_EAD!D$31:D$52)+SUM(BDC_EAD!D$81:D$102) -> 3.8291 | X7: =SUM(BDC_EAD!D$6:D$27)+SUM(BDC_EAD!D$56:D$77) -> 9.004882 | Y7: =MAX(0,Q7-W7) -> 27.6709 | Z7: =MAX(0,R7-(X7-W7)) -> 0.924218 | AA7: 0 | AB7: 0 | AC7: 49.867 | AD7: 0 | AE7: 4.55 | AF7: 83.31 | AG7: 684 | AH7: 1.12 | AI7: 899.7 | AJ7: 2025.124 | AK7: 59.979 | AL7: 332.218 | AM7: 0.17209185 | AN7: =AL7*AM7 -> 57.172009 | AO7: 27.98 | AP7: 7.87 | AQ7: 357 | AR7: 0 | AS7: 0.121 | AT7: 1.816 | AU7: 2.724 | AV7: 4.086 | AW7: 5.448 | AX7: 6.81 | AY7: 335.222 | AZ7: 200.993 | BA7: =G7/H7 -> 0.10877789 | BB7: =Holdings!$P7 -> 211.05
A8: C | B8: Citigroup | C8: USD | D8: 1 | E8: 1 | F8: 3 | G8: 157.4 | H8: 1231.9 | I8: 0.116 | J8: 10.551 | K8: 286.765 | L8: -1.084 | M8: 167.893 | N8: -10.369 | O8: 2.5 | P8: 0 | Q8: 51.4 | R8: 19.8 | S8: 9 | T8: 4.2 | U8: 10.6 | V8: 0 | W8: =SUM(BDC_EAD!E$31:E$52)+SUM(BDC_EAD!E$81:E$102) -> 2.388312 | X8: =SUM(BDC_EAD!E$6:E$27)+SUM(BDC_EAD!E$56:E$77) -> 5.348295 | Y8: =MAX(0,Q8-W8) -> 49.011688 | Z8: =MAX(0,R8-(X8-W8)) -> 16.840017 | AA8: 0 | AB8: 83.322 | AC8: 0 | AD8: 3 | AE8: 4.55 | AF8: 37.19 | AG8: 641.2 | AH8: 1.13 | AI8: 739.5 | AJ8: 1492.607 | AK8: 60.978 | AL8: 411.126 | AM8: 0.19404473 | AN8: =AL8*AM8 -> 79.776835 | AO8: 3.89 | AP8: 17.48 | AQ8: 163 | AR8: 0 | AS8: 0.2 | AT8: 0.4 | AU8: 0.6 | AV8: 0.9 | AW8: 1.2 | AX8: 1.5 | AY8: 297.956 | AZ8: 442.819 | BA8: =G8/H8 -> 0.12777011 | BB8: =Holdings!$P8 -> 198.5
A9: WFC | B9: Wells Fargo | C9: USD | D9: 1 | E9: 1 | F9: 3 | G9: 134.6 | H9: 1339.8 | I9: 0.085 | J9: 8.961 | K9: 250.326 | L9: -3.267 | M9: 198.573 | N9: -32.408 | O9: 2.5 | P9: 0 | Q9: 72 | R9: 36.2 | S9: 56.7 | T9: 27.6 | U9: 0 | V9: 0 | W9: =SUM(BDC_EAD!F$31:F$52)+SUM(BDC_EAD!F$81:F$102) -> 4.346347 | X9: =SUM(BDC_EAD!F$6:F$27)+SUM(BDC_EAD!F$56:F$77) -> 9.37608 | Y9: =MAX(0,Q9-W9) -> 67.653653 | Z9: =MAX(0,R9-(X9-W9)) -> 31.170267 | AA9: 0 | AB9: 0 | AC9: 0 | AD9: 2.6 | AE9: 4.55 | AF9: 126.02 | AG9: 414.24 | AH9: 1.19 | AI9: 786.2 | AJ9: 1501.405 | AK9: 25.168 | AL9: 251.804 | AM9: 0.19134785 | AN9: =AL9*AM9 -> 48.182155 | AO9: 12.67 | AP9: 17.2 | AQ9: 435.968 | AR9: 0 | AS9: 1.3666667 | AT9: 2.7333333 | AU9: 4.1 | AV9: 4.1 | AW9: 4.1 | AX9: 4.1 | AY9: 287.074 | AZ9: 163.988 | BA9: =G9/H9 -> 0.10046276 | BB9: =Holdings!$P9 -> 127.74
A10: GS | B10: Goldman Sachs | C10: USD | D10: 1 | E10: 1 | F10: 3 | G10: 101.4 | H10: 817 | I10: 0.114 | J10: 8.665 | K10: 155.636 | L10: -1 | M10: 74.658 | N10: -0.003 | O10: 2.5 | P10: 0 | Q10: 27.4 | R10: 15.5 | S10: 34.6 | T10: 14.6 | U10: 0 | V10: 0 | W10: =SUM(BDC_EAD!G$31:G$52)+SUM(BDC_EAD!G$81:G$102) -> 2.130358 | X10: =SUM(BDC_EAD!G$6:G$27)+SUM(BDC_EAD!G$56:G$77) -> 3.822584 | Y10: =MAX(0,Q10-W10) -> 25.269642 | Z10: =MAX(0,R10-(X10-W10)) -> 13.807774 | AA10: 0 | AB10: 145.84 | AC10: 0 | AD10: 0 | AE10: 4.55 | AF10: 40.31 | AG10: 454.349 | AH10: 1.26 | AI10: 214 | AJ10: 557.955 | AK10: 55.681 | AL10: 357.574 | AM10: 0.37173189 | AN10: =AL10*AM10 -> 132.92166 | AO10: 1.51 | AP10: 2.37 | AQ10: 379.39 | AR10: 0 | AS10: 0.165 | AT10: 1.778 | AU10: 2.667 | AV10: 4.0005 | AW10: 5.334 | AX10: 6.6675 | AY10: 400.09 | AZ10: 165.461 | BA10: =G10/H10 -> 0.12411261 | BB10: =Holdings!$P10 -> 366.97
A11: MS | B11: Morgan Stanley | C11: USD | D11: 1 | E11: 1 | F11: 4 | G11: 88.8 | H11: 595.8 | I11: 0.118 | J11: 7.446 | K11: 105.532 | L11: -2.229 | M11: 47.747 | N11: -7.509 | O11: 2.5 | P11: 0 | Q11: 20.9 | R11: 12.6 | S11: 12 | T11: 8.5 | U11: 0 | V11: 0 | W11: =SUM(BDC_EAD!H$31:H$52)+SUM(BDC_EAD!H$81:H$102) -> 2.651772 | X11: =SUM(BDC_EAD!H$6:H$27)+SUM(BDC_EAD!H$56:H$77) -> 5.792229 | Y11: =MAX(0,Q11-W11) -> 18.248228 | Z11: =MAX(0,R11-(X11-W11)) -> 9.459543 | AA11: 0 | AB11: 100.328 | AC11: 0 | AD11: 0 | AE11: 4.55 | AF11: 16.4 | AG11: 319.165 | AH11: 1.29 | AI11: 159.3 | AJ11: 446.068 | AK11: 9.4 | AL11: 152.757 | AM11: 0.45087003 | AN11: =AL11*AM11 -> 68.873553 | AO11: 0 | AP11: 0 | AQ11: 159.5825 | AR11: 0 | AS11: 0.427 | AT11: 0.875 | AU11: 1.3125 | AV11: 1.96875 | AW11: 2.625 | AX11: 3.28125 | AY11: 297.64 | AZ11: 120.379 | BA11: =G11/H11 -> 0.1490433 | BB11: =Holdings!$P11 -> 297.98
A12: PNC | B12: PNC | C12: USD | D12: 0 | E12: 0 | F12: 4 | G12: 49.1 | H12: 500.8 | I12: 0.07 | J12: 2.777 | K12: 71.1 | L12: -2.107 | M12: 78.406 | N12: -2.884 | O12: 2.5 | P12: 0 | Q12: 34.8 | R12: 15.6 | S12: 27.1 | T12: 18.9 | U12: 0 | V12: 0 | W12: =SUM(BDC_EAD!I$31:I$52)+SUM(BDC_EAD!I$81:I$102) -> 0.110746 | X12: =SUM(BDC_EAD!I$6:I$27)+SUM(BDC_EAD!I$56:I$77) -> 0.51562 | Y12: =MAX(0,Q12-W12) -> 34.689254 | Z12: =MAX(0,R12-(X12-W12)) -> 15.195126 | AA12: 0 | AB12: 0 | AC12: 0 | AD12: 0 | AE12: 0 | AF12: 47.15 | AG12: 104.7 | AH12: 1.1 | AI12: 204.9 | AJ12: 449.792 | AK12: 2.767 | AL12: 0 | AM12: 0.105 | AN12: =AL12*AM12 -> 0 | AO12: 0 | AP12: 0 | AQ12: 124.4 | AR12: 0 | AS12: 0.5 | AT12: 1 | AU12: 1.5 | AV12: 2 | AW12: 2 | AX12: 2 | AY12: 18.29316 | AZ12: 18.29316 | BA12: =G12/H12 -> 0.098043131 | BB12: =Holdings!$P12 -> 9.15
A13: USB | B13: U.S. Bancorp | C13: USD | D13: 0 | E13: 0 | F13: 4 | G13: 55 | H13: 508.2 | I13: 0.071 | J13: 3.258 | K13: 89.085 | L13: -4.444 | M13: 74.085 | N13: -9.463 | O13: 2.5 | P13: 0 | Q13: 14.2 | R13: 5.9 | S13: 14.4 | T13: 12.2 | U13: 0 | V13: 0 | W13: =SUM(BDC_EAD!J$31:J$52)+SUM(BDC_EAD!J$81:J$102) -> 0.359937 | X13: =SUM(BDC_EAD!J$6:J$27)+SUM(BDC_EAD!J$56:J$77) -> 1.475541 | Y13: =MAX(0,Q13-W13) -> 13.840063 | Z13: =MAX(0,R13-(X13-W13)) -> 4.784396 | AA13: 0 | AB13: 0 | AC13: 0 | AD13: 0 | AE13: 0 | AF13: 50.72 | AG13: 108.834 | AH13: 1.076 | AI13: 282.9 | AJ13: 532.066 | AK13: 37.337 | AL13: 8.77 | AM13: 0.105 | AN13: =AL13*AM13 -> 0.92085 | AO13: 0 | AP13: 1.06 | AQ13: 192.854 | AR13: 0 | AS13: 0.075 | AT13: 0.15 | AU13: 0.225 | AV13: 0.3 | AW13: 0.3 | AX13: 0.3 | AY13: 21.16665 | AZ13: 21.16665 | BA13: =G13/H13 -> 0.10822511 | BB13: =Holdings!$P13 -> 13.01
A14: TFC | B14: Truist | C14: USD | D14: 0 | E14: 0 | F14: 3 | G14: 46.3 | H14: 431.8 | I14: 0.07 | J14: 2.21 | K14: 67.651 | L14: -4.674 | M14: 46.351 | N14: -8.206 | O14: 2.5 | P14: 0 | Q14: 22.7 | R14: 19.1 | S14: 5.4 | T14: 4.3 | U14: 0 | V14: 0 | W14: =SUM(BDC_EAD!K$31:K$52)+SUM(BDC_EAD!K$81:K$102) -> 1.175366 | X14: =SUM(BDC_EAD!K$6:K$27)+SUM(BDC_EAD!K$56:K$77) -> 2.914783 | Y14: =MAX(0,Q14-W14) -> 21.524634 | Z14: =MAX(0,R14-(X14-W14)) -> 17.360583 | AA14: 0 | AB14: 0 | AC14: 0 | AD14: 0 | AE14: 0 | AF14: 51.02 | AG14: 92.8 | AH14: 1.13 | AI14: 188.3 | AJ14: 409.379 | AK14: 3.414 | AL14: 5.871 | AM14: 0.105 | AN14: =AL14*AM14 -> 0.616455 | AO14: 5.98 | AP14: 0.05 | AQ14: 108.495 | AR14: 0 | AS14: 0.0928 | AT14: 0.1856 | AU14: 0.2784 | AV14: 0.3712 | AW14: 0.464 | AX14: 0.5568 | AY14: 16.45038 | AZ14: 16.45038 | BA14: =G14/H14 -> 0.10722557 | BB14: =Holdings!$P14 -> 4.41
A15: STT | B15: State Street | C15: USD | D15: 1 | E15: 1 | F15: 5 | G15: 15.4 | H15: 140.6 | I15: 0.08 | J15: 1.389 | K15: 72.297 | L15: 0 | M15: 35.29 | N15: -4.186 | O15: 2.5 | P15: 0 | Q15: 22.3 | R15: 6.7 | S15: 10.7 | T15: 5.3 | U15: 0 | V15: 0 | W15: =SUM(BDC_EAD!L$31:L$52)+SUM(BDC_EAD!L$81:L$102) -> 0.586001 | X15: =SUM(BDC_EAD!L$6:L$27)+SUM(BDC_EAD!L$56:L$77) -> 1.995399 | Y15: =MAX(0,Q15-W15) -> 21.713999 | Z15: =MAX(0,R15-(X15-W15)) -> 5.290602 | AA15: 0 | AB15: 0 | AC15: 0 | AD15: 0 | AE15: 0 | AF15: 2.29 | AG15: 105.683 | AH15: 1.07 | AI15: 247.603 | AJ15: 319.547 | AK15: 4.372 | AL15: 0.395 | AM15: 0.14965543 | AN15: =AL15*AM15 -> 0.059113895 | AO15: 0 | AP15: 0 | AQ15: 82.79 | AR15: 0 | AS15: 0.33 | AT15: 0.66 | AU15: 0.99 | AV15: 1.32 | AW15: 1.65 | AX15: 1.65 | AY15: 103.682 | AZ15: 302.325 | BA15: =G15/H15 -> 0.10953058 | BB15: =Holdings!$P15 -> 16.07
A16: BK | B16: BNY | C16: USD | D16: 1 | E16: 1 | F16: 5 | G16: 21 | H16: 191.8 | I16: 0.085 | J16: 2.259 | K16: 107.4 | L16: -0.703 | M16: 48.239 | N16: -2.939 | O16: 2.5 | P16: 0 | Q16: 0.364 | R16: 0.385 | S16: 5.185 | T16: 3.227 | U16: 0 | V16: 0 | W16: =SUM(BDC_EAD!M$31:M$52)+SUM(BDC_EAD!M$81:M$102) -> 0.341158 | X16: =SUM(BDC_EAD!M$6:M$27)+SUM(BDC_EAD!M$56:M$77) -> 0.863781 | Y16: =MAX(0,Q16-W16) -> 0.022842 | Z16: =MAX(0,R16-(X16-W16)) -> 0 | AA16: 0 | AB16: 30.2 | AC16: 0 | AD16: 0 | AE16: 0 | AF16: 5.63 | AG16: 142 | AH16: 1.11 | AI16: 254.043 | AJ16: 370.541 | AK16: 5.217 | AL16: 26.114 | AM16: 0.16684227 | AN16: =AL16*AM16 -> 4.356919 | AO16: 0 | AP16: 0.7 | AQ16: 92 | AR16: 0 | AS16: 0.0198 | AT16: 0.0396 | AU16: 0.0594 | AV16: 0.0792 | AW16: 0.099 | AX16: 0.099 | AY16: 95.998 | AZ16: 379.653 | BA16: =G16/H16 -> 0.10948905 | BB16: =Holdings!$P16 -> 26.92
A17: FCNCA | B17: First Citizens | C17: USD | D17: 0 | E17: 0 | F17: 2 | G17: 19.885 | H17: 184.6 | I17: 0.07 | J17: 0.881 | K17: 33.983 | L17: -0.527 | M17: 9.418 | N17: -1.204 | O17: 2.5 | P17: 0 | Q17: 2.3 | R17: 1.4 | S17: 35 | T17: 13.6 | U17: 0 | V17: 0 | W17: =SUM(BDC_EAD!N$31:N$52)+SUM(BDC_EAD!N$81:N$102) -> 0.179924 | X17: =SUM(BDC_EAD!N$6:N$27)+SUM(BDC_EAD!N$56:N$77) -> 0.445406 | Y17: =MAX(0,Q17-W17) -> 2.120076 | Z17: =MAX(0,R17-(X17-W17)) -> 1.134518 | AA17: 0 | AB17: 0 | AC17: 0 | AD17: 0 | AE17: 0 | AF17: 38.81 | AG17: 59.14 | AH17: 1.1 | AI17: 65.06 | AJ17: 173.427 | AK17: 0 | AL17: 0.152 | AM17: 0.105 | AN17: =AL17*AM17 -> 0.01596 | AO17: 0 | AP17: 0 | AQ17: 30.52 | AR17: 0 | AS17: 0.05914 | AT17: 0.11828 | AU17: 0.17742 | AV17: 0.23656 | AW17: 0.2957 | AX17: 0.35484 | AY17: 7.08951 | AZ17: 7.08951 | BA17: =G17/H17 -> 0.10771939 | BB17: =Holdings!$P17 -> 0.16
A18: CFG | B18: Citizens | C18: USD | D18: 0 | E18: 0 | F18: 3 | G18: 18.7 | H18: 177.3 | I18: 0.09 | J18: 0.889 | K18: 37.448 | L18: -1.501 | M18: 7.638 | N18: -0.854 | O18: 2.5 | P18: 0 | Q18: 6.1 | R18: 3.6 | S18: 9.8 | T18: 9.8 | U18: 0 | V18: 0 | W18: =SUM(BDC_EAD!O$31:O$52)+SUM(BDC_EAD!O$81:O$102) -> 0.590632 | X18: =SUM(BDC_EAD!O$6:O$27)+SUM(BDC_EAD!O$56:O$77) -> 1.062374 | Y18: =MAX(0,Q18-W18) -> 5.509368 | Z18: =MAX(0,R18-(X18-W18)) -> 3.128258 | AA18: 0 | AB18: 0 | AC18: 0 | AD18: 0 | AE18: 0 | AF18: 26.95 | AG18: 51.3 | AH18: 1.1 | AI18: 89.617 | AJ18: 185.62 | AK18: 1.159 | AL18: 0 | AM18: 0.105 | AN18: =AL18*AM18 -> 0 | AO18: 0 | AP18: 0 | AQ18: 78.3 | AR18: 0 | AS18: 0.0513 | AT18: 0.1026 | AU18: 0.1539 | AV18: 0.2052 | AW18: 0.2565 | AX18: 0.3078 | AY18: 6.97551 | AZ18: 6.97551 | BA18: =G18/H18 -> 0.10547095 | BB18: =Holdings!$P18 -> 0.73
A19: BARC | B19: Barclays | C19: GBP | D19: 1 | E19: 1 | F19: 3 | G19: 69.21198 | H19: 483.68832 | I19: 0.122 | J19: 5.0689157 | K19: 109.68 | L19: 0 | M19: 109.68 | N19: 0 | O19: 1 | P19: 0 | Q19: 21.2144 | R19: 6.6295 | S19: 5.3036 | T19: 0 | U19: 26.518 | V19: 26.38541 | W19: =SUM(BDC_EAD!P$31:P$52)+SUM(BDC_EAD!P$81:P$102) -> 1.249667 | X19: =SUM(BDC_EAD!P$6:P$27)+SUM(BDC_EAD!P$56:P$77) -> 2.387078 | Y19: =MAX(0,Q19-W19) -> 19.964733 | Z19: =MAX(0,R19-(X19-W19)) -> 5.492089 | AA19: 70 | AB19: 114.15999 | AC19: 0 | AD19: 0 | AE19: 0 | AF19: 29.36 | AG19: 425.87908 | AH19: 1.577 | AI19: 354.62608 | AJ19: 788.05795 | AK19: 103.81797 | AL19: 243.46441 | AM19: 0.50431599 | AN19: =AL19*AM19 -> 122.783 | AO19: 30.26 | AP19: 2.82 | AQ19: 459.68953 | AR19: 0 | AS19: 1.3259 | AT19: 3.9777 | AU19: 5.96655 | AV19: 8.949825 | AW19: 11.9331 | AX19: 14.916375 | AY19: 249.38898 | AZ19: 267.2456 | BA19: =G19/H19 -> 0.14309211 | BB19: =Holdings!$P19 -> 223.18
A20: HSBA | B20: HSBC | C20: USD | D20: 1 | E20: 1 | F20: 4 | G20: 127.7 | H20: 906.4 | I20: 0.112 | J20: 10.4 | K20: 247.365 | L20: -2.4 | M20: 247.365 | N20: -2.1 | O20: 1 | P20: 0 | Q20: 16 | R20: 6 | S20: 25 | T20: 0 | U20: 21.7 | V20: 0 | W20: =SUM(BDC_EAD!Q$31:Q$52)+SUM(BDC_EAD!Q$81:Q$102) -> 0.702337 | X20: =SUM(BDC_EAD!Q$6:Q$27)+SUM(BDC_EAD!Q$56:Q$77) -> 2.011166 | Y20: =MAX(0,Q20-W20) -> 15.297663 | Z20: =MAX(0,R20-(X20-W20)) -> 4.691171 | AA20: 0 | AB20: 0 | AC20: 0 | AD20: 0 | AE20: 0 | AF20: 67.74 | AG20: 713.669 | AH20: 1.34 | AI20: 950.01 | AJ20: 1919.104 | AK20: 0 | AL20: 276.266 | AM20: 0.39857768 | AN20: =AL20*AM20 -> 110.11346 | AO20: 0 | AP20: 2.12 | AQ20: 356.8345 | AR20: 0 | AS20: 0.06 | AT20: 0.12 | AU20: 0.18 | AV20: 0.27 | AW20: 0.36 | AX20: 0.45 | AY20: 335.546 | AZ20: 314.53321 | BA20: =G20/H20 -> 0.14088703 | BB20: =Holdings!$P20 -> 327.87
A21: DBK | B21: Deutsche Bank | C21: EUR | D21: 1 | E21: 1 | F21: 5 | G21: 58.339728 | H21: 419.23224 | I21: 0.112 | J21: 3.5837963 | K21: 86.84 | L21: 0 | M21: 86.84 | N21: 0 | O21: 1 | P21: 0 | Q21: 29.57003 | R21: 8.871009 | S21: 0 | T21: 0 | U21: 34.251 | V21: 0 | W21: =SUM(BDC_EAD!R$31:R$52)+SUM(BDC_EAD!R$81:R$102) -> 2.834584 | X21: =SUM(BDC_EAD!R$6:R$27)+SUM(BDC_EAD!R$56:R$77) -> 5.561722 | Y21: =MAX(0,Q21-W21) -> 26.735446 | Z21: =MAX(0,R21-(X21-W21)) -> 6.143871 | AA21: 77.5 | AB21: 0 | AC21: 0 | AD21: 0 | AE21: 0 | AF21: 47.66 | AG21: 281.39366 | AH21: 1.4 | AI21: 297.18337 | AJ21: 797.1201 | AK21: 28.371245 | AL21: 103.15945 | AM21: 0.33448289 | AN21: =AL21*AM21 -> 34.505069 | AO21: 5.15 | AP21: 0 | AQ21: 140.69683 | AR21: 0 | AS21: 0.1838137 | AT21: 0.2420404 | AU21: 0.3630606 | AV21: 0.5445909 | AW21: 0.7261212 | AX21: 0.9076515 | AY21: 142.51526 | AZ21: 153.83927 | BA21: =G21/H21 -> 0.1391585 | BB21: =Holdings!$P21 -> 87.29
A22: BNP | B22: BNP Paribas | C22: EUR | D22: 1 | E22: 1 | F22: 6 | G22: 117.82344 | H22: 907.6515 | I22: 0.1043 | J22: 6.9700785 | K22: 176.25 | L22: 0 | M22: 176.25 | N22: 0 | O22: 1 | P22: 0 | Q22: 25.1174 | R22: 7.53522 | S22: 0 | T22: 0 | U22: 10.04696 | V22: 3.014088 | W22: =SUM(BDC_EAD!S$31:S$52)+SUM(BDC_EAD!S$81:S$102) -> 3.627251 | X22: =SUM(BDC_EAD!S$6:S$27)+SUM(BDC_EAD!S$56:S$77) -> 9.468492 | Y22: =MAX(0,Q22-W22) -> 21.490149 | Z22: =MAX(0,R22-(X22-W22)) -> 1.693979 | AA22: 90 | AB22: 0 | AC22: 0 | AD22: 0 | AE22: 0 | AF22: 85.23 | AG22: 490.931 | AH22: 1.49 | AI22: 581.39702 | AJ22: 1423.411 | AK22: 28.375812 | AL22: 503.10495 | AM22: 0.50000709 | AN22: =AL22*AM22 -> 251.55604 | AO22: 6.01 | AP22: 19.32 | AQ22: 594.8257 | AR22: 0 | AS22: 0.490931 | AT22: 0.981862 | AU22: 1.472793 | AV22: 1.963724 | AW22: 2.454655 | AX22: 2.945586 | AY22: 446.99608 | AZ22: 292.86383 | BA22: =G22/H22 -> 0.12981132 | BB22: =Holdings!$P22 -> 352.51
A23: GLE | B23: Societe Generale | C23: EUR | D23: 1 | E23: 1 | F23: 5 | G23: 61.08095 | H23: 463.5302 | I23: 0.1026 | J23: 3.3577397 | K23: 71.865 | L23: 0 | M23: 71.865 | N23: 0 | O23: 1 | P23: 0 | Q23: 12.5587 | R23: 3.76761 | S23: 3.4251 | T23: 0 | U23: 0 | V23: 0 | W23: =SUM(BDC_EAD!T$31:T$52)+SUM(BDC_EAD!T$81:T$102) -> 2.87833 | X23: =SUM(BDC_EAD!T$6:T$27)+SUM(BDC_EAD!T$56:T$77) -> 6.657164 | Y23: =MAX(0,Q23-W23) -> 9.68037 | Z23: =MAX(0,R23-(X23-W23)) -> 0 | AA23: 0 | AB23: 0 | AC23: 0 | AD23: 0 | AE23: 0 | AF23: 32.46 | AG23: 300.2671 | AH23: 1.46 | AI23: 275.14274 | AJ23: 611.4283 | AK23: 0 | AL23: 185.3824 | AM23: 0.53237246 | AN23: =AL23*AM23 -> 98.692483 | AO23: 3.8 | AP23: 9.76 | AQ23: 363.0606 | AR23: 0 | AS23: 0.3002671 | AT23: 0.6005342 | AU23: 0.9008013 | AV23: 1.2010684 | AW23: 1.5013355 | AX23: 1.8016026 | AY23: 298.46974 | AZ23: 265.24883 | BA23: =G23/H23 -> 0.1317734 | BB23: =Holdings!$P23 -> 163.63
A24: UBS | B24: UBS | C24: USD | D24: 1 | E24: 1 | F24: 4 | G24: 72.464 | H24: 503.9 | I24: 0.1083 | J24: 3.714 | K24: 30.925 | L24: 0 | M24: 30.925 | N24: 0 | O24: 1 | P24: 0 | Q24: 0 | R24: 0 | S24: 0 | T24: 0 | U24: 0 | V24: 0 | W24: =SUM(BDC_EAD!U$31:U$52)+SUM(BDC_EAD!U$81:U$102) -> 0.023394 | X24: =SUM(BDC_EAD!U$6:U$27)+SUM(BDC_EAD!U$56:U$77) -> 0.12931 | Y24: =MAX(0,Q24-W24) -> 0 | Z24: =MAX(0,R24-(X24-W24)) -> 0 | AA24: 0 | AB24: 0 | AC24: 0 | AD24: 0 | AE24: 0 | AF24: 93.13 | AG24: 341.8 | AH24: 1.773 | AI24: 365.4855 | AJ24: 812.19 | AK24: 44.031 | AL24: 20.449 | AM24: 0.8 | AN24: =AL24*AM24 -> 16.3592 | AO24: 6.29 | AP24: 0.3 | AQ24: 170.9 | AR24: 0 | AS24: 0.3418 | AT24: 0.6836 | AU24: 1.0254 | AV24: 1.3672 | AW24: 1.709 | AX24: 2.0508 | AY24: 325.18089 | AZ24: 467.59331 | BA24: =G24/H24 -> 0.14380631 | BB24: =Holdings!$P24 -> 255.77
A25: MUFG | B25: MUFG | C25: JPY | D25: 1 | E25: 1 | F25: 4 | G25: 99.637784 | H25: 768.83771 | I25: 0.0869 | J25: 5.0113769 | K25: 229.915 | L25: -2.873132 | M25: 229.915 | N25: -7.7301519 | O25: 1 | P25: 26.136074 | Q25: 26.443638 | R25: 13.221819 | S25: 26.443638 | T25: 13.221819 | U25: 0 | V25: 0 | W25: =SUM(BDC_EAD!V$31:V$52)+SUM(BDC_EAD!V$81:V$102) -> 2.817403 | X25: =SUM(BDC_EAD!V$6:V$27)+SUM(BDC_EAD!V$56:V$77) -> 6.21229 | Y25: =MAX(0,Q25-W25) -> 23.626235 | Z25: =MAX(0,R25-(X25-W25)) -> 9.8269321 | AA25: 0 | AB25: 0 | AC25: 0 | AD25: 0 | AE25: 0 | AF25: 95.94 | AG25: 759.07233 | AH25: 1.404 | AI25: 760.7536 | AJ25: 1603.5628 | AK25: 111.41472 | AL25: 250.71151 | AM25: 0.23327164 | AN25: =AL25*AM25 -> 58.483885 | AO25: 32.9 | AP25: 2.79 | AQ25: 379.53617 | AR25: 0 | AS25: 0.20447697 | AT25: 0.40895394 | AU25: 0.61343091 | AV25: 0.81790788 | AW25: 0.81790788 | AX25: 0.81790788 | AY25: 336.47062 | AZ25: 227.19185 | BA25: =G25/H25 -> 0.12959534 | BB25: =Holdings!$P25 -> 139.9
A26: SMFG | B26: SMFG | C26: JPY | D26: 1 | E26: 1 | F26: 4 | G26: 79.337931 | H26: 628.05609 | I26: 0.0817 | J26: 4.4419162 | K26: 100.925 | L26: -1.9623639 | M26: 100.925 | N26: -1.65119 | O26: 1 | P26: 24.684171 | Q26: 8.3635693 | R26: 2.0908923 | S26: 8.3635693 | T26: 2.0908923 | U26: 0 | V26: 0 | W26: =SUM(BDC_EAD!W$31:W$52)+SUM(BDC_EAD!W$81:W$102) -> 1.537808 | X26: =SUM(BDC_EAD!W$6:W$27)+SUM(BDC_EAD!W$56:W$77) -> 4.668771 | Y26: =MAX(0,Q26-W26) -> 6.8257613 | Z26: =MAX(0,R26-(X26-W26)) -> 0 | AA26: 0 | AB26: 0 | AC26: 0 | AD26: 0 | AE26: 0 | AF26: 43.5 | AG26: 597.48935 | AH26: 1.383 | AI26: 579.37209 | AJ26: 1241.8082 | AK26: 142.21343 | AL26: 148.67816 | AM26: 0.15706172 | AN26: =AL26*AM26 -> 23.351648 | AO26: 24.02 | AP26: 0.78 | AQ26: 298.74467 | AR26: 0 | AS26: 0.59748935 | AT26: 1.1949787 | AU26: 1.792468 | AV26: 2.3899574 | AW26: 2.9874467 | AX26: 3.5849361 | AY26: 385.17425 | AZ26: 154.78467 | BA26: =G26/H26 -> 0.126323 | BB26: =Holdings!$P26 -> 37.61
A27: MFG | B27: Mizuho | C27: JPY | D27: 1 | E27: 1 | F27: 4 | G27: 68.322981 | H27: 505.58822 | I27: 0.0813 | J27: 3.2740914 | K27: 85.305 | L27: 0 | M27: 85.305 | N27: -0.91138306 | O27: 1 | P27: 18.386938 | Q27: 7.3333333 | R27: 3.6666667 | S27: 14.666667 | T27: 7.3333333 | U27: 0 | V27: 0 | W27: =SUM(BDC_EAD!X$31:X$52)+SUM(BDC_EAD!X$81:X$102) -> 0.411154 | X27: =SUM(BDC_EAD!X$6:X$27)+SUM(BDC_EAD!X$56:X$77) -> 1.469927 | Y27: =MAX(0,Q27-W27) -> 6.9221793 | Z27: =MAX(0,R27-(X27-W27)) -> 2.6078937 | AA27: 0 | AB27: 0 | AC27: 0 | AD27: 0 | AE27: 0 | AF27: 0 | AG27: 503.44704 | AH27: 1.261 | AI27: 556.83606 | AJ27: 1101.0295 | AK27: 37.602503 | AL27: 244.75177 | AM27: 0.22397089 | AN27: =AL27*AM27 -> 54.817273 | AO27: 15.5 | AP27: 7.29 | AQ27: 251.72352 | AR27: 0 | AS27: 0.58421991 | AT27: 1.1684398 | AU27: 1.7526597 | AV27: 2.3368797 | AW27: 2.3368797 | AX27: 2.3368797 | AY27: 116.0015 | AZ27: 130.77673 | BA27: =G27/H27 -> 0.13513563 | BB27: =Holdings!$P27 -> 49.24
A28: RY | B28: RBC | C28: CAD | D28: 1 | E28: 1 | F28: 5 | G28: 73.88666 | H28: 547.69447 | I28: 0.111 | J28: 6.1590989 | K28: 158.98 | L28: -0.22527279 | M28: 158.98 | N28: -2.2379444 | O28: 1 | P28: 0 | Q28: 10.770855 | R28: 0 | S28: 0 | T28: 0 | U28: 23.935234 | V28: 0 | W28: =SUM(BDC_EAD!Y$31:Y$52)+SUM(BDC_EAD!Y$81:Y$102) -> 1.193217 | X28: =SUM(BDC_EAD!Y$6:Y$27)+SUM(BDC_EAD!Y$56:Y$77) -> 3.950015 | Y28: =MAX(0,Q28-W28) -> 9.5776383 | Z28: =MAX(0,R28-(X28-W28)) -> 0 | AA28: 0 | AB28: 0 | AC28: 0 | AD28: 0 | AE28: 0 | AF28: 78.23 | AG28: 342.73214 | AH28: 1.25 | AI28: 381.63393 | AJ28: 1157.7423 | AK28: 111.12284 | AL28: 228.92291 | AM28: 0.29868984 | AN28: =AL28*AM28 -> 68.376949 | AO28: 38.53 | AP28: 2.13 | AQ28: 440.38508 | AR28: 0 | AS28: 0.29567054 | AT28: 0.45406547 | AU28: 0.71312918 | AV28: 1.0696938 | AW28: 1.4262584 | AX28: 1.7828229 | AY28: 138.14253 | AZ28: 111.7711 | BA28: =G28/H28 -> 0.13490488 | BB28: =Holdings!$P28 -> 135.42
A29: JEF | B29: Jefferies | C29: USD | D29: 0 | E29: 1 | F29: 2 | G29: 8.718 | H29: 96.866667 | I29: 0.0675 | J29: 0.351 | K29: 0 | L29: 0 | M29: 0 | N29: 0 | O29: 0 | P29: 0 | Q29: 0 | R29: 0 | S29: 0 | T29: 0 | U29: 0 | V29: 0 | W29: =SUM(BDC_EAD!Z$31:Z$52)+SUM(BDC_EAD!Z$81:Z$102) -> 0 | X29: =SUM(BDC_EAD!Z$6:Z$27)+SUM(BDC_EAD!Z$56:Z$77) -> 0 | Y29: =MAX(0,Q29-W29) -> 0 | Z29: =MAX(0,R29-(X29-W29)) -> 0 | AA29: 0 | AB29: 0 | AC29: 0 | AD29: 0 | AE29: 0 | AF29: 0 | AG29: 17.238 | AH29: 1 | AI29: 0 | AJ29: 0 | AK29: 1.603 | AL29: 16.734 | AM29: 0.72828685 | AN29: =AL29*AM29 -> 12.187152 | AO29: 0 | AP29: 0 | AQ29: 3.61 | AR29: 0 | AS29: 0.44985 | AT29: 0.8997 | AU29: 0.8997 | AV29: 0.8997 | AW29: 0.8997 | AX29: 0.8997 | AY29: 12.225 | AZ29: 12.225 | BA29: =G29/H29 -> 0.09 | BB29: =Holdings!$P29 -> 18.28

Sheet Holdings
A1: Holdings by asset class (USD bn) and fire-sale parameters
A2: Rows 31-39: price-impact lambda (bp of price per $bn sold, before dealer multiplier), capital-relevant net fraction, saleable flag, discount cap, fundamental price decline (scenario), non-bank seller allocation, panic discount at full panic (S = 1; correlation-to-1 repricing of every risky class).
A5: Id | B5: Institution | C5: UST | D5: AGENCY_MBS | E5: OTHER_SOV | F5: MUNI | G5: IG_CORP | H5: HY_CORP | I5: LEV_LOANS | J5: CLO | K5: ABS_OTHER | L5: PRIV_CREDIT_LOANS | M5: EQUITIES | N5: CRE_LOANS | O5: OTHER | P5: Saleable total | Q5: w UST | R5: w AGENCY_MBS | S5: w OTHER_SOV | T5: w MUNI | U5: w IG_CORP | V5: w HY_CORP | W5: w LEV_LOANS | X5: w CLO | Y5: w ABS_OTHER | Z5: w PRIV_CREDIT_LOANS | AA5: w EQUITIES | AB5: w CRE_LOANS | AC5: w OTHER
A6: JPM | B6: JPMorgan | C6: 726.55 | D6: 349.32 | E6: 242.69 | F6: 34 | G6: 55.56 | H6: 0 | I6: 14.24 | J6: 44.03 | K6: 33.98 | L6: 0 | M6: 267.07 | N6: 180.31 | O6: 31.39 | P6: =SUMPRODUCT(C6:O6,$C$33:$O$33) -> 480.27 | Q6: =IF($P6>0,C6*C$33/$P6,0) -> 0 | R6: =IF($P6>0,D6*D$33/$P6,0) -> 0 | S6: =IF($P6>0,E6*E$33/$P6,0) -> 0 | T6: =IF($P6>0,F6*F$33/$P6,0) -> 0.070793512 | U6: =IF($P6>0,G6*G$33/$P6,0) -> 0.11568493 | V6: =IF($P6>0,H6*H$33/$P6,0) -> 0 | W6: =IF($P6>0,I6*I$33/$P6,0) -> 0.029649989 | X6: =IF($P6>0,J6*J$33/$P6,0) -> 0.091677598 | ... AC6: =IF($P6>0,O6*O$33/$P6,0) -> 0.065359069
A7: BAC | B7: Bank of America | C7: 375.38 | D7: 528.24 | E7: 111.71 | F7: 14.32 | G7: 45.65 | H7: 0 | I7: 6.9 | J7: 8.75 | K7: 14.76 | L7: 0 | M7: 120.67 | N7: 83.31 | O7: 0 | P7: =SUMPRODUCT(C7:O7,$C$33:$O$33) -> 211.05 | Q7: =IF($P7>0,C7*C$33/$P7,0) -> 0 | R7: =IF($P7>0,D7*D$33/$P7,0) -> 0 | S7: =IF($P7>0,E7*E$33/$P7,0) -> 0 | T7: =IF($P7>0,F7*F$33/$P7,0) -> 0.06785122 | U7: =IF($P7>0,G7*G$33/$P7,0) -> 0.21629946 | V7: =IF($P7>0,H7*H$33/$P7,0) -> 0 | W7: =IF($P7>0,I7*I$33/$P7,0) -> 0.032693674 | X7: =IF($P7>0,J7*J$33/$P7,0) -> 0.04145937 | ... AC7: =IF($P7>0,O7*O$33/$P7,0) -> 0
A8: C | B8: Citigroup | C8: 280.64 | D8: 221.97 | E8: 321.85 | F8: 9.97 | G8: 31.57 | H8: 0 | I8: 1.45 | J8: 18.23 | K8: 8.48 | L8: 0 | M8: 97.93 | N8: 37.19 | O8: 30.87 | P8: =SUMPRODUCT(C8:O8,$C$33:$O$33) -> 198.5 | Q8: =IF($P8>0,C8*C$33/$P8,0) -> 0 | R8: =IF($P8>0,D8*D$33/$P8,0) -> 0 | S8: =IF($P8>0,E8*E$33/$P8,0) -> 0 | T8: =IF($P8>0,F8*F$33/$P8,0) -> 0.0502267 | U8: =IF($P8>0,G8*G$33/$P8,0) -> 0.15904282 | V8: =IF($P8>0,H8*H$33/$P8,0) -> 0 | W8: =IF($P8>0,I8*I$33/$P8,0) -> 0.0073047859 | X8: =IF($P8>0,J8*J$33/$P8,0) -> 0.091838791 | ... AC8: =IF($P8>0,O8*O$33/$P8,0) -> 0.15551637
A9: WFC | B9: Wells Fargo | C9: 148.35 | D9: 391.16 | E9: 0.33 | F9: 29.87 | G9: 17.09 | H9: 0 | I9: 5.03 | J9: 13.21 | K9: 5.26 | L9: 0 | M9: 37.96 | N9: 126.02 | O9: 19.32 | P9: =SUMPRODUCT(C9:O9,$C$33:$O$33) -> 127.74 | Q9: =IF($P9>0,C9*C$33/$P9,0) -> 0 | R9: =IF($P9>0,D9*D$33/$P9,0) -> 0 | S9: =IF($P9>0,E9*E$33/$P9,0) -> 0 | T9: =IF($P9>0,F9*F$33/$P9,0) -> 0.23383435 | U9: =IF($P9>0,G9*G$33/$P9,0) -> 0.13378738 | V9: =IF($P9>0,H9*H$33/$P9,0) -> 0 | W9: =IF($P9>0,I9*I$33/$P9,0) -> 0.039376859 | X9: =IF($P9>0,J9*J$33/$P9,0) -> 0.10341318 | ... AC9: =IF($P9>0,O9*O$33/$P9,0) -> 0.15124472
A10: GS | B10: Goldman Sachs | C10: 392.14 | D10: 76.82 | E10: 151.26 | F10: 0.89 | G10: 67.92 | H10: 0 | I10: 23.81 | J10: 0 | K10: 23.07 | L10: 0 | M10: 247.17 | N10: 40.31 | O10: 4.11 | P10: =SUMPRODUCT(C10:O10,$C$33:$O$33) -> 366.97 | Q10: =IF($P10>0,C10*C$33/$P10,0) -> 0 | R10: =IF($P10>0,D10*D$33/$P10,0) -> 0 | S10: =IF($P10>0,E10*E$33/$P10,0) -> 0 | T10: =IF($P10>0,F10*F$33/$P10,0) -> 0.0024252664 | U10: =IF($P10>0,G10*G$33/$P10,0) -> 0.18508325 | V10: =IF($P10>0,H10*H$33/$P10,0) -> 0 | W10: =IF($P10>0,I10*I$33/$P10,0) -> 0.064882688 | X10: =IF($P10>0,J10*J$33/$P10,0) -> 0 | ... AC10: =IF($P10>0,O10*O$33/$P10,0) -> 0.011199826
A11: MS | B11: Morgan Stanley | C11: 161.79 | D11: 136.84 | E11: 64.29 | F11: 6.51 | G11: 46.68 | H11: 0 | I11: 24.16 | J11: 0 | K11: 5.23 | L11: 0 | M11: 211.99 | N11: 16.4 | O11: 3.41 | P11: =SUMPRODUCT(C11:O11,$C$33:$O$33) -> 297.98 | Q11: =IF($P11>0,C11*C$33/$P11,0) -> 0 | R11: =IF($P11>0,D11*D$33/$P11,0) -> 0 | S11: =IF($P11>0,E11*E$33/$P11,0) -> 0 | T11: =IF($P11>0,F11*F$33/$P11,0) -> 0.021847104 | U11: =IF($P11>0,G11*G$33/$P11,0) -> 0.15665481 | V11: =IF($P11>0,H11*H$33/$P11,0) -> 0 | W11: =IF($P11>0,I11*I$33/$P11,0) -> 0.081079267 | X11: =IF($P11>0,J11*J$33/$P11,0) -> 0 | ... AC11: =IF($P11>0,O11*O$33/$P11,0) -> 0.011443721
A12: PNC | B12: PNC | C12: 46.42 | D12: 96.53 | E12: 0.06 | F12: 2.37 | G12: 2.02 | H12: 0 | I12: 0.02 | J12: 0.06 | K12: 4.68 | L12: 0 | M12: 0 | N12: 47.15 | O12: 0 | P12: =SUMPRODUCT(C12:O12,$C$33:$O$33) -> 9.15 | Q12: =IF($P12>0,C12*C$33/$P12,0) -> 0 | R12: =IF($P12>0,D12*D$33/$P12,0) -> 0 | S12: =IF($P12>0,E12*E$33/$P12,0) -> 0 | T12: =IF($P12>0,F12*F$33/$P12,0) -> 0.25901639 | U12: =IF($P12>0,G12*G$33/$P12,0) -> 0.22076503 | V12: =IF($P12>0,H12*H$33/$P12,0) -> 0 | W12: =IF($P12>0,I12*I$33/$P12,0) -> 0.0021857923 | X12: =IF($P12>0,J12*J$33/$P12,0) -> 0.006557377 | ... AC12: =IF($P12>0,O12*O$33/$P12,0) -> 0
A13: USB | B13: U.S. Bancorp | C13: 24.09 | D13: 125.09 | E13: 0.42 | F13: 7.38 | G13: 0 | H13: 0 | I13: 0.09 | J13: 4.38 | K13: 1.16 | L13: 0 | M13: 0 | N13: 50.72 | O13: 0 | P13: =SUMPRODUCT(C13:O13,$C$33:$O$33) -> 13.01 | Q13: =IF($P13>0,C13*C$33/$P13,0) -> 0 | R13: =IF($P13>0,D13*D$33/$P13,0) -> 0 | S13: =IF($P13>0,E13*E$33/$P13,0) -> 0 | T13: =IF($P13>0,F13*F$33/$P13,0) -> 0.56725596 | U13: =IF($P13>0,G13*G$33/$P13,0) -> 0 | V13: =IF($P13>0,H13*H$33/$P13,0) -> 0 | W13: =IF($P13>0,I13*I$33/$P13,0) -> 0.0069177556 | X13: =IF($P13>0,J13*J$33/$P13,0) -> 0.3366641 | ... AC13: =IF($P13>0,O13*O$33/$P13,0) -> 0
A14: TFC | B14: Truist | C14: 13.12 | D14: 99.11 | E14: 0 | F14: 0.34 | G14: 0 | H14: 0 | I14: 0.17 | J14: 0 | K14: 1.28 | L14: 0 | M14: 0 | N14: 51.02 | O14: 2.62 | P14: =SUMPRODUCT(C14:O14,$C$33:$O$33) -> 4.41 | Q14: =IF($P14>0,C14*C$33/$P14,0) -> 0 | R14: =IF($P14>0,D14*D$33/$P14,0) -> 0 | S14: =IF($P14>0,E14*E$33/$P14,0) -> 0 | T14: =IF($P14>0,F14*F$33/$P14,0) -> 0.077097506 | U14: =IF($P14>0,G14*G$33/$P14,0) -> 0 | V14: =IF($P14>0,H14*H$33/$P14,0) -> 0 | W14: =IF($P14>0,I14*I$33/$P14,0) -> 0.038548753 | X14: =IF($P14>0,J14*J$33/$P14,0) -> 0 | ... AC14: =IF($P14>0,O14*O$33/$P14,0) -> 0.59410431
A15: STT | B15: State Street | C15: 24.3 | D15: 43.05 | E15: 23.96 | F15: 0.03 | G15: 0.12 | H15: 0 | I15: 0 | J15: 4.01 | K15: 11.79 | L15: 0 | M15: 0 | N15: 2.29 | O15: 0.12 | P15: =SUMPRODUCT(C15:O15,$C$33:$O$33) -> 16.07 | Q15: =IF($P15>0,C15*C$33/$P15,0) -> 0 | R15: =IF($P15>0,D15*D$33/$P15,0) -> 0 | S15: =IF($P15>0,E15*E$33/$P15,0) -> 0 | T15: =IF($P15>0,F15*F$33/$P15,0) -> 0.0018668326 | U15: =IF($P15>0,G15*G$33/$P15,0) -> 0.0074673304 | V15: =IF($P15>0,H15*H$33/$P15,0) -> 0 | W15: =IF($P15>0,I15*I$33/$P15,0) -> 0 | X15: =IF($P15>0,J15*J$33/$P15,0) -> 0.24953329 | ... AC15: =IF($P15>0,O15*O$33/$P15,0) -> 0.0074673304
A16: BK | B16: BNY | C16: 36.02 | D16: 65.47 | E16: 32.94 | F16: 0.01 | G16: 8.57 | H16: 0 | I16: 0 | J16: 8.85 | K16: 3.8 | L16: 0 | M16: 0 | N16: 5.63 | O16: 5.69 | P16: =SUMPRODUCT(C16:O16,$C$33:$O$33) -> 26.92 | Q16: =IF($P16>0,C16*C$33/$P16,0) -> 0 | R16: =IF($P16>0,D16*D$33/$P16,0) -> 0 | S16: =IF($P16>0,E16*E$33/$P16,0) -> 0 | T16: =IF($P16>0,F16*F$33/$P16,0) -> 0.00037147103 | U16: =IF($P16>0,G16*G$33/$P16,0) -> 0.31835067 | V16: =IF($P16>0,H16*H$33/$P16,0) -> 0 | W16: =IF($P16>0,I16*I$33/$P16,0) -> 0 | X16: =IF($P16>0,J16*J$33/$P16,0) -> 0.32875186 | ... AC16: =IF($P16>0,O16*O$33/$P16,0) -> 0.21136701
A17: FCNCA | B17: First Citizens | C17: 13.71 | D17: 29.29 | E17: 0.25 | F17: 0.01 | G17: 0.13 | H17: 0 | I17: 0 | J17: 0 | K17: 0.02 | L17: 0 | M17: 0 | N17: 38.81 | O17: 0 | P17: =SUMPRODUCT(C17:O17,$C$33:$O$33) -> 0.16 | Q17: =IF($P17>0,C17*C$33/$P17,0) -> 0 | R17: =IF($P17>0,D17*D$33/$P17,0) -> 0 | S17: =IF($P17>0,E17*E$33/$P17,0) -> 0 | T17: =IF($P17>0,F17*F$33/$P17,0) -> 0.0625 | U17: =IF($P17>0,G17*G$33/$P17,0) -> 0.8125 | V17: =IF($P17>0,H17*H$33/$P17,0) -> 0 | W17: =IF($P17>0,I17*I$33/$P17,0) -> 0 | X17: =IF($P17>0,J17*J$33/$P17,0) -> 0 | ... AC17: =IF($P17>0,O17*O$33/$P17,0) -> 0
... A29: JEF | B29: Jefferies | C29: 3.11 | D29: 2.02 | E29: 1.69 | F29: 0.65 | G29: 5.27 | H29: 0 | I29: 1.83 | J29: 0.71 | K29: 0.98 | L29: 0 | M29: 8.66 | N29: 0 | O29: 0.18 | P29: =SUMPRODUCT(C29:O29,$C$33:$O$33) -> 18.28 | Q29: =IF($P29>0,C29*C$33/$P29,0) -> 0 | R29: =IF($P29>0,D29*D$33/$P29,0) -> 0 | S29: =IF($P29>0,E29*E$33/$P29,0) -> 0 | T29: =IF($P29>0,F29*F$33/$P29,0) -> 0.035557987 | U29: =IF($P29>0,G29*G$33/$P29,0) -> 0.28829322 | V29: =IF($P29>0,H29*H$33/$P29,0) -> 0 | W29: =IF($P29>0,I29*I$33/$P29,0) -> 0.10010941 | X29: =IF($P29>0,J29*J$33/$P29,0) -> 0.038840263 | ... AC29: =IF($P29>0,O29*O$33/$P29,0) -> 0.0098468271
B31: Lambda (bp per $bn) | C31: 0.02 | D31: 0.06 | E31: 0.3 | F31: 0.25 | G31: 0.75 | H31: 1.5 | I31: 3 | J31: 3 | K31: 1.5 | L31: 3 | M31: 0.05 | N31: 3 | O31: 1
B32: Net fraction hitting capital | C32: 0.1 | D32: 0.1 | E32: 0.1 | F32: 0.25 | G32: 0.25 | H32: 0.5 | I32: 1 | J32: 0.5 | K32: 0.5 | L32: 0 | M32: 0.02 | N32: 0 | O32: 0.1
B33: Saleable (1/0) | C33: 0 | D33: 0 | E33: 0 | F33: 1 | G33: 1 | H33: 1 | I33: 1 | J33: 1 | K33: 1 | L33: 0 | M33: 1 | N33: 0 | O33: 1
B34: Cap on fire-sale discount | C34: 0.05 | D34: 0.05 | E34: 0.1 | F34: 0.2 | G34: 0.25 | H34: 0.35 | I34: 0.45 | J34: 0.45 | K34: 0.4 | L34: 0.45 | M34: 0.4 | N34: 0.3 | O34: 0.3
B35: Fundamental price decline (scenario) | C35: 0 | D35: 0 | E35: =-p_dp_OSOV -> 0.02 | F35: =-p_dp_MUNI -> 0.06 | G35: =-p_dp_IG -> 0.08 | H35: =-p_dp_HY -> 0.25 | I35: =-p_dp_LEV -> 0.3 | J35: =-p_dp_CLO -> 0.25 | K35: =-p_dp_ABS -> 0.2 | L35: 0 | M35: =-p_dp_EQ -> 0.45 | N35: 0 | O35: 0
B36: Matched-book client sale allocation | C36: 0 | D36: 0 | E36: 0 | F36: 0.03 | G36: 0.25 | H36: 0.11 | I36: 0 | J36: 0 | K36: 0.13 | L36: 0 | M36: 0.48 | N36: 0 | O36: 0
B37: Insurer sale allocation | C37: 0 | D37: 0 | E37: 0 | F37: 0 | G37: 0.5 | H37: 0 | I37: 0 | J37: 0.2 | K37: 0.15 | L37: 0.15 | M37: 0 | N37: 0 | O37: 0
B38: Non-bank sales ($bn, round-invariant) | C38: =CE_ins_sales*C37 -> 0 | D38: =CE_ins_sales*D37 -> 0 | E38: =CE_ins_sales*E37 -> 0 | F38: =CE_ins_sales*F37 -> 0 | G38: =CE_ins_sales*G37 -> 14.78125 | H38: =CE_ins_sales*H37 -> 0 | I38: =CE_ins_sales*I37 -> 0 | J38: =CE_ins_sales*J37 -> 5.9125 | K38: =CE_ins_sales*K37 -> 4.434375 | L38: =CE_ins_sales*L37+CE_nonbank_pcl -> 151.83355 | M38: =CE_ins_sales*M37 -> 0 | N38: =CE_ins_sales*N37 -> 0 | O38: =CE_ins_sales*O37 -> 0
B39: Panic discount at full panic (S = 1) | C39: 0 | D39: 0.01 | E39: 0.02 | F39: 0.08 | G39: 0.1 | H39: 0.15 | I39: 0.2 | J39: 0.15 | K39: 0.1 | L39: 0.2 | M39: 0.3 | N39: 0 | O39: 0.1
B40: Basis | C40: Cont-Schaanning UST 0.23bp/EUR10bn; no panic discount (flight to quality) | D40: Duarte-Eisenbach agency = 3x UST | E40: Cont-Schaanning EU sovereigns 4.6-13bp/EUR10bn | F40: Duarte-Eisenbach munis = 12x UST; panic: judgment | G40: Ellul et al. 7.5bp per $10bn; panic: judgment, March-2020 scale | H40: Judgment: 2x IG; panic: March-2020 scale | I40: Calibration judgment; panic: LLI 76.23 on 23-Mar-2020 | J40: Calibration judgment (as loans) | K40: Judgment: between IG and loans | L40: Judgment (as loans); enters M1/M10 via pool liquidation value | M40: Judgment: deep market; dealer equity inventory delta-hedged (net 2%); panic: S&P -34% Feb-Mar 2020 scale | N40: Judgment; CRE losses in M7 | O40: Judgment
A41: Matched-book allocation = NY Fed tri-party collateral mix 10-Sep-2026 (equities 48%, IG 25%, ABS 13%, HY 11%, munis 3%); insurer allocation = judgment.

Sheet BDC
A1: BDC look-through: IG-rated intermediaries holding junk loans (34 vehicles, $381bn)
A2: Inputs from Q2-26 10-Qs; P/NAV 6-Oct-26. Pool value per BDC blends generic/software losses, valuation gap and market-implied mark. Revolver lenders are senior to unsecured notes: loss only if pool < secured debt/assets.
A5: BDC | B5: Type | C5: Investments FV ($bn) | D5: Software share | E5: Gross D/E | F5: P/NAV 6-Oct-26 | G5: Unsecured share of debt | H5: Q3 redemption requests | I5: Non-traded (1/0) | J5: Equity / assets | K5: Debt / assets | L5: Market-implied mark (listed) | M5: Mark used | N5: Overmark applied | O5: Pool value, hold | P5: Spread MTM | Q5: Secured debt / assets | R5: Asset coverage after loss | S5: NAV change | T5: Already HY (1/0) | U5: Loses IG (1/0) | V5: Borrowing-base deficiency (% assets) | W5: 150% coverage deficiency (% assets) | X5: Redemption sales (% assets) | Y5: Forced sales ($bn) | Z5: Pool value, liquidated (no FS) | AA5: Loss rate SPV (standalone) | AB5: Loss rate revolver (standalone) | AC5: helper mark x assets | AD5: helper listed assets
A6: BCRED | B6: NT | C6: 77.65 | D6: 0.258 | E6: 0.82 | G6: 0.424 | H6: 0.1 | I6: =IF(B6="NT",1,0) -> 1 | J6: =1/(1+E6) -> 0.54945055 | K6: =E6/(1+E6) -> 0.45054945 | L6: =IF(F6="","",MIN(1,1-(1-F6)*J6)) | M6: =IF(L6="",$C$42,L6) -> 0.88433128 | N6: =p_w_mkt*(1-M6) -> 0.11566872 | O6: =1-((1-D6)*CE_Lg+D6*CE_Ls)-p_gap-N6 -> 0.44762583 | P6: =(1-D6)*CE_MTMg+D6*CE_MTMs -> 0.060963435 | Q6: =(1-G6)*K6 -> 0.25951648 | R6: =O6/K6 -> 0.99351099 | S6: =(O6-1)/J6 -> -1.005321 | T6: 0 | U6: =MAX(T6,IF(OR(R6<1.75,S6<-0.2),1,0)) -> 1 | V6: =MAX(0,1-O6*(1-CE_mig_hc)-p_bb_cush)*Q6 -> 0.150154 | W6: =MAX(0,K6-O6/1.5) -> 0.15213223 | X6: =I6*J6*MIN(H6,p_red_rate)*(1-0.3) -> 0.038461538 | Y6: =C6*(p_theta_lev*MAX(V6,W6)+X6) -> 13.618299 | Z6: =O6-P6-p_c_liq -> 0.3366624 | AA6: =p_phi*MAX(0,p_a_spv-Z6)/p_a_spv+(1-p_phi)*MAX(0,p_a_spv-O6)/p_a_spv -> 0.48734988 | AB6: =IF(Q6>0,p_phi*MAX(0,Q6-Z6)/Q6+(1-p_phi)*MAX(0,Q6-O6)/Q6,0) -> 0 | AC6: =IF(L6="",0,L6*C6) -> 0 | AD6: =IF(L6="",0,C6) -> 0
A7: OCIC | B7: NT | C7: 35.69 | D7: 0.136 | E7: 0.91 | G7: 0.42 | H7: 0.168 | I7: =IF(B7="NT",1,0) -> 1 | J7: =1/(1+E7) -> 0.52356021 | K7: =E7/(1+E7) -> 0.47643979 | L7: =IF(F7="","",MIN(1,1-(1-F7)*J7)) | M7: =IF(L7="",$C$42,L7) -> 0.88433128 | N7: =p_w_mkt*(1-M7) -> 0.11566872 | O7: =1-((1-D7)*CE_Lg+D7*CE_Ls)-p_gap-N7 -> 0.47679678 | P7: =(1-D7)*CE_MTMg+D7*CE_MTMs -> 0.064256376 | Q7: =(1-G7)*K7 -> 0.27633508 | R7: =O7/K7 -> 1.0007493 | S7: =(O7-1)/J7 -> -0.99931815 | T7: 0 | U7: =MAX(T7,IF(OR(R7<1.75,S7<-0.2),1,0)) -> 1 | V7: =MAX(0,1-O7*(1-CE_mig_hc)-p_bb_cush)*Q7 -> 0.15283651 | W7: =MAX(0,K7-O7/1.5) -> 0.15857527 | X7: =I7*J7*MIN(H7,p_red_rate)*(1-0.3) -> 0.054973822 | Y7: =C7*(p_theta_lev*MAX(V7,W7)+X7) -> 7.0556119 | Z7: =O7-P7-p_c_liq -> 0.36254041 | AA7: =p_phi*MAX(0,p_a_spv-Z7)/p_a_spv+(1-p_phi)*MAX(0,p_a_spv-O7)/p_a_spv -> 0.44944045 | AB7: =IF(Q7>0,p_phi*MAX(0,Q7-Z7)/Q7+(1-p_phi)*MAX(0,Q7-O7)/Q7,0) -> 0 | AC7: =IF(L7="",0,L7*C7) -> 0 | AD7: =IF(L7="",0,C7) -> 0
A8: ARCC | B8: P | C8: 29.35 | D8: 0.22 | E8: 1.14 | F8: 0.947 | G8: 0.637 | H8: 0 | I8: =IF(B8="NT",1,0) -> 0 | J8: =1/(1+E8) -> 0.46728972 | K8: =E8/(1+E8) -> 0.53271028 | L8: =IF(F8="","",MIN(1,1-(1-F8)*J8)) -> 0.97523364 | M8: =IF(L8="",$C$42,L8) -> 0.97523364 | N8: =p_w_mkt*(1-M8) -> 0.024766355 | O8: =1-((1-D8)*CE_Lg+D8*CE_Ls)-p_gap-N8 -> 0.54761423 | P8: =(1-D8)*CE_MTMg+D8*CE_MTMs -> 0.061989105 | Q8: =(1-G8)*K8 -> 0.19337383 | R8: =O8/K8 -> 1.0279776 | S8: =(O8-1)/J8 -> -0.96810555 | T8: 0 | U8: =MAX(T8,IF(OR(R8<1.75,S8<-0.2),1,0)) -> 1 | V8: =MAX(0,1-O8*(1-CE_mig_hc)-p_bb_cush)*Q8 -> 0.094977585 | W8: =MAX(0,K8-O8/1.5) -> 0.16763413 | X8: =I8*J8*MIN(H8,p_red_rate)*(1-0.3) -> 0 | Y8: =C8*(p_theta_lev*MAX(V8,W8)+X8) -> 4.4280555 | Z8: =O8-P8-p_c_liq -> 0.43562512 | AA8: =p_phi*MAX(0,p_a_spv-Z8)/p_a_spv+(1-p_phi)*MAX(0,p_a_spv-O8)/p_a_spv -> 0.34568151 | AB8: =IF(Q8>0,p_phi*MAX(0,Q8-Z8)/Q8+(1-p_phi)*MAX(0,Q8-O8)/Q8,0) -> 0 | AC8: =IF(L8="",0,L8*C8) -> 28.623107 | AD8: =IF(L8="",0,C8) -> 29.35
A9: ADS | B9: NT | C9: 25.37 | D9: 0.107 | E9: 0.87 | G9: 0.476 | H9: 0.147 | I9: =IF(B9="NT",1,0) -> 1 | J9: =1/(1+E9) -> 0.53475936 | K9: =E9/(1+E9) -> 0.46524064 | L9: =IF(F9="","",MIN(1,1-(1-F9)*J9)) | M9: =IF(L9="",$C$42,L9) -> 0.88433128 | N9: =p_w_mkt*(1-M9) -> 0.11566872 | O9: =1-((1-D9)*CE_Lg+D9*CE_Ls)-p_gap-N9 -> 0.48373086 | P9: =(1-D9)*CE_MTMg+D9*CE_MTMs -> 0.065039124 | Q9: =(1-G9)*K9 -> 0.2437861 | R9: =O9/K9 -> 1.0397433 | S9: =(O9-1)/J9 -> -0.96542329 | T9: 0 | U9: =MAX(T9,IF(OR(R9<1.75,S9<-0.2),1,0)) -> 1 | V9: =MAX(0,1-O9*(1-CE_mig_hc)-p_bb_cush)*Q9 -> 0.13335605 | W9: =MAX(0,K9-O9/1.5) -> 0.1427534 | X9: =I9*J9*MIN(H9,p_red_rate)*(1-0.3) -> 0.055026738 | Y9: =C9*(p_theta_lev*MAX(V9,W9)+X9) -> 4.6555168 | Z9: =O9-P9-p_c_liq -> 0.36869174 | AA9: =p_phi*MAX(0,p_a_spv-Z9)/p_a_spv+(1-p_phi)*MAX(0,p_a_spv-O9)/p_a_spv -> 0.4404292 | AB9: =IF(Q9>0,p_phi*MAX(0,Q9-Z9)/Q9+(1-p_phi)*MAX(0,Q9-O9)/Q9,0) -> 0 | AC9: =IF(L9="",0,L9*C9) -> 0 | AD9: =IF(L9="",0,C9) -> 0
A10: HLEND | B10: NT | C10: 24.18 | D10: 0.176 | E10: 1 | G10: 0.452 | H10: 0.115 | I10: =IF(B10="NT",1,0) -> 1 | J10: =1/(1+E10) -> 0.5 | K10: =E10/(1+E10) -> 0.5 | L10: =IF(F10="","",MIN(1,1-(1-F10)*J10)) | M10: =IF(L10="",$C$42,L10) -> 0.88433128 | N10: =p_w_mkt*(1-M10) -> 0.11566872 | O10: =1-((1-D10)*CE_Lg+D10*CE_Ls)-p_gap-N10 -> 0.46723254 | P10: =(1-D10)*CE_MTMg+D10*CE_MTMs -> 0.063176723 | Q10: =(1-G10)*K10 -> 0.274 | R10: =O10/K10 -> 0.93446507 | S10: =(O10-1)/J10 -> -1.0655349 | T10: 0 | U10: =MAX(T10,IF(OR(R10<1.75,S10<-0.2),1,0)) -> 1 | V10: =MAX(0,1-O10*(1-CE_mig_hc)-p_bb_cush)*Q10 -> 0.15383649 | W10: =MAX(0,K10-O10/1.5) -> 0.18851164 | X10: =I10*J10*MIN(H10,p_red_rate)*(1-0.3) -> 0.04025 | Y10: =C10*(p_theta_lev*MAX(V10,W10)+X10) -> 5.0756354 | Z10: =O10-P10-p_c_liq -> 0.35405581 | AA10: =p_phi*MAX(0,p_a_spv-Z10)/p_a_spv+(1-p_phi)*MAX(0,p_a_spv-O10)/p_a_spv -> 0.46186977 | AB10: =IF(Q10>0,p_phi*MAX(0,Q10-Z10)/Q10+(1-p_phi)*MAX(0,Q10-O10)/Q10,0) -> 0 | AC10: =IF(L10="",0,L10*C10) -> 0 | AD10: =IF(L10="",0,C10) -> 0
A11: ASIF | B11: NT | C11: 21.84 | D11: 0.213 | E11: 1.18 | G11: 0.501 | H11: 0.131 | I11: =IF(B11="NT",1,0) -> 1 | J11: =1/(1+E11) -> 0.4587156 | K11: =E11/(1+E11) -> 0.5412844 | L11: =IF(F11="","",MIN(1,1-(1-F11)*J11)) | M11: =IF(L11="",$C$42,L11) -> 0.88433128 | N11: =p_w_mkt*(1-M11) -> 0.11566872 | O11: =1-((1-D11)*CE_Lg+D11*CE_Ls)-p_gap-N11 -> 0.45838561 | P11: =(1-D11)*CE_MTMg+D11*CE_MTMs -> 0.062178044 | Q11: =(1-G11)*K11 -> 0.27010092 | R11: =O11/K11 -> 0.84684799 | S11: =(O11-1)/J11 -> -1.1807194 | T11: 0 | U11: =MAX(T11,IF(OR(R11<1.75,S11<-0.2),1,0)) -> 1 | V11: =MAX(0,1-O11*(1-CE_mig_hc)-p_bb_cush)*Q11 -> 0.15373682 | W11: =MAX(0,K11-O11/1.5) -> 0.235694 | X11: =I11*J11*MIN(H11,p_red_rate)*(1-0.3) -> 0.04206422 | Y11: =C11*(p_theta_lev*MAX(V11,W11)+X11) -> 5.5514838 | Z11: =O11-P11-p_c_liq -> 0.34620756 | AA11: =p_phi*MAX(0,p_a_spv-Z11)/p_a_spv+(1-p_phi)*MAX(0,p_a_spv-O11)/p_a_spv -> 0.47336689 | AB11: =IF(Q11>0,p_phi*MAX(0,Q11-Z11)/Q11+(1-p_phi)*MAX(0,Q11-O11)/Q11,0) -> 0 | AC11: =IF(L11="",0,L11*C11) -> 0 | AD11: =IF(L11="",0,C11) -> 0
A12: GS PCC | B12: NT | C12: 18.19 | D12: 0.241 | E12: 0.96 | G12: 0.438 | H12: 0.0203 | I12: =IF(B12="NT",1,0) -> 1 | J12: =1/(1+E12) -> 0.51020408 | K12: =E12/(1+E12) -> 0.48979592 | L12: =IF(F12="","",MIN(1,1-(1-F12)*J12)) | M12: =IF(L12="",$C$42,L12) -> 0.88433128 | N12: =p_w_mkt*(1-M12) -> 0.11566872 | O12: =1-((1-D12)*CE_Lg+D12*CE_Ls)-p_gap-N12 -> 0.45169064 | P12: =(1-D12)*CE_MTMg+D12*CE_MTMs -> 0.061422287 | Q12: =(1-G12)*K12 -> 0.27526531 | R12: =O12/K12 -> 0.92220172 | S12: =(O12-1)/J12 -> -1.0746864 | T12: 0 | U12: =MAX(T12,IF(OR(R12<1.75,S12<-0.2),1,0)) -> 1 | V12: =MAX(0,1-O12*(1-CE_mig_hc)-p_bb_cush)*Q12 -> 0.15828775 | W12: =MAX(0,K12-O12/1.5) -> 0.18866883 | X12: =I12*J12*MIN(H12,p_red_rate)*(1-0.3) -> 0.00725 | Y12: =C12*(p_theta_lev*MAX(V12,W12)+X12) -> 3.2205749 | Z12: =O12-P12-p_c_liq -> 0.34026835 | AA12: =p_phi*MAX(0,p_a_spv-Z12)/p_a_spv+(1-p_phi)*MAX(0,p_a_spv-O12)/p_a_spv -> 0.48206742 | AB12: =IF(Q12>0,p_phi*MAX(0,Q12-Z12)/Q12+(1-p_phi)*MAX(0,Q12-O12)/Q12,0) -> 0 | AC12: =IF(L12="",0,L12*C12) -> 0 | AD12: =IF(L12="",0,C12) -> 0
A13: OBDC | B13: P | C13: 14.96 | D13: 0.116 | E13: 1.12 | F13: 0.686 | G13: 0.664 | H13: 0 | I13: =IF(B13="NT",1,0) -> 0 | J13: =1/(1+E13) -> 0.47169811 | K13: =E13/(1+E13) -> 0.52830189 | L13: =IF(F13="","",MIN(1,1-(1-F13)*J13)) -> 0.85188679 | M13: =IF(L13="",$C$42,L13) -> 0.85188679 | N13: =p_w_mkt*(1-M13) -> 0.14811321 | O13: =1-((1-D13)*CE_Lg+D13*CE_Ls)-p_gap-N13 -> 0.44913441 | P13: =(1-D13)*CE_MTMg+D13*CE_MTMs -> 0.064796202 | Q13: =(1-G13)*K13 -> 0.17750943 | R13: =O13/K13 -> 0.85014728 | S13: =(O13-1)/J13 -> -1.167835 | T13: 0 | U13: =MAX(T13,IF(OR(R13<1.75,S13<-0.2),1,0)) -> 1 | V13: =MAX(0,1-O13*(1-CE_mig_hc)-p_bb_cush)*Q13 -> 0.10247127 | W13: =MAX(0,K13-O13/1.5) -> 0.22887894 | X13: =I13*J13*MIN(H13,p_red_rate)*(1-0.3) -> 0 | Y13: =C13*(p_theta_lev*MAX(V13,W13)+X13) -> 3.0816261 | Z13: =O13-P13-p_c_liq -> 0.33433821 | AA13: =p_phi*MAX(0,p_a_spv-Z13)/p_a_spv+(1-p_phi)*MAX(0,p_a_spv-O13)/p_a_spv -> 0.48957507 | AB13: =IF(Q13>0,p_phi*MAX(0,Q13-Z13)/Q13+(1-p_phi)*MAX(0,Q13-O13)/Q13,0) -> 0 | AC13: =IF(L13="",0,L13*C13) -> 12.744226 | AD13: =IF(L13="",0,C13) -> 14.96
A14: OTF | B14: P | C14: 14.68 | D14: 0.328 | E14: 0.95 | F14: 0.547 | G14: 0.362 | H14: 0 | I14: =IF(B14="NT",1,0) -> 0 | J14: =1/(1+E14) -> 0.51282051 | K14: =E14/(1+E14) -> 0.48717949 | L14: =IF(F14="","",MIN(1,1-(1-F14)*J14)) -> 0.76769231 | M14: =IF(L14="",$C$42,L14) -> 0.76769231 | N14: =p_w_mkt*(1-M14) -> 0.23230769 | O14: =1-((1-D14)*CE_Lg+D14*CE_Ls)-p_gap-N14 -> 0.31424943 | P14: =(1-D14)*CE_MTMg+D14*CE_MTMs -> 0.059074043 | Q14: =(1-G14)*K14 -> 0.31082051 | R14: =O14/K14 -> 0.6450383 | S14: =(O14-1)/J14 -> -1.3372136 | T14: 0 | U14: =MAX(T14,IF(OR(R14<1.75,S14<-0.2),1,0)) -> 1 | V14: =MAX(0,1-O14*(1-CE_mig_hc)-p_bb_cush)*Q14 -> 0.21608773 | W14: =MAX(0,K14-O14/1.5) -> 0.27767987 | X14: =I14*J14*MIN(H14,p_red_rate)*(1-0.3) -> 0 | Y14: =C14*(p_theta_lev*MAX(V14,W14)+X14) -> 3.6687064 | Z14: =O14-P14-p_c_liq -> 0.20517538 | AA14: =p_phi*MAX(0,p_a_spv-Z14)/p_a_spv+(1-p_phi)*MAX(0,p_a_spv-O14)/p_a_spv -> 0.6757283 | AB14: =IF(Q14>0,p_phi*MAX(0,Q14-Z14)/Q14+(1-p_phi)*MAX(0,Q14-O14)/Q14,0) -> 0.27191289 | AC14: =IF(L14="",0,L14*C14) -> 11.269723 | AD14: =IF(L14="",0,C14) -> 14.68
A15: BXSL | B15: P | C15: 13.36 | D15: 0.189 | E15: 1.27 | F15: 0.918 | G15: 0.676 | H15: 0 | I15: =IF(B15="NT",1,0) -> 0 | J15: =1/(1+E15) -> 0.44052863 | K15: =E15/(1+E15) -> 0.55947137 | L15: =IF(F15="","",MIN(1,1-(1-F15)*J15)) -> 0.96387665 | M15: =IF(L15="",$C$42,L15) -> 0.96387665 | N15: =p_w_mkt*(1-M15) -> 0.036123348 | O15: =1-((1-D15)*CE_Lg+D15*CE_Ls)-p_gap-N15 -> 0.54366952 | P15: =(1-D15)*CE_MTMg+D15*CE_MTMs -> 0.062825836 | Q15: =(1-G15)*K15 -> 0.18126872 | R15: =O15/K15 -> 0.97175576 | S15: =(O15-1)/J15 -> -1.0358702 | T15: 0 | U15: =MAX(T15,IF(OR(R15<1.75,S15<-0.2),1,0)) -> 1 | V15: =MAX(0,1-O15*(1-CE_mig_hc)-p_bb_cush)*Q15 -> 0.089657281 | W15: =MAX(0,K15-O15/1.5) -> 0.19702502 | X15: =I15*J15*MIN(H15,p_red_rate)*(1-0.3) -> 0 | Y15: =C15*(p_theta_lev*MAX(V15,W15)+X15) -> 2.3690288 | Z15: =O15-P15-p_c_liq -> 0.43084369 | AA15: =p_phi*MAX(0,p_a_spv-Z15)/p_a_spv+(1-p_phi)*MAX(0,p_a_spv-O15)/p_a_spv -> 0.35227306 | AB15: =IF(Q15>0,p_phi*MAX(0,Q15-Z15)/Q15+(1-p_phi)*MAX(0,Q15-O15)/Q15,0) -> 0 | AC15: =IF(L15="",0,L15*C15) -> 12.877392 | AD15: =IF(L15="",0,C15) -> 13.36
A16: FSK | B16: P | C16: 11.42 | D16: 0.177 | E16: 1.26 | F16: 0.552 | G16: 0.7 | H16: 0 | I16: =IF(B16="NT",1,0) -> 0 | J16: =1/(1+E16) -> 0.44247788 | K16: =E16/(1+E16) -> 0.55752212 | L16: =IF(F16="","",MIN(1,1-(1-F16)*J16)) -> 0.80176991 | M16: =IF(L16="",$C$42,L16) -> 0.80176991 | N16: =p_w_mkt*(1-M16) -> 0.19823009 | O16: =1-((1-D16)*CE_Lg+D16*CE_Ls)-p_gap-N16 -> 0.38443206 | P16: =(1-D16)*CE_MTMg+D16*CE_MTMs -> 0.063149732 | Q16: =(1-G16)*K16 -> 0.16725664 | R16: =O16/K16 -> 0.68953687 | S16: =(O16-1)/J16 -> -1.3911835 | T16: 1 | U16: =MAX(T16,IF(OR(R16<1.75,S16<-0.2),1,0)) -> 1 | V16: =MAX(0,1-O16*(1-CE_mig_hc)-p_bb_cush)*Q16 -> 0.10601539 | W16: =MAX(0,K16-O16/1.5) -> 0.30123409 | X16: =I16*J16*MIN(H16,p_red_rate)*(1-0.3) -> 0 | Y16: =C16*(p_theta_lev*MAX(V16,W16)+X16) -> 3.0960839 | Z16: =O16-P16-p_c_liq -> 0.27128233 | AA16: =p_phi*MAX(0,p_a_spv-Z16)/p_a_spv+(1-p_phi)*MAX(0,p_a_spv-O16)/p_a_spv -> 0.58012533 | AB16: =IF(Q16>0,p_phi*MAX(0,Q16-Z16)/Q16+(1-p_phi)*MAX(0,Q16-O16)/Q16,0) -> 0 | AC16: =IF(L16="",0,L16*C16) -> 9.1562124 | AD16: =IF(L16="",0,C16) -> 11.42
A17: GCRED | B17: NT | C17: 9.62 | D17: 0.21 | E17: 1.15 | G17: 0.451 | H17: 0.05 | I17: =IF(B17="NT",1,0) -> 1 | J17: =1/(1+E17) -> 0.46511628 | K17: =E17/(1+E17) -> 0.53488372 | L17: =IF(F17="","",MIN(1,1-(1-F17)*J17)) | M17: =IF(L17="",$C$42,L17) -> 0.88433128 | N17: =p_w_mkt*(1-M17) -> 0.11566872 | O17: =1-((1-D17)*CE_Lg+D17*CE_Ls)-p_gap-N17 -> 0.45910293 | P17: =(1-D17)*CE_MTMg+D17*CE_MTMs -> 0.062259018 | Q17: =(1-G17)*K17 -> 0.29365116 | R17: =O17/K17 -> 0.85832286 | S17: =(O17-1)/J17 -> -1.1629287 | T17: 0 | U17: =MAX(T17,IF(OR(R17<1.75,S17<-0.2),1,0)) -> 1 | V17: =MAX(0,1-O17*(1-CE_mig_hc)-p_bb_cush)*Q17 -> 0.16695703 | W17: =MAX(0,K17-O17/1.5) -> 0.2288151 | X17: =I17*J17*MIN(H17,p_red_rate)*(1-0.3) -> 0.01627907 | Y17: =C17*(p_theta_lev*MAX(V17,W17)+X17) -> 2.1376858 | Z17: =O17-P17-p_c_liq -> 0.34684391 | AA17: =p_phi*MAX(0,p_a_spv-Z17)/p_a_spv+(1-p_phi)*MAX(0,p_a_spv-O17)/p_a_spv -> 0.4724347 | AB17: =IF(Q17>0,p_phi*MAX(0,Q17-Z17)/Q17+(1-p_phi)*MAX(0,Q17-O17)/Q17,0) -> 0 | AC17: =IF(L17="",0,L17*C17) -> 0 | AD17: =IF(L17="",0,C17) -> 0
A18: SSLP | B18: NT | C18: 8.65 | D18: 0.089 | E18: 0.91 | G18: 0.507 | H18: 0 | I18: =IF(B18="NT",1,0) -> 1 | J18: =1/(1+E18) -> 0.52356021 | K18: =E18/(1+E18) -> 0.47643979 | L18: =IF(F18="","",MIN(1,1-(1-F18)*J18)) | M18: =IF(L18="",$C$42,L18) -> 0.88433128 | N18: =p_w_mkt*(1-M18) -> 0.11566872 | O18: =1-((1-D18)*CE_Lg+D18*CE_Ls)-p_gap-N18 -> 0.48803477 | P18: =(1-D18)*CE_MTMg+D18*CE_MTMs -> 0.065524967 | Q18: =(1-G18)*K18 -> 0.23488482 | R18: =O18/K18 -> 1.0243367 | S18: =(O18-1)/J18 -> -0.97785359 | T18: 0 | U18: =MAX(T18,IF(OR(R18<1.75,S18<-0.2),1,0)) -> 1 | V18: =MAX(0,1-O18*(1-CE_mig_hc)-p_bb_cush)*Q18 -> 0.12760291 | W18: =MAX(0,K18-O18/1.5) -> 0.15108328 | X18: =I18*J18*MIN(H18,p_red_rate)*(1-0.3) -> 0 | Y18: =C18*(p_theta_lev*MAX(V18,W18)+X18) -> 1.1761833 | Z18: =O18-P18-p_c_liq -> 0.3725098 | AA18: =p_phi*MAX(0,p_a_spv-Z18)/p_a_spv+(1-p_phi)*MAX(0,p_a_spv-O18)/p_a_spv -> 0.434836 | AB18: =IF(Q18>0,p_phi*MAX(0,Q18-Z18)/Q18+(1-p_phi)*MAX(0,Q18-O18)/Q18,0) -> 0 | AC18: =IF(L18="",0,L18*C18) -> 0 | AD18: =IF(L18="",0,C18) -> 0
A19: GBDC | B19: P | C19: 8.2 | D19: 0.26 | E19: 1.23 | F19: 0.846 | G19: 0.641 | H19: 0 | I19: =IF(B19="NT",1,0) -> 0 | J19: =1/(1+E19) -> 0.44843049 | K19: =E19/(1+E19) -> 0.55156951 | L19: =IF(F19="","",MIN(1,1-(1-F19)*J19)) -> 0.9309417 | M19: =IF(L19="",$C$42,L19) -> 0.9309417 | N19: =p_w_mkt*(1-M19) -> 0.069058296 | O19: =1-((1-D19)*CE_Lg+D19*CE_Ls)-p_gap-N19 -> 0.49375804 | P19: =(1-D19)*CE_MTMg+D19*CE_MTMs -> 0.060909452 | Q19: =(1-G19)*K19 -> 0.19801345 | R19: =O19/K19 -> 0.89518734 | S19: =(O19-1)/J19 -> -1.1289196 | T19: 0 | U19: =MAX(T19,IF(OR(R19<1.75,S19<-0.2),1,0)) -> 1 | V19: =MAX(0,1-O19*(1-CE_mig_hc)-p_bb_cush)*Q19 -> 0.10658131 | W19: =MAX(0,K19-O19/1.5) -> 0.22239748 | X19: =I19*J19*MIN(H19,p_red_rate)*(1-0.3) -> 0 | Y19: =C19*(p_theta_lev*MAX(V19,W19)+X19) -> 1.6412934 | Z19: =O19-P19-p_c_liq -> 0.38284859 | AA19: =p_phi*MAX(0,p_a_spv-Z19)/p_a_spv+(1-p_phi)*MAX(0,p_a_spv-O19)/p_a_spv -> 0.42138503 | AB19: =IF(Q19>0,p_phi*MAX(0,Q19-Z19)/Q19+(1-p_phi)*MAX(0,Q19-O19)/Q19,0) -> 0 | AC19: =IF(L19="",0,L19*C19) -> 7.633722 | AD19: =IF(L19="",0,C19) -> 8.2
A20: OSCF | B20: NT | C20: 6.8 | D20: 0.173 | E20: 0.61 | G20: 0.439 | H20: 0.038 | I20: =IF(B20="NT",1,0) -> 1 | J20: =1/(1+E20) -> 0.62111801 | K20: =E20/(1+E20) -> 0.37888199 | L20: =IF(F20="","",MIN(1,1-(1-F20)*J20)) | M20: =IF(L20="",$C$42,L20) -> 0.88433128 | N20: =p_w_mkt*(1-M20) -> 0.11566872 | O20: =1-((1-D20)*CE_Lg+D20*CE_Ls)-p_gap-N20 -> 0.46794985 | P20: =(1-D20)*CE_MTMg+D20*CE_MTMs -> 0.063257697 | Q20: =(1-G20)*K20 -> 0.2125528 | R20: =O20/K20 -> 1.2350808 | S20: =(O20-1)/J20 -> -0.85660073 | T20: 0 | U20: =MAX(T20,IF(OR(R20<1.75,S20<-0.2),1,0)) -> 1 | V20: =MAX(0,1-O20*(1-CE_mig_hc)-p_bb_cush)*Q20 -> 0.11920382 | W20: =MAX(0,K20-O20/1.5) -> 0.066915418 | X20: =I20*J20*MIN(H20,p_red_rate)*(1-0.3) -> 0.016521739 | Y20: =C20*(p_theta_lev*MAX(V20,W20)+X20) -> 0.84187522 | Z20: =O20-P20-p_c_liq -> 0.35469216 | AA20: =p_phi*MAX(0,p_a_spv-Z20)/p_a_spv+(1-p_phi)*MAX(0,p_a_spv-O20)/p_a_spv -> 0.46093758 | AB20: =IF(Q20>0,p_phi*MAX(0,Q20-Z20)/Q20+(1-p_phi)*MAX(0,Q20-O20)/Q20,0) -> 0 | AC20: =IF(L20="",0,L20*C20) -> 0 | AD20: =IF(L20="",0,C20) -> 0
A21: PSEC | B21: P | C21: 6.34 | D21: 0.023 | E21: 0.63 | F21: 0.268 | G21: 0.5 | H21: 0 | I21: =IF(B21="NT",1,0) -> 0 | J21: =1/(1+E21) -> 0.61349693 | K21: =E21/(1+E21) -> 0.38650307 | L21: =IF(F21="","",MIN(1,1-(1-F21)*J21)) -> 0.55092025 | M21: =IF(L21="",$C$42,L21) -> 0.55092025 | N21: =p_w_mkt*(1-M21) -> 0.44907975 | O21: =1-((1-D21)*CE_Lg+D21*CE_Ls)-p_gap-N21 -> 0.17040474 | P21: =(1-D21)*CE_MTMg+D21*CE_MTMs -> 0.067306394 | Q21: =(1-G21)*K21 -> 0.19325153 | R21: =O21/K21 -> 0.44088845 | S21: =(O21-1)/J21 -> -1.3522403 | T21: 0 | U21: =MAX(T21,IF(OR(R21<1.75,S21<-0.2),1,0)) -> 1 | V21: =MAX(0,1-O21*(1-CE_mig_hc)-p_bb_cush)*Q21 -> 0.1586588 | W21: =MAX(0,K21-O21/1.5) -> 0.27289991 | X21: =I21*J21*MIN(H21,p_red_rate)*(1-0.3) -> 0 | Y21: =C21*(p_theta_lev*MAX(V21,W21)+X21) -> 1.5571669 | Z21: =O21-P21-p_c_liq -> 0.053098343 | AA21: =p_phi*MAX(0,p_a_spv-Z21)/p_a_spv+(1-p_phi)*MAX(0,p_a_spv-O21)/p_a_spv -> 0.89062911 | AB21: =IF(Q21>0,p_phi*MAX(0,Q21-Z21)/Q21+(1-p_phi)*MAX(0,Q21-O21)/Q21,0) -> 0.60383434 | AC21: =IF(L21="",0,L21*C21) -> 3.4928344 | AD21: =IF(L21="",0,C21) -> 6.34
A22: NHPIF | B22: NT | C22: 5.98 | D22: 0.227 | E22: 0.96 | G22: 0.5 | H22: 0.114 | I22: =IF(B22="NT",1,0) -> 1 | J22: =1/(1+E22) -> 0.51020408 | K22: =E22/(1+E22) -> 0.48979592 | L22: =IF(F22="","",MIN(1,1-(1-F22)*J22)) | M22: =IF(L22="",$C$42,L22) -> 0.88433128 | N22: =p_w_mkt*(1-M22) -> 0.11566872 | O22: =1-((1-D22)*CE_Lg+D22*CE_Ls)-p_gap-N22 -> 0.45503812 | P22: =(1-D22)*CE_MTMg+D22*CE_MTMs -> 0.061800166 | Q22: =(1-G22)*K22 -> 0.24489796 | R22: =O22/K22 -> 0.92903617 | S22: =(O22-1)/J22 -> -1.0681253 | T22: 0 | U22: =MAX(T22,IF(OR(R22<1.75,S22<-0.2),1,0)) -> 1 | V22: =MAX(0,1-O22*(1-CE_mig_hc)-p_bb_cush)*Q22 -> 0.14010857 | W22: =MAX(0,K22-O22/1.5) -> 0.18643717 | X22: =I22*J22*MIN(H22,p_red_rate)*(1-0.3) -> 0.040714286 | Y22: =C22*(p_theta_lev*MAX(V22,W22)+X22) -> 1.2468763 | Z22: =O22-P22-p_c_liq -> 0.34323796 | AA22: =p_phi*MAX(0,p_a_spv-Z22)/p_a_spv+(1-p_phi)*MAX(0,p_a_spv-O22)/p_a_spv -> 0.47771716 | AB22: =IF(Q22>0,p_phi*MAX(0,Q22-Z22)/Q22+(1-p_phi)*MAX(0,Q22-O22)/Q22,0) -> 0 | AC22: =IF(L22="",0,L22*C22) -> 0 | AD22: =IF(L22="",0,C22) -> 0
A23: MAIN | B23: P | C23: 5.75 | D23: 0.051 | E23: 0.8 | F23: 1.545 | G23: 0.767 | H23: 0 | I23: =IF(B23="NT",1,0) -> 0 | J23: =1/(1+E23) -> 0.55555556 | K23: =E23/(1+E23) -> 0.44444444 | L23: =IF(F23="","",MIN(1,1-(1-F23)*J23)) -> 1 | M23: =IF(L23="",$C$42,L23) -> 1 | N23: =p_w_mkt*(1-M23) -> 0 | O23: =1-((1-D23)*CE_Lg+D23*CE_Ls)-p_gap-N23 -> 0.61278952 | P23: =(1-D23)*CE_MTMg+D23*CE_MTMs -> 0.066550637 | Q23: =(1-G23)*K23 -> 0.10355556 | R23: =O23/K23 -> 1.3787764 | S23: =(O23-1)/J23 -> -0.69697886 | T23: 0 | U23: =MAX(T23,IF(OR(R23<1.75,S23<-0.2),1,0)) -> 1 | V23: =MAX(0,1-O23*(1-CE_mig_hc)-p_bb_cush)*Q23 -> 0.044960771 | W23: =MAX(0,K23-O23/1.5) -> 0.035918098 | X23: =I23*J23*MIN(H23,p_red_rate)*(1-0.3) -> 0 | Y23: =C23*(p_theta_lev*MAX(V23,W23)+X23) -> 0.23267199 | Z23: =O23-P23-p_c_liq -> 0.49623888 | AA23: =p_phi*MAX(0,p_a_spv-Z23)/p_a_spv+(1-p_phi)*MAX(0,p_a_spv-O23)/p_a_spv -> 0.25778713 | AB23: =IF(Q23>0,p_phi*MAX(0,Q23-Z23)/Q23+(1-p_phi)*MAX(0,Q23-O23)/Q23,0) -> 0 | AC23: =IF(L23="",0,L23*C23) -> 5.75 | AD23: =IF(L23="",0,C23) -> 5.75
A24: OTIC | B24: NT | C24: 5.06 | D24: 0.3 | E24: 0.86 | G24: 0.075 | H24: 0.39 | I24: =IF(B24="NT",1,0) -> 1 | J24: =1/(1+E24) -> 0.53763441 | K24: =E24/(1+E24) -> 0.46236559 | L24: =IF(F24="","",MIN(1,1-(1-F24)*J24)) | M24: =IF(L24="",$C$42,L24) -> 0.88433128 | N24: =p_w_mkt*(1-M24) -> 0.11566872 | O24: =1-((1-D24)*CE_Lg+D24*CE_Ls)-p_gap-N24 -> 0.43758337 | P24: =(1-D24)*CE_MTMg+D24*CE_MTMs -> 0.0598298 | Q24: =(1-G24)*K24 -> 0.42768817 | R24: =O24/K24 -> 0.94640125 | S24: =(O24-1)/J24 -> -1.0460949 | T24: 0 | U24: =MAX(T24,IF(OR(R24<1.75,S24<-0.2),1,0)) -> 1 | V24: =MAX(0,1-O24*(1-CE_mig_hc)-p_bb_cush)*Q24 -> 0.25121231 | W24: =MAX(0,K24-O24/1.5) -> 0.17064334 | X24: =I24*J24*MIN(H24,p_red_rate)*(1-0.3) -> 0.056451613 | Y24: =C24*(p_theta_lev*MAX(V24,W24)+X24) -> 1.429666 | Z24: =O24-P24-p_c_liq -> 0.32775358 | AA24: =p_phi*MAX(0,p_a_spv-Z24)/p_a_spv+(1-p_phi)*MAX(0,p_a_spv-O24)/p_a_spv -> 0.50040066 | AB24: =IF(Q24>0,p_phi*MAX(0,Q24-Z24)/Q24+(1-p_phi)*MAX(0,Q24-O24)/Q24,0) -> 0.18692983 | AC24: =IF(L24="",0,L24*C24) -> 0 | AD24: =IF(L24="",0,C24) -> 0
A25: ASCF | B25: NT | C25: 4.62 | D25: 0.187 | E25: 1.17 | G25: 0.5 | H25: 0.103 | I25: =IF(B25="NT",1,0) -> 1 | J25: =1/(1+E25) -> 0.46082949 | K25: =E25/(1+E25) -> 0.53917051 | L25: =IF(F25="","",MIN(1,1-(1-F25)*J25)) | M25: =IF(L25="",$C$42,L25) -> 0.88433128 | N25: =p_w_mkt*(1-M25) -> 0.11566872 | O25: =1-((1-D25)*CE_Lg+D25*CE_Ls)-p_gap-N25 -> 0.46460237 | P25: =(1-D25)*CE_MTMg+D25*CE_MTMs -> 0.062879818 | Q25: =(1-G25)*K25 -> 0.26958525 | R25: =O25/K25 -> 0.86169841 | S25: =(O25-1)/J25 -> -1.1618129 | T25: 0 | U25: =MAX(T25,IF(OR(R25<1.75,S25<-0.2),1,0)) -> 1 | V25: =MAX(0,1-O25*(1-CE_mig_hc)-p_bb_cush)*Q25 -> 0.15197785 | W25: =MAX(0,K25-O25/1.5) -> 0.22943559 | X25: =I25*J25*MIN(H25,p_red_rate)*(1-0.3) -> 0.033225806 | Y25: =C25*(p_theta_lev*MAX(V25,W25)+X25) -> 1.1074964 | Z25: =O25-P25-p_c_liq -> 0.35172255 | AA25: =p_phi*MAX(0,p_a_spv-Z25)/p_a_spv+(1-p_phi)*MAX(0,p_a_spv-O25)/p_a_spv -> 0.46528784 | AB25: =IF(Q25>0,p_phi*MAX(0,Q25-Z25)/Q25+(1-p_phi)*MAX(0,Q25-O25)/Q25,0) -> 0 | AC25: =IF(L25="",0,L25*C25) -> 0 | AD25: =IF(L25="",0,C25) -> 0
A26: HTGC | B26: P | C26: 4.58 | D26: 0.328 | E26: 1.03 | F26: 1.313 | G26: 0.5 | H26: 0 | I26: =IF(B26="NT",1,0) -> 0 | J26: =1/(1+E26) -> 0.49261084 | K26: =E26/(1+E26) -> 0.50738916 | L26: =IF(F26="","",MIN(1,1-(1-F26)*J26)) -> 1 | M26: =IF(L26="",$C$42,L26) -> 1 | N26: =p_w_mkt*(1-M26) -> 0 | O26: =1-((1-D26)*CE_Lg+D26*CE_Ls)-p_gap-N26 -> 0.54655712 | P26: =(1-D26)*CE_MTMg+D26*CE_MTMs -> 0.059074043 | Q26: =(1-G26)*K26 -> 0.25369458 | R26: =O26/K26 -> 1.0771951 | S26: =(O26-1)/J26 -> -0.92048905 | T26: 0 | U26: =MAX(T26,IF(OR(R26<1.75,S26<-0.2),1,0)) -> 1 | V26: =MAX(0,1-O26*(1-CE_mig_hc)-p_bb_cush)*Q26 -> 0.12483925 | W26: =MAX(0,K26-O26/1.5) -> 0.14301775 | X26: =I26*J26*MIN(H26,p_red_rate)*(1-0.3) -> 0 | Y26: =C26*(p_theta_lev*MAX(V26,W26)+X26) -> 0.58951917 | Z26: =O26-P26-p_c_liq -> 0.43748308 | AA26: =p_phi*MAX(0,p_a_spv-Z26)/p_a_spv+(1-p_phi)*MAX(0,p_a_spv-O26)/p_a_spv -> 0.34386017 | AB26: =IF(Q26>0,p_phi*MAX(0,Q26-Z26)/Q26+(1-p_phi)*MAX(0,Q26-O26)/Q26,0) -> 0 | AC26: =IF(L26="",0,L26*C26) -> 4.58 | AD26: =IF(L26="",0,C26) -> 4.58
A27: MSDL | B27: P | C27: 3.55 | D27: 0.212 | E27: 1.2 | F27: 0.655 | G27: 0.562 | H27: 0 | I27: =IF(B27="NT",1,0) -> 0 | J27: =1/(1+E27) -> 0.45454545 | K27: =E27/(1+E27) -> 0.54545455 | L27: =IF(F27="","",MIN(1,1-(1-F27)*J27)) -> 0.84318182 | M27: =IF(L27="",$C$42,L27) -> 0.84318182 | N27: =p_w_mkt*(1-M27) -> 0.15681818 | O27: =1-((1-D27)*CE_Lg+D27*CE_Ls)-p_gap-N27 -> 0.41747525 | P27: =(1-D27)*CE_MTMg+D27*CE_MTMs -> 0.062205036 | Q27: =(1-G27)*K27 -> 0.23890909 | R27: =O27/K27 -> 0.76537129 | S27: =(O27-1)/J27 -> -1.2815545 | T27: 0 | U27: =MAX(T27,IF(OR(R27<1.75,S27<-0.2),1,0)) -> 1 | V27: =MAX(0,1-O27*(1-CE_mig_hc)-p_bb_cush)*Q27 -> 0.14452933 | W27: =MAX(0,K27-O27/1.5) -> 0.26713771 | X27: =I27*J27*MIN(H27,p_red_rate)*(1-0.3) -> 0 | Y27: =C27*(p_theta_lev*MAX(V27,W27)+X27) -> 0.85350499 | Z27: =O27-P27-p_c_liq -> 0.30527021 | AA27: =p_phi*MAX(0,p_a_spv-Z27)/p_a_spv+(1-p_phi)*MAX(0,p_a_spv-O27)/p_a_spv -> 0.53184111 | AB27: =IF(Q27>0,p_phi*MAX(0,Q27-Z27)/Q27+(1-p_phi)*MAX(0,Q27-O27)/Q27,0) -> 0 | AC27: =IF(L27="",0,L27*C27) -> 2.9932955 | AD27: =IF(L27="",0,C27) -> 3.55
A28: TSLX | B28: P | C28: 3.3 | D28: 0.19 | E28: 1.27 | F28: 1.029 | G28: 0.788 | H28: 0 | I28: =IF(B28="NT",1,0) -> 0 | J28: =1/(1+E28) -> 0.44052863 | K28: =E28/(1+E28) -> 0.55947137 | L28: =IF(F28="","",MIN(1,1-(1-F28)*J28)) -> 1 | M28: =IF(L28="",$C$42,L28) -> 1 | N28: =p_w_mkt*(1-M28) -> 0 | O28: =1-((1-D28)*CE_Lg+D28*CE_Ls)-p_gap-N28 -> 0.57955377 | P28: =(1-D28)*CE_MTMg+D28*CE_MTMs -> 0.062798844 | Q28: =(1-G28)*K28 -> 0.11860793 | R28: =O28/K28 -> 1.0358953 | S28: =(O28-1)/J28 -> -0.95441295 | T28: 0 | U28: =MAX(T28,IF(OR(R28<1.75,S28<-0.2),1,0)) -> 1 | V28: =MAX(0,1-O28*(1-CE_mig_hc)-p_bb_cush)*Q28 -> 0.054943015 | W28: =MAX(0,K28-O28/1.5) -> 0.17310219 | X28: =I28*J28*MIN(H28,p_red_rate)*(1-0.3) -> 0 | Y28: =C28*(p_theta_lev*MAX(V28,W28)+X28) -> 0.5141135 | Z28: =O28-P28-p_c_liq -> 0.46675492 | AA28: =p_phi*MAX(0,p_a_spv-Z28)/p_a_spv+(1-p_phi)*MAX(0,p_a_spv-O28)/p_a_spv -> 0.30097901 | AB28: =IF(Q28>0,p_phi*MAX(0,Q28-Z28)/Q28+(1-p_phi)*MAX(0,Q28-O28)/Q28,0) -> 0 | AC28: =IF(L28="",0,L28*C28) -> 3.3 | AD28: =IF(L28="",0,C28) -> 3.3
A29: GSBD | B29: P | C29: 3.2 | D29: 0.196 | E29: 1.36 | F29: 0.714 | G29: 0.633 | H29: 0 | I29: =IF(B29="NT",1,0) -> 0 | J29: =1/(1+E29) -> 0.42372881 | K29: =E29/(1+E29) -> 0.57627119 | L29: =IF(F29="","",MIN(1,1-(1-F29)*J29)) -> 0.87881356 | M29: =IF(L29="",$C$42,L29) -> 0.87881356 | N29: =p_w_mkt*(1-M29) -> 0.12118644 | O29: =1-((1-D29)*CE_Lg+D29*CE_Ls)-p_gap-N29 -> 0.45693269 | P29: =(1-D29)*CE_MTMg+D29*CE_MTMs -> 0.062636897 | Q29: =(1-G29)*K29 -> 0.21149153 | R29: =O29/K29 -> 0.79291261 | S29: =(O29-1)/J29 -> -1.2816389 | T29: 0 | U29: =MAX(T29,IF(OR(R29<1.75,S29<-0.2),1,0)) -> 1 | V29: =MAX(0,1-O29*(1-CE_mig_hc)-p_bb_cush)*Q29 -> 0.12064605 | W29: =MAX(0,K29-O29/1.5) -> 0.27164939 | X29: =I29*J29*MIN(H29,p_red_rate)*(1-0.3) -> 0 | Y29: =C29*(p_theta_lev*MAX(V29,W29)+X29) -> 0.78235025 | Z29: =O29-P29-p_c_liq -> 0.34429579 | AA29: =p_phi*MAX(0,p_a_spv-Z29)/p_a_spv+(1-p_phi)*MAX(0,p_a_spv-O29)/p_a_spv -> 0.4759669 | AB29: =IF(Q29>0,p_phi*MAX(0,Q29-Z29)/Q29+(1-p_phi)*MAX(0,Q29-O29)/Q29,0) -> 0 | AC29: =IF(L29="",0,L29*C29) -> 2.8122034 | AD29: =IF(L29="",0,C29) -> 3.2
A30: OCSL | B30: P | C30: 2.74 | D30: 0.189 | E30: 1.04 | F30: 0.728 | G30: 0.5 | H30: 0 | I30: =IF(B30="NT",1,0) -> 0 | J30: =1/(1+E30) -> 0.49019608 | K30: =E30/(1+E30) -> 0.50980392 | L30: =IF(F30="","",MIN(1,1-(1-F30)*J30)) -> 0.86666667 | M30: =IF(L30="",$C$42,L30) -> 0.86666667 | N30: =p_w_mkt*(1-M30) -> 0.13333333 | O30: =1-((1-D30)*CE_Lg+D30*CE_Ls)-p_gap-N30 -> 0.44645954 | P30: =(1-D30)*CE_MTMg+D30*CE_MTMs -> 0.062825836 | Q30: =(1-G30)*K30 -> 0.25490196 | R30: =O30/K30 -> 0.87574756 | S30: =(O30-1)/J30 -> -1.1292225 | T30: 0 | U30: =MAX(T30,IF(OR(R30<1.75,S30<-0.2),1,0)) -> 1 | V30: =MAX(0,1-O30*(1-CE_mig_hc)-p_bb_cush)*Q30 -> 0.14774403 | W30: =MAX(0,K30-O30/1.5) -> 0.21216423 | X30: =I30*J30*MIN(H30,p_red_rate)*(1-0.3) -> 0 | Y30: =C30*(p_theta_lev*MAX(V30,W30)+X30) -> 0.52319699 | Z30: =O30-P30-p_c_liq -> 0.3336337 | AA30: =p_phi*MAX(0,p_a_spv-Z30)/p_a_spv+(1-p_phi)*MAX(0,p_a_spv-O30)/p_a_spv -> 0.49114447 | AB30: =IF(Q30>0,p_phi*MAX(0,Q30-Z30)/Q30+(1-p_phi)*MAX(0,Q30-O30)/Q30,0) -> 0 | AC30: =IF(L30="",0,L30*C30) -> 2.3746667 | AD30: =IF(L30="",0,C30) -> 2.74
A31: BBDC | B31: P | C31: 2.46 | D31: 0.094 | E31: 1.23 | F31: 0.763 | G31: 0.5 | H31: 0 | I31: =IF(B31="NT",1,0) -> 0 | J31: =1/(1+E31) -> 0.44843049 | K31: =E31/(1+E31) -> 0.55156951 | L31: =IF(F31="","",MIN(1,1-(1-F31)*J31)) -> 0.89372197 | M31: =IF(L31="",$C$42,L31) -> 0.89372197 | N31: =p_w_mkt*(1-M31) -> 0.10627803 | O31: =1-((1-D31)*CE_Lg+D31*CE_Ls)-p_gap-N31 -> 0.49622993 | P31: =(1-D31)*CE_MTMg+D31*CE_MTMs -> 0.065390011 | Q31: =(1-G31)*K31 -> 0.27578475 | R31: =O31/K31 -> 0.8996689 | S31: =(O31-1)/J31 -> -1.1234073 | T31: 0 | U31: =MAX(T31,IF(OR(R31<1.75,S31<-0.2),1,0)) -> 1 | V31: =MAX(0,1-O31*(1-CE_mig_hc)-p_bb_cush)*Q31 -> 0.14784585 | W31: =MAX(0,K31-O31/1.5) -> 0.22074955 | X31: =I31*J31*MIN(H31,p_red_rate)*(1-0.3) -> 0 | Y31: =C31*(p_theta_lev*MAX(V31,W31)+X31) -> 0.48873951 | Z31: =O31-P31-p_c_liq -> 0.38083992 | AA31: =p_phi*MAX(0,p_a_spv-Z31)/p_a_spv+(1-p_phi)*MAX(0,p_a_spv-O31)/p_a_spv -> 0.4229744 | AB31: =IF(Q31>0,p_phi*MAX(0,Q31-Z31)/Q31+(1-p_phi)*MAX(0,Q31-O31)/Q31,0) -> 0 | AC31: =IF(L31="",0,L31*C31) -> 2.1985561 | AD31: =IF(L31="",0,C31) -> 2.46
A32: CGBD | B32: P | C32: 2.36 | D32: 0.127 | E32: 1.19 | F32: 0.647 | G32: 0.457 | H32: 0 | I32: =IF(B32="NT",1,0) -> 0 | J32: =1/(1+E32) -> 0.456621 | K32: =E32/(1+E32) -> 0.543379 | L32: =IF(F32="","",MIN(1,1-(1-F32)*J32)) -> 0.83881279 | M32: =IF(L32="",$C$42,L32) -> 0.83881279 | N32: =p_w_mkt*(1-M32) -> 0.16118721 | O32: =1-((1-D32)*CE_Lg+D32*CE_Ls)-p_gap-N32 -> 0.43343024 | P32: =(1-D32)*CE_MTMg+D32*CE_MTMs -> 0.064499297 | Q32: =(1-G32)*K32 -> 0.29505479 | R32: =O32/K32 -> 0.79765733 | S32: =(O32-1)/J32 -> -1.2407878 | T32: 0 | U32: =MAX(T32,IF(OR(R32<1.75,S32<-0.2),1,0)) -> 1 | V32: =MAX(0,1-O32*(1-CE_mig_hc)-p_bb_cush)*Q32 -> 0.1743786 | W32: =MAX(0,K32-O32/1.5) -> 0.2544255 | X32: =I32*J32*MIN(H32,p_red_rate)*(1-0.3) -> 0 | Y32: =C32*(p_theta_lev*MAX(V32,W32)+X32) -> 0.54039977 | Z32: =O32-P32-p_c_liq -> 0.31893094 | AA32: =p_phi*MAX(0,p_a_spv-Z32)/p_a_spv+(1-p_phi)*MAX(0,p_a_spv-O32)/p_a_spv -> 0.51167028 | AB32: =IF(Q32>0,p_phi*MAX(0,Q32-Z32)/Q32+(1-p_phi)*MAX(0,Q32-O32)/Q32,0) -> 0 | AC32: =IF(L32="",0,L32*C32) -> 1.9795982 | AD32: =IF(L32="",0,C32) -> 2.36
A33: KBDC | B33: P | C33: 2.29 | D33: 0.015 | E33: 1.17 | F33: 0.765 | G33: 0.5 | H33: 0 | I33: =IF(B33="NT",1,0) -> 0 | J33: =1/(1+E33) -> 0.46082949 | K33: =E33/(1+E33) -> 0.53917051 | L33: =IF(F33="","",MIN(1,1-(1-F33)*J33)) -> 0.89170507 | M33: =IF(L33="",$C$42,L33) -> 0.89170507 | N33: =p_w_mkt*(1-M33) -> 0.10829493 | O33: =1-((1-D33)*CE_Lg+D33*CE_Ls)-p_gap-N33 -> 0.51310241 | P33: =(1-D33)*CE_MTMg+D33*CE_MTMs -> 0.067522325 | Q33: =(1-G33)*K33 -> 0.26958525 | R33: =O33/K33 -> 0.95165148 | S33: =(O33-1)/J33 -> -1.0565678 | T33: 0 | U33: =MAX(T33,IF(OR(R33<1.75,S33<-0.2),1,0)) -> 1 | V33: =MAX(0,1-O33*(1-CE_mig_hc)-p_bb_cush)*Q33 -> 0.14054503 | W33: =MAX(0,K33-O33/1.5) -> 0.19710223 | X33: =I33*J33*MIN(H33,p_red_rate)*(1-0.3) -> 0 | Y33: =C33*(p_theta_lev*MAX(V33,W33)+X33) -> 0.4062277 | Z33: =O33-P33-p_c_liq -> 0.39558009 | AA33: =p_phi*MAX(0,p_a_spv-Z33)/p_a_spv+(1-p_phi)*MAX(0,p_a_spv-O33)/p_a_spv -> 0.40130778 | AB33: =IF(Q33>0,p_phi*MAX(0,Q33-Z33)/Q33+(1-p_phi)*MAX(0,Q33-O33)/Q33,0) -> 0 | AC33: =IF(L33="",0,L33*C33) -> 2.0420046 | AD33: =IF(L33="",0,C33) -> 2.29
A34: NMFC | B34: P | C34: 2.29 | D34: 0.165 | E34: 1.31 | F34: 0.608 | G34: 0.578 | H34: 0 | I34: =IF(B34="NT",1,0) -> 0 | J34: =1/(1+E34) -> 0.43290043 | K34: =E34/(1+E34) -> 0.56709957 | L34: =IF(F34="","",MIN(1,1-(1-F34)*J34)) -> 0.83030303 | M34: =IF(L34="",$C$42,L34) -> 0.83030303 | N34: =p_w_mkt*(1-M34) -> 0.16969697 | O34: =1-((1-D34)*CE_Lg+D34*CE_Ls)-p_gap-N34 -> 0.41583445 | P34: =(1-D34)*CE_MTMg+D34*CE_MTMs -> 0.063473627 | Q34: =(1-G34)*K34 -> 0.23931602 | R34: =O34/K34 -> 0.73326533 | S34: =(O34-1)/J34 -> -1.3494224 | T34: 0 | U34: =MAX(T34,IF(OR(R34<1.75,S34<-0.2),1,0)) -> 1 | V34: =MAX(0,1-O34*(1-CE_mig_hc)-p_bb_cush)*Q34 -> 0.14511886 | W34: =MAX(0,K34-O34/1.5) -> 0.2898766 | X34: =I34*J34*MIN(H34,p_red_rate)*(1-0.3) -> 0 | Y34: =C34*(p_theta_lev*MAX(V34,W34)+X34) -> 0.59743567 | Z34: =O34-P34-p_c_liq -> 0.30236082 | AA34: =p_phi*MAX(0,p_a_spv-Z34)/p_a_spv+(1-p_phi)*MAX(0,p_a_spv-O34)/p_a_spv -> 0.53563493 | AB34: =IF(Q34>0,p_phi*MAX(0,Q34-Z34)/Q34+(1-p_phi)*MAX(0,Q34-O34)/Q34,0) -> 0 | AC34: =IF(L34="",0,L34*C34) -> 1.9013939 | AD34: =IF(L34="",0,C34) -> 2.29
A35: HPS CCS | B35: NT | C35: 2.27 | D35: 0.104 | E35: 0.69 | G35: 0.5 | H35: 0.046 | I35: =IF(B35="NT",1,0) -> 1 | J35: =1/(1+E35) -> 0.59171598 | K35: =E35/(1+E35) -> 0.40828402 | L35: =IF(F35="","",MIN(1,1-(1-F35)*J35)) | M35: =IF(L35="",$C$42,L35) -> 0.88433128 | N35: =p_w_mkt*(1-M35) -> 0.11566872 | O35: =1-((1-D35)*CE_Lg+D35*CE_Ls)-p_gap-N35 -> 0.48444818 | P35: =(1-D35)*CE_MTMg+D35*CE_MTMs -> 0.065120098 | Q35: =(1-G35)*K35 -> 0.20414201 | R35: =O35/K35 -> 1.186547 | S35: =(O35-1)/J35 -> -0.87128258 | T35: 0 | U35: =MAX(T35,IF(OR(R35<1.75,S35<-0.2),1,0)) -> 1 | V35: =MAX(0,1-O35*(1-CE_mig_hc)-p_bb_cush)*Q35 -> 0.11154187 | W35: =MAX(0,K35-O35/1.5) -> 0.085318571 | X35: =I35*J35*MIN(H35,p_red_rate)*(1-0.3) -> 0.019053254 | Y35: =C35*(p_theta_lev*MAX(V35,W35)+X35) -> 0.27113094 | Z35: =O35-P35-p_c_liq -> 0.36932808 | AA35: =p_phi*MAX(0,p_a_spv-Z35)/p_a_spv+(1-p_phi)*MAX(0,p_a_spv-O35)/p_a_spv -> 0.439497 | AB35: =IF(Q35>0,p_phi*MAX(0,Q35-Z35)/Q35+(1-p_phi)*MAX(0,Q35-O35)/Q35,0) -> 0 | AC35: =IF(L35="",0,L35*C35) -> 0 | AD35: =IF(L35="",0,C35) -> 0
A36: APCF | B36: NT | C36: 1.73 | D36: 0.178 | E36: 1.15 | G36: 0.5 | H36: 0.0045 | I36: =IF(B36="NT",1,0) -> 1 | J36: =1/(1+E36) -> 0.46511628 | K36: =E36/(1+E36) -> 0.53488372 | L36: =IF(F36="","",MIN(1,1-(1-F36)*J36)) | M36: =IF(L36="",$C$42,L36) -> 0.88433128 | N36: =p_w_mkt*(1-M36) -> 0.11566872 | O36: =1-((1-D36)*CE_Lg+D36*CE_Ls)-p_gap-N36 -> 0.46675432 | P36: =(1-D36)*CE_MTMg+D36*CE_MTMs -> 0.06312274 | Q36: =(1-G36)*K36 -> 0.26744186 | R36: =O36/K36 -> 0.87262765 | S36: =(O36-1)/J36 -> -1.1464782 | T36: 0 | U36: =MAX(T36,IF(OR(R36<1.75,S36<-0.2),1,0)) -> 1 | V36: =MAX(0,1-O36*(1-CE_mig_hc)-p_bb_cush)*Q36 -> 0.15026628 | W36: =MAX(0,K36-O36/1.5) -> 0.22371417 | X36: =I36*J36*MIN(H36,p_red_rate)*(1-0.3) -> 0.0014651163 | Y36: =C36*(p_theta_lev*MAX(V36,W36)+X36) -> 0.35085762 | Z36: =O36-P36-p_c_liq -> 0.35363158 | AA36: =p_phi*MAX(0,p_a_spv-Z36)/p_a_spv+(1-p_phi)*MAX(0,p_a_spv-O36)/p_a_spv -> 0.46249124 | AB36: =IF(Q36>0,p_phi*MAX(0,Q36-Z36)/Q36+(1-p_phi)*MAX(0,Q36-O36)/Q36,0) -> 0 | AC36: =IF(L36="",0,L36*C36) -> 0 | AD36: =IF(L36="",0,C36) -> 0
A37: TCPC | B37: P | C37: 1.29 | D37: 0.263 | E37: 1.65 | F37: 0.628 | G37: 0.5 | H37: 0 | I37: =IF(B37="NT",1,0) -> 0 | J37: =1/(1+E37) -> 0.37735849 | K37: =E37/(1+E37) -> 0.62264151 | L37: =IF(F37="","",MIN(1,1-(1-F37)*J37)) -> 0.85962264 | M37: =IF(L37="",$C$42,L37) -> 0.85962264 | N37: =p_w_mkt*(1-M37) -> 0.14037736 | O37: =1-((1-D37)*CE_Lg+D37*CE_Ls)-p_gap-N37 -> 0.42172166 | P37: =(1-D37)*CE_MTMg+D37*CE_MTMs -> 0.060828479 | Q37: =(1-G37)*K37 -> 0.31132075 | R37: =O37/K37 -> 0.67731054 | S37: =(O37-1)/J37 -> -1.5324376 | T37: 1 | U37: =MAX(T37,IF(OR(R37<1.75,S37<-0.2),1,0)) -> 1 | V37: =MAX(0,1-O37*(1-CE_mig_hc)-p_bb_cush)*Q37 -> 0.18717919 | W37: =MAX(0,K37-O37/1.5) -> 0.34149374 | X37: =I37*J37*MIN(H37,p_red_rate)*(1-0.3) -> 0 | Y37: =C37*(p_theta_lev*MAX(V37,W37)+X37) -> 0.39647423 | Z37: =O37-P37-p_c_liq -> 0.31089318 | AA37: =p_phi*MAX(0,p_a_spv-Z37)/p_a_spv+(1-p_phi)*MAX(0,p_a_spv-O37)/p_a_spv -> 0.5242016 | AB37: =IF(Q37>0,p_phi*MAX(0,Q37-Z37)/Q37+(1-p_phi)*MAX(0,Q37-O37)/Q37,0) -> 0.0010987346 | AC37: =IF(L37="",0,L37*C37) -> 1.1089132 | AD37: =IF(L37="",0,C37) -> 1.29
A38: OBDC II | B38: NT | C38: 0.69 | D38: 0.093 | E38: 0.27 | G38: 0 | H38: 0 | I38: =IF(B38="NT",1,0) -> 1 | J38: =1/(1+E38) -> 0.78740157 | K38: =E38/(1+E38) -> 0.21259843 | L38: =IF(F38="","",MIN(1,1-(1-F38)*J38)) | M38: =IF(L38="",$C$42,L38) -> 0.88433128 | N38: =p_w_mkt*(1-M38) -> 0.11566872 | O38: =1-((1-D38)*CE_Lg+D38*CE_Ls)-p_gap-N38 -> 0.48707835 | P38: =(1-D38)*CE_MTMg+D38*CE_MTMs -> 0.065417002 | Q38: =(1-G38)*K38 -> 0.21259843 | R38: =O38/K38 -> 2.2910722 | S38: =(O38-1)/J38 -> -0.6514105 | T38: 0 | U38: =MAX(T38,IF(OR(R38<1.75,S38<-0.2),1,0)) -> 1 | V38: =MAX(0,1-O38*(1-CE_mig_hc)-p_bb_cush)*Q38 -> 0.11567346 | W38: =MAX(0,K38-O38/1.5) -> 0 | X38: =I38*J38*MIN(H38,p_red_rate)*(1-0.3) -> 0 | Y38: =C38*(p_theta_lev*MAX(V38,W38)+X38) -> 0.071833218 | Z38: =O38-P38-p_c_liq -> 0.37166134 | AA38: =p_phi*MAX(0,p_a_spv-Z38)/p_a_spv+(1-p_phi)*MAX(0,p_a_spv-O38)/p_a_spv -> 0.43607894 | AB38: =IF(Q38>0,p_phi*MAX(0,Q38-Z38)/Q38+(1-p_phi)*MAX(0,Q38-O38)/Q38,0) -> 0 | AC38: =IF(L38="",0,L38*C38) -> 0 | AD38: =IF(L38="",0,C38) -> 0
A39: NHPIF-A | B39: NT | C39: 0.6 | D39: 0.204 | E39: 1.03 | G39: 0.5 | H39: 0.068 | I39: =IF(B39="NT",1,0) -> 1 | J39: =1/(1+E39) -> 0.49261084 | K39: =E39/(1+E39) -> 0.50738916 | L39: =IF(F39="","",MIN(1,1-(1-F39)*J39)) | M39: =IF(L39="",$C$42,L39) -> 0.88433128 | N39: =p_w_mkt*(1-M39) -> 0.11566872 | O39: =1-((1-D39)*CE_Lg+D39*CE_Ls)-p_gap-N39 -> 0.46053756 | P39: =(1-D39)*CE_MTMg+D39*CE_MTMs -> 0.062420966 | Q39: =(1-G39)*K39 -> 0.25369458 | R39: =O39/K39 -> 0.90766141 | S39: =(O39-1)/J39 -> -1.0951087 | T39: 0 | U39: =MAX(T39,IF(OR(R39<1.75,S39<-0.2),1,0)) -> 1 | V39: =MAX(0,1-O39*(1-CE_mig_hc)-p_bb_cush)*Q39 -> 0.14392124 | W39: =MAX(0,K39-O39/1.5) -> 0.20036412 | X39: =I39*J39*MIN(H39,p_red_rate)*(1-0.3) -> 0.023448276 | Y39: =C39*(p_theta_lev*MAX(V39,W39)+X39) -> 0.12226559 | Z39: =O39-P39-p_c_liq -> 0.3481166 | AA39: =p_phi*MAX(0,p_a_spv-Z39)/p_a_spv+(1-p_phi)*MAX(0,p_a_spv-O39)/p_a_spv -> 0.4705703 | AB39: =IF(Q39>0,p_phi*MAX(0,Q39-Z39)/Q39+(1-p_phi)*MAX(0,Q39-O39)/Q39,0) -> 0 | AC39: =IF(L39="",0,L39*C39) -> 0 | AD39: =IF(L39="",0,C39) -> 0
B42: Listed asset-weighted mark (applied to non-traded) | C42: =SUM(AC6:AC39)/SUM(AD6:AD39) -> 0.88433128
B43: Total forced sales by BDCs ($bn) | C43: =SUM(Y6:Y39) -> 73.699587
B44: BDCs losing IG (count) | C44: =SUM(U6:U39) -> 34
B45: BDCs below 150% coverage (count) | C45: =COUNTIF(R6:R39,"<1.5") -> 33
B46: Asset share below 150% coverage (panic news input) | C46: =SUMPRODUCT((R6:R39<1.5)*C6:C39)/SUM(C6:C39) -> 0.99818926
A48: Sources: Q2-26 10-Qs, P/NAV 6-Oct-26; unsecured share = 10-Q debt notes (orange = 50% assumed where not computed); FSK / TCPC already below IG (Moody's Ba1 / Fitch BB+; KBRA BB+).

Sheet BDC_EAD
A1: Bank exposure to named BDC facilities (USD bn): estimated lender shares and stressed EAD
A2: Rows = facility vehicle, columns = bank. Blocks: SPV commitments, SPV outstanding, revolver commitments, revolver outstanding (inputs); stressed EAD (formulas). Lender amounts are equal-split estimates where syndicate shares are not disclosed.
A5: SPV commitments | C5: JPM | D5: BAC | E5: C | F5: WFC | G5: GS | H5: MS | I5: PNC | J5: USB | K5: TFC | L5: STT | M5: BK | N5: FCNCA | O5: CFG | P5: BARC | Q5: HSBA | R5: DBK | S5: BNP | T5: GLE | U5: UBS | V5: MUFG | W5: SMFG | X5: MFG | Y5: RY | Z5: JEF
A6: ADS | B6: =MATCH(A6,BDC!$A$6:$A$39,0) -> 4 | C6: 0 | D6: 0.5 | E6: 0.764815 | F6: 1 | G6: 0.5 | H6: 0.6 | I6: 0 | J6: 0 | K6: 0.6 | L6: 0 | M6: 0 | N6: 0 | O6: 0 | P6: 0 | Q6: 0 | R6: 0 | S6: 0 | T6: 0 | U6: 0 | V6: 0.3 | W6: 0 | X6: 0 | Y6: 0.435185 | Z6: 0
A7: ARCC | B7: =MATCH(A7,BDC!$A$6:$A$39,0) -> 3 | C7: 0 | D7: 0.475 | E7: 0 | F7: 1.15 | G7: 0 | H7: 0 | I7: 0 | J7: 0 | K7: 0 | L7: 0 | M7: 0.1 | N7: 0 | O7: 0 | P7: 0 | Q7: 0 | R7: 0 | S7: 1.465 | T7: 0 | U7: 0 | V7: 0 | W7: 1.6 | X7: 0 | Y7: 0 | Z7: 0
A8: ASIF | B8: =MATCH(A8,BDC!$A$6:$A$39,0) -> 6 | C8: 0 | D8: 0 | E8: 0 | F8: 0 | G8: 0 | H8: 0 | I8: 0 | J8: 0 | K8: 0 | L8: 0 | M8: 0 | N8: 0 | O8: 0.290625 | P8: 0 | Q8: 0 | R8: 0 | S8: 1 | T8: 0.290625 | U8: 0 | V8: 0.290625 | W8: 0 | X8: 0 | Y8: 0 | Z8: 0
A9: BBDC | B9: =MATCH(A9,BDC!$A$6:$A$39,0) -> 26 | C9: 0 | D9: 0 | E9: 0 | F9: 0 | G9: 0 | H9: 0 | I9: 0 | J9: 0 | K9: 0 | L9: 0 | M9: 0 | N9: 0 | O9: 0 | P9: 0 | Q9: 0 | R9: 0 | S9: 0 | T9: 0 | U9: 0 | V9: 0 | W9: 0 | X9: 0 | Y9: 0 | Z9: 0
A10: BCRED | B10: =MATCH(A10,BDC!$A$6:$A$39,0) -> 1 | C10: 0 | D10: 3.1 | E10: 2.6 | F10: 2.3644 | G10: 1 | H10: 1.5 | I10: 0 | J10: 0 | K10: 0 | L10: 0 | M10: 0 | N10: 0 | O10: 0 | P10: 1.1 | Q10: 0.715945 | R10: 1.425 | S10: 2.138 | T10: 2.475 | U10: 0 | V10: 2.5 | W10: 0 | X10: 0 | Y10: 1 | Z10: 0
A11: BXSL | B11: =MATCH(A11,BDC!$A$6:$A$39,0) -> 10 | C11: 0 | D11: 0.8 | E11: 0 | F11: 0 | G11: 0 | H11: 0 | I11: 0 | J11: 0 | K11: 0 | L11: 0 | M11: 0 | N11: 0 | O11: 0 | P11: 0 | Q11: 0 | R11: 0 | S11: 1.575 | T11: 0 | U11: 0 | V11: 0 | W11: 0 | X11: 0 | Y11: 0 | Z11: 0
A12: CGBD | B12: =MATCH(A12,BDC!$A$6:$A$39,0) -> 27 | C12: 0 | D12: 0 | E12: 0 | F12: 0 | G12: 0 | H12: 0 | I12: 0 | J12: 0 | K12: 0 | L12: 0 | M12: 0 | N12: 0 | O12: 0 | P12: 0 | Q12: 0 | R12: 0 | S12: 0 | T12: 0 | U12: 0 | V12: 0 | W12: 0 | X12: 0 | Y12: 0 | Z12: 0
A13: FSK | B13: =MATCH(A13,BDC!$A$6:$A$39,0) -> 11 | C13: 0 | D13: 0 | E13: 0 | F13: 0 | G13: 0 | H13: 0 | I13: 0 | J13: 0 | K13: 0 | L13: 0 | M13: 0 | N13: 0 | O13: 0 | P13: 0 | Q13: 0 | R13: 0 | S13: 0 | T13: 0 | U13: 0 | V13: 0 | W13: 0 | X13: 0 | Y13: 0 | Z13: 0
A14: GBDC | B14: =MATCH(A14,BDC!$A$6:$A$39,0) -> 14 | C14: 0 | D14: 0 | E14: 0 | F14: 0 | G14: 0 | H14: 0 | I14: 0 | J14: 0 | K14: 0 | L14: 0 | M14: 0 | N14: 0 | O14: 0 | P14: 0 | Q14: 0 | R14: 0 | S14: 0 | T14: 0 | U14: 0 | V14: 0 | W14: 0 | X14: 0 | Y14: 0 | Z14: 0
A15: GSBD | B15: =MATCH(A15,BDC!$A$6:$A$39,0) -> 24 | C15: 0 | D15: 0 | E15: 0 | F15: 0 | G15: 0 | H15: 0 | I15: 0 | J15: 0 | K15: 0 | L15: 0 | M15: 0 | N15: 0 | O15: 0 | P15: 0 | Q15: 0 | R15: 0 | S15: 0 | T15: 0 | U15: 0 | V15: 0 | W15: 0 | X15: 0 | Y15: 0 | Z15: 0
A16: HLEND | B16: =MATCH(A16,BDC!$A$6:$A$39,0) -> 5 | C16: 0 | D16: 1.5 | E16: 0 | F16: 1 | G16: 0 | H16: 1.6 | I16: 0 | J16: 0 | K16: 0 | L16: 0 | M16: 0 | N16: 0 | O16: 0 | P16: 0 | Q16: 0 | R16: 0 | S16: 1 | T16: 0 | U16: 0 | V16: 0 | W16: 0 | X16: 0 | Y16: 0 | Z16: 0
A17: HTGC | B17: =MATCH(A17,BDC!$A$6:$A$39,0) -> 21 | C17: 0 | D17: 0 | E17: 0 | F17: 0 | G17: 0.075 | H17: 0 | I17: 0 | J17: 0 | K17: 0 | L17: 0 | M17: 0 | N17: 0 | O17: 0.025 | P17: 0 | Q17: 0 | R17: 0 | S17: 0 | T17: 0 | U17: 0 | V17: 0.15 | W17: 0 | X17: 0 | Y17: 0.04 | Z17: 0
... A27: TSLX | B27: =MATCH(A27,BDC!$A$6:$A$39,0) -> 23 | C27: 0 | D27: 0 | E27: 0 | F27: 0 | G27: 0 | H27: 0 | I27: 0 | J27: 0 | K27: 0 | L27: 0 | M27: 0 | N27: 0 | O27: 0 | P27: 0 | Q27: 0 | R27: 0 | S27: 0 | T27: 0 | U27: 0 | V27: 0 | W27: 0 | X27: 0 | Y27: 0 | Z27: 0
A30: SPV outstanding | C30: JPM | D30: BAC | E30: C | F30: WFC | G30: GS | H30: MS | I30: PNC | J30: USB | K30: TFC | L30: STT | M30: BK | N30: FCNCA | O30: CFG | P30: BARC | Q30: HSBA | R30: DBK | S30: BNP | T30: GLE | U30: UBS | V30: MUFG | W30: SMFG | X30: MFG | Y30: RY | Z30: JEF
A31: ADS | B31: =MATCH(A31,BDC!$A$6:$A$39,0) -> 4 | C31: 0 | D31: 0.5 | E31: 0.688333 | F31: 0.9 | G31: 0.5 | H31: 0.45 | I31: 0 | J31: 0 | K31: 0.6 | L31: 0 | M31: 0 | N31: 0 | O31: 0 | P31: 0 | Q31: 0 | R31: 0 | S31: 0 | T31: 0 | U31: 0 | V31: 0.225 | W31: 0 | X31: 0 | Y31: 0.391667 | Z31: 0
A32: ARCC | B32: =MATCH(A32,BDC!$A$6:$A$39,0) -> 3 | C32: 0 | D32: 0.229267 | E32: 0 | F32: 0.555067 | G32: 0 | H32: 0 | I32: 0 | J32: 0 | K32: 0 | L32: 0 | M32: 0.048267 | N32: 0 | O32: 0 | P32: 0 | Q32: 0 | R32: 0 | S32: 0.674 | T32: 0 | U32: 0 | V32: 0 | W32: 0.728 | X32: 0 | Y32: 0 | Z32: 0
A33: ASIF | B33: =MATCH(A33,BDC!$A$6:$A$39,0) -> 6 | C33: 0 | D33: 0 | E33: 0 | F33: 0 | G33: 0 | H33: 0 | I33: 0 | J33: 0 | K33: 0 | L33: 0 | M33: 0 | N33: 0 | O33: 0.183851 | P33: 0 | Q33: 0 | R33: 0 | S33: 0.583 | T33: 0.183851 | U33: 0 | V33: 0.183851 | W33: 0 | X33: 0 | Y33: 0 | Z33: 0
A34: BBDC | B34: =MATCH(A34,BDC!$A$6:$A$39,0) -> 26 | C34: 0 | D34: 0 | E34: 0 | F34: 0 | G34: 0 | H34: 0 | I34: 0 | J34: 0 | K34: 0 | L34: 0 | M34: 0 | N34: 0 | O34: 0 | P34: 0 | Q34: 0 | R34: 0 | S34: 0 | T34: 0 | U34: 0 | V34: 0 | W34: 0 | X34: 0 | Y34: 0 | Z34: 0
A35: BCRED | B35: =MATCH(A35,BDC!$A$6:$A$39,0) -> 1 | C35: 0 | D35: 1.2805 | E35: 0.866931 | F35: 0.957919 | G35: 0.75 | H35: 0.73 | I35: 0 | J35: 0 | K35: 0 | L35: 0 | M35: 0 | N35: 0 | O35: 0 | P35: 0.825 | Q35: 0.329945 | R35: 0.714593 | S35: 0.72583 | T35: 0.928644 | U35: 0 | V35: 1.353 | W35: 0 | X35: 0 | Y35: 0.2 | Z35: 0
A36: BXSL | B36: =MATCH(A36,BDC!$A$6:$A$39,0) -> 10 | C36: 0 | D36: 0.3574 | E36: 0 | F36: 0 | G36: 0 | H36: 0 | I36: 0 | J36: 0 | K36: 0 | L36: 0 | M36: 0 | N36: 0 | O36: 0 | P36: 0 | Q36: 0 | R36: 0 | S36: 0.32155 | T36: 0 | U36: 0 | V36: 0 | W36: 0 | X36: 0 | Y36: 0 | Z36: 0
A37: CGBD | B37: =MATCH(A37,BDC!$A$6:$A$39,0) -> 27 | C37: 0 | D37: 0 | E37: 0 | F37: 0 | G37: 0 | H37: 0 | I37: 0 | J37: 0 | K37: 0 | L37: 0 | M37: 0 | N37: 0 | O37: 0 | P37: 0 | Q37: 0 | R37: 0 | S37: 0 | T37: 0 | U37: 0 | V37: 0 | W37: 0 | X37: 0 | Y37: 0 | Z37: 0
A38: FSK | B38: =MATCH(A38,BDC!$A$6:$A$39,0) -> 11 | C38: 0 | D38: 0 | E38: 0 | F38: 0 | G38: 0 | H38: 0 | I38: 0 | J38: 0 | K38: 0 | L38: 0 | M38: 0 | N38: 0 | O38: 0 | P38: 0 | Q38: 0 | R38: 0 | S38: 0 | T38: 0 | U38: 0 | V38: 0 | W38: 0 | X38: 0 | Y38: 0 | Z38: 0
A39: GBDC | B39: =MATCH(A39,BDC!$A$6:$A$39,0) -> 14 | C39: 0 | D39: 0 | E39: 0 | F39: 0 | G39: 0 | H39: 0 | I39: 0 | J39: 0 | K39: 0 | L39: 0 | M39: 0 | N39: 0 | O39: 0 | P39: 0 | Q39: 0 | R39: 0 | S39: 0 | T39: 0 | U39: 0 | V39: 0 | W39: 0 | X39: 0 | Y39: 0 | Z39: 0
A40: GSBD | B40: =MATCH(A40,BDC!$A$6:$A$39,0) -> 24 | C40: 0 | D40: 0 | E40: 0 | F40: 0 | G40: 0 | H40: 0 | I40: 0 | J40: 0 | K40: 0 | L40: 0 | M40: 0 | N40: 0 | O40: 0 | P40: 0 | Q40: 0 | R40: 0 | S40: 0 | T40: 0 | U40: 0 | V40: 0 | W40: 0 | X40: 0 | Y40: 0 | Z40: 0
A41: HLEND | B41: =MATCH(A41,BDC!$A$6:$A$39,0) -> 5 | C41: 0 | D41: 0.568143 | E41: 0 | F41: 0.096539 | G41: 0 | H41: 0.725788 | I41: 0 | J41: 0 | K41: 0 | L41: 0 | M41: 0 | N41: 0 | O41: 0 | P41: 0 | Q41: 0 | R41: 0 | S41: 0.5032 | T41: 0 | U41: 0 | V41: 0 | W41: 0 | X41: 0 | Y41: 0 | Z41: 0
A42: HTGC | B42: =MATCH(A42,BDC!$A$6:$A$39,0) -> 21 | C42: 0 | D42: 0 | E42: 0 | F42: 0 | G42: 0.015 | H42: 0 | I42: 0 | J42: 0 | K42: 0 | L42: 0 | M42: 0 | N42: 0 | O42: 0.005 | P42: 0 | Q42: 0 | R42: 0 | S42: 0 | T42: 0 | U42: 0 | V42: 0.03 | W42: 0 | X42: 0 | Y42: 0.008 | Z42: 0
... A52: TSLX | B52: =MATCH(A52,BDC!$A$6:$A$39,0) -> 23 | C52: 0 | D52: 0 | E52: 0 | F52: 0 | G52: 0 | H52: 0 | I52: 0 | J52: 0 | K52: 0 | L52: 0 | M52: 0 | N52: 0 | O52: 0 | P52: 0 | Q52: 0 | R52: 0 | S52: 0 | T52: 0 | U52: 0 | V52: 0 | W52: 0 | X52: 0 | Y52: 0 | Z52: 0
A55: Revolver commitments | C55: JPM | D55: BAC | E55: C | F55: WFC | G55: GS | H55: MS | I55: PNC | J55: USB | K55: TFC | L55: STT | M55: BK | N55: FCNCA | O55: CFG | P55: BARC | Q55: HSBA | R55: DBK | S55: BNP | T55: GLE | U55: UBS | V55: MUFG | W55: SMFG | X55: MFG | Y55: RY | Z55: JEF
A56: ADS | B56: =MATCH(A56,BDC!$A$6:$A$39,0) -> 4 | C56: 0.15312 | D56: 0.15312 | E56: 0.15312 | F56: 0.15312 | G56: 0.15312 | H56: 0.15312 | I56: 0.15312 | J56: 0.15312 | K56: 0.15312 | L56: 0.15312 | M56: 0 | N56: 0 | O56: 0 | P56: 0.15312 | Q56: 0.15312 | R56: 0 | S56: 0.15312 | T56: 0.15312 | U56: 0 | V56: 0.15312 | W56: 0.15312 | X56: 0.15312 | Y56: 0.15312 | Z56: 0
A57: ARCC | B57: =MATCH(A57,BDC!$A$6:$A$39,0) -> 3 | C57: 0.137025 | D57: 0.137025 | E57: 0.137025 | F57: 0.137025 | G57: 0.137025 | H57: 0.137025 | I57: 0 | J57: 0.137025 | K57: 0.137025 | L57: 0.137025 | M57: 0.137025 | N57: 0 | O57: 0 | P57: 0.137025 | Q57: 0.137025 | R57: 0.137025 | S57: 0.137025 | T57: 0.137025 | U57: 0 | V57: 0.137025 | W57: 0.137025 | X57: 0.137025 | Y57: 0.137025 | Z57: 0
A58: ASIF | B58: =MATCH(A58,BDC!$A$6:$A$39,0) -> 6 | C58: 0.172417 | D58: 0.172417 | E58: 0.172417 | F58: 0.172417 | G58: 0.172417 | H58: 0.172417 | I58: 0 | J58: 0.172417 | K58: 0.172417 | L58: 0 | M58: 0.172417 | N58: 0 | O58: 0 | P58: 0.172417 | Q58: 0.172417 | R58: 0.172417 | S58: 0.172417 | T58: 0.172417 | U58: 0 | V58: 0.172417 | W58: 0.172417 | X58: 0.172417 | Y58: 0.172417 | Z58: 0
A59: BBDC | B59: =MATCH(A59,BDC!$A$6:$A$39,0) -> 26 | C59: 0.051388 | D59: 0.051388 | E59: 0.051388 | F59: 0.051388 | G59: 0 | H59: 0 | I59: 0 | J59: 0 | K59: 0 | L59: 0.051388 | M59: 0 | N59: 0.051388 | O59: 0 | P59: 0 | Q59: 0 | R59: 0 | S59: 0.051388 | T59: 0.051388 | U59: 0 | V59: 0.051388 | W59: 0.051388 | X59: 0 | Y59: 0 | Z59: 0
A60: BCRED | B60: =MATCH(A60,BDC!$A$6:$A$39,0) -> 1 | C60: 0.2125 | D60: 0.2125 | E60: 0.2125 | F60: 0.2125 | G60: 0.2125 | H60: 0.2125 | I60: 0.2125 | J60: 0.2125 | K60: 0.2125 | L60: 0.2125 | M60: 0.2125 | N60: 0 | O60: 0 | P60: 0.2125 | Q60: 0.2125 | R60: 0.2125 | S60: 0.2125 | T60: 0.2125 | U60: 0 | V60: 0.2125 | W60: 0.2125 | X60: 0.2125 | Y60: 0.2125 | Z60: 0
A61: BXSL | B61: =MATCH(A61,BDC!$A$6:$A$39,0) -> 10 | C61: 0.115649 | D61: 0.115649 | E61: 0.115649 | F61: 0.115649 | G61: 0.115649 | H61: 0 | I61: 0 | J61: 0.115649 | K61: 0.115649 | L61: 0.115649 | M61: 0.115649 | N61: 0 | O61: 0 | P61: 0.115649 | Q61: 0 | R61: 0 | S61: 0 | T61: 0.115649 | U61: 0 | V61: 0.115649 | W61: 0.115649 | X61: 0 | Y61: 0.115649 | Z61: 0
A62: CGBD | B62: =MATCH(A62,BDC!$A$6:$A$39,0) -> 27 | C62: 0.125 | D62: 0.075 | E62: 0.075 | F62: 0 | G62: 0.05 | H62: 0.075 | I62: 0 | J62: 0 | K62: 0 | L62: 0.125 | M62: 0 | N62: 0 | O62: 0 | P62: 0.075 | Q62: 0.075 | R62: 0.075 | S62: 0 | T62: 0 | U62: 0 | V62: 0.037376 | W62: 0 | X62: 0 | Y62: 0 | Z62: 0
A63: FSK | B63: =MATCH(A63,BDC!$A$6:$A$39,0) -> 11 | C63: 0.275862 | D63: 0.301724 | E63: 0.12931 | F63: 0 | G63: 0.107759 | H63: 0.086207 | I63: 0 | J63: 0.043103 | K63: 0.258621 | L63: 0.12931 | M63: 0 | N63: 0 | O63: 0 | P63: 0.086207 | Q63: 0.172414 | R63: 0 | S63: 0.086207 | T63: 0.086207 | U63: 0.12931 | V63: 0.258621 | W63: 0.293103 | X63: 0.193966 | Y63: 0.172414 | Z63: 0
A64: GBDC | B64: =MATCH(A64,BDC!$A$6:$A$39,0) -> 14 | C64: 0.110972 | D64: 0 | E64: 0 | F64: 0.110972 | G64: 0.110972 | H64: 0.110972 | I64: 0 | J64: 0.110972 | K64: 0.110972 | L64: 0 | M64: 0 | N64: 0 | O64: 0 | P64: 0 | Q64: 0 | R64: 0 | S64: 0.110972 | T64: 0.110972 | U64: 0 | V64: 0.110972 | W64: 0.110972 | X64: 0 | Y64: 0.110972 | Z64: 0
A65: GSBD | B65: =MATCH(A65,BDC!$A$6:$A$39,0) -> 24 | C65: 0 | D65: 0.122917 | E65: 0 | F65: 0 | G65: 0 | H65: 0.122917 | I65: 0 | J65: 0 | K65: 0.122917 | L65: 0.122917 | M65: 0 | N65: 0 | O65: 0 | P65: 0.122917 | Q65: 0.122917 | R65: 0 | S65: 0.122917 | T65: 0 | U65: 0 | V65: 0.122917 | W65: 0.122917 | X65: 0 | Y65: 0 | Z65: 0
A66: HLEND | B66: =MATCH(A66,BDC!$A$6:$A$39,0) -> 5 | C66: 0.12619 | D66: 0.12619 | E66: 0.12619 | F66: 0.12619 | G66: 0.12619 | H66: 0.12619 | I66: 0 | J66: 0.12619 | K66: 0.12619 | L66: 0 | M66: 0.12619 | N66: 0 | O66: 0 | P66: 0.12619 | Q66: 0 | R66: 0.12619 | S66: 0.12619 | T66: 0.12619 | U66: 0 | V66: 0.12619 | W66: 0.12619 | X66: 0 | Y66: 0.12619 | Z66: 0
A67: HTGC | B67: =MATCH(A67,BDC!$A$6:$A$39,0) -> 21 | C67: 0 | D67: 0 | E67: 0 | F67: 0 | G67: 0 | H67: 0 | I67: 0 | J67: 0 | K67: 0 | L67: 0 | M67: 0 | N67: 0 | O67: 0 | P67: 0 | Q67: 0 | R67: 0 | S67: 0 | T67: 0 | U67: 0 | V67: 0 | W67: 0 | X67: 0 | Y67: 0 | Z67: 0
... A77: TSLX | B77: =MATCH(A77,BDC!$A$6:$A$39,0) -> 23 | C77: 0.080263 | D77: 0.080263 | E77: 0.080263 | F77: 0.080263 | G77: 0.080263 | H77: 0.080263 | I77: 0 | J77: 0 | K77: 0.080263 | L77: 0.080263 | M77: 0 | N77: 0.080263 | O77: 0.080263 | P77: 0 | Q77: 0.080263 | R77: 0 | S77: 0 | T77: 0 | U77: 0 | V77: 0.080263 | W77: 0.080263 | X77: 0.080263 | Y77: 0.080263 | Z77: 0
A80: Revolver outstanding | C80: JPM | D80: BAC | E80: C | F80: WFC | G80: GS | H80: MS | I80: PNC | J80: USB | K80: TFC | L80: STT | M80: BK | N80: FCNCA | O80: CFG | P80: BARC | Q80: HSBA | R80: DBK | S80: BNP | T80: GLE | U80: UBS | V80: MUFG | W80: SMFG | X80: MFG | Y80: RY | Z80: JEF
A81: ADS | B81: =MATCH(A81,BDC!$A$6:$A$39,0) -> 4 | C81: 0 | D81: 0 | E81: 0 | F81: 0 | G81: 0 | H81: 0 | I81: 0 | J81: 0 | K81: 0 | L81: 0 | M81: 0 | N81: 0 | O81: 0 | P81: 0 | Q81: 0 | R81: 0 | S81: 0 | T81: 0 | U81: 0 | V81: 0 | W81: 0 | X81: 0 | Y81: 0 | Z81: 0
A82: ARCC | B82: =MATCH(A82,BDC!$A$6:$A$39,0) -> 3 | C82: 0.03915 | D82: 0.03915 | E82: 0.03915 | F82: 0.03915 | G82: 0.03915 | H82: 0.03915 | I82: 0 | J82: 0.03915 | K82: 0.03915 | L82: 0.03915 | M82: 0.03915 | N82: 0 | O82: 0 | P82: 0.03915 | Q82: 0.03915 | R82: 0.03915 | S82: 0.03915 | T82: 0.03915 | U82: 0 | V82: 0.03915 | W82: 0.03915 | X82: 0.03915 | Y82: 0.03915 | Z82: 0
A83: ASIF | B83: =MATCH(A83,BDC!$A$6:$A$39,0) -> 6 | C83: 0.087065 | D83: 0.087065 | E83: 0.087065 | F83: 0.087065 | G83: 0.087065 | H83: 0.087065 | I83: 0 | J83: 0.087065 | K83: 0.087065 | L83: 0 | M83: 0.087065 | N83: 0 | O83: 0 | P83: 0.087065 | Q83: 0.087065 | R83: 0.087065 | S83: 0.087065 | T83: 0.087065 | U83: 0 | V83: 0.087065 | W83: 0.087065 | X83: 0.087065 | Y83: 0.087065 | Z83: 0
A84: BBDC | B84: =MATCH(A84,BDC!$A$6:$A$39,0) -> 26 | C84: 0.017327 | D84: 0.017327 | E84: 0.017327 | F84: 0.017327 | G84: 0 | H84: 0 | I84: 0 | J84: 0 | K84: 0 | L84: 0.017327 | M84: 0 | N84: 0.017327 | O84: 0 | P84: 0 | Q84: 0 | R84: 0 | S84: 0.017327 | T84: 0.017327 | U84: 0 | V84: 0.017327 | W84: 0.017327 | X84: 0 | Y84: 0 | Z84: 0
A85: BCRED | B85: =MATCH(A85,BDC!$A$6:$A$39,0) -> 1 | C85: 0.082301 | D85: 0.082301 | E85: 0.082301 | F85: 0.082301 | G85: 0.082301 | H85: 0.082301 | I85: 0.082301 | J85: 0.082301 | K85: 0.082301 | L85: 0.082301 | M85: 0.082301 | N85: 0 | O85: 0 | P85: 0.082301 | Q85: 0.082301 | R85: 0.082301 | S85: 0.082301 | T85: 0.082301 | U85: 0 | V85: 0.082301 | W85: 0.082301 | X85: 0.082301 | Y85: 0.082301 | Z85: 0
A86: BXSL | B86: =MATCH(A86,BDC!$A$6:$A$39,0) -> 10 | C86: 0.063204 | D86: 0.063204 | E86: 0.063204 | F86: 0.063204 | G86: 0.063204 | H86: 0 | I86: 0 | J86: 0.063204 | K86: 0.063204 | L86: 0.063204 | M86: 0.063204 | N86: 0 | O86: 0 | P86: 0.063204 | Q86: 0 | R86: 0 | S86: 0 | T86: 0.063204 | U86: 0 | V86: 0.063204 | W86: 0.063204 | X86: 0 | Y86: 0.063204 | Z86: 0
A87: CGBD | B87: =MATCH(A87,BDC!$A$6:$A$39,0) -> 27 | C87: 0.047423 | D87: 0.028454 | E87: 0.028454 | F87: 0 | G87: 0.018969 | H87: 0.028454 | I87: 0 | J87: 0 | K87: 0 | L87: 0.047423 | M87: 0 | N87: 0 | O87: 0 | P87: 0.028454 | Q87: 0.028454 | R87: 0.028454 | S87: 0 | T87: 0 | U87: 0 | V87: 0.01418 | W87: 0 | X87: 0 | Y87: 0 | Z87: 0
A88: FSK | B88: =MATCH(A88,BDC!$A$6:$A$39,0) -> 11 | C88: 0.049906 | D88: 0.054585 | E88: 0.023394 | F88: 0 | G88: 0.019495 | H88: 0.015596 | I88: 0 | J88: 0.007798 | K88: 0.046787 | L88: 0.023394 | M88: 0 | N88: 0 | O88: 0 | P88: 0.015596 | Q88: 0.031191 | R88: 0 | S88: 0.015596 | T88: 0.015596 | U88: 0.023394 | V88: 0.046787 | W88: 0.053026 | X88: 0.03509 | Y88: 0.031191 | Z88: 0
A89: GBDC | B89: =MATCH(A89,BDC!$A$6:$A$39,0) -> 14 | C89: 0.015087 | D89: 0 | E89: 0 | F89: 0.015087 | G89: 0.015087 | H89: 0.015087 | I89: 0 | J89: 0.015087 | K89: 0.015087 | L89: 0 | M89: 0 | N89: 0 | O89: 0 | P89: 0 | Q89: 0 | R89: 0 | S89: 0.015087 | T89: 0.015087 | U89: 0 | V89: 0.015087 | W89: 0.015087 | X89: 0 | Y89: 0.015087 | Z89: 0
A90: GSBD | B90: =MATCH(A90,BDC!$A$6:$A$39,0) -> 24 | C90: 0 | D90: 0.056617 | E90: 0 | F90: 0 | G90: 0 | H90: 0.056617 | I90: 0 | J90: 0 | K90: 0.056617 | L90: 0.056617 | M90: 0 | N90: 0 | O90: 0 | P90: 0.056617 | Q90: 0.056617 | R90: 0 | S90: 0.056617 | T90: 0 | U90: 0 | V90: 0.056617 | W90: 0.056617 | X90: 0 | Y90: 0 | Z90: 0
A91: HLEND | B91: =MATCH(A91,BDC!$A$6:$A$39,0) -> 5 | C91: 0.021171 | D91: 0.021171 | E91: 0.021171 | F91: 0.021171 | G91: 0.021171 | H91: 0.021171 | I91: 0 | J91: 0.021171 | K91: 0.021171 | L91: 0 | M91: 0.021171 | N91: 0 | O91: 0 | P91: 0.021171 | Q91: 0 | R91: 0.021171 | S91: 0.021171 | T91: 0.021171 | U91: 0 | V91: 0.021171 | W91: 0.021171 | X91: 0 | Y91: 0.021171 | Z91: 0
A92: HTGC | B92: =MATCH(A92,BDC!$A$6:$A$39,0) -> 21 | C92: 0 | D92: 0 | E92: 0 | F92: 0 | G92: 0 | H92: 0 | I92: 0 | J92: 0 | K92: 0 | L92: 0 | M92: 0 | N92: 0 | O92: 0 | P92: 0 | Q92: 0 | R92: 0 | S92: 0 | T92: 0 | U92: 0 | V92: 0 | W92: 0 | X92: 0 | Y92: 0 | Z92: 0
... A102: TSLX | B102: =MATCH(A102,BDC!$A$6:$A$39,0) -> 23 | C102: 0.021896 | D102: 0.021896 | E102: 0.021896 | F102: 0.021896 | G102: 0.021896 | H102: 0.021896 | I102: 0 | J102: 0 | K102: 0.021896 | L102: 0.021896 | M102: 0 | N102: 0.021896 | O102: 0.021896 | P102: 0 | Q102: 0.021896 | R102: 0 | S102: 0 | T102: 0 | U102: 0 | V102: 0.021896 | W102: 0.021896 | X102: 0.021896 | Y102: 0.021896 | Z102: 0
A105: Stressed EAD, SPV = outstanding + CCF x undrawn | C105: JPM | D105: BAC | E105: C | F105: WFC | G105: GS | H105: MS | I105: PNC | J105: USB | K105: TFC | L105: STT | M105: BK | N105: FCNCA | O105: CFG | P105: BARC | Q105: HSBA | R105: DBK | S105: BNP | T105: GLE | U105: UBS | V105: MUFG | W105: SMFG | X105: MFG | Y105: RY | Z105: JEF | AB105: LR SPV (std) | AC105: LR revolver (std)
A106: ADS | C106: =C31+p_ccf_bl*(C6-C31) -> 0 | D106: =D31+p_ccf_bl*(D6-D31) -> 0.5 | E106: =E31+p_ccf_bl*(E6-E31) -> 0.7571668 | F106: =F31+p_ccf_bl*(F6-F31) -> 0.99 | G106: =G31+p_ccf_bl*(G6-G31) -> 0.5 | H106: =H31+p_ccf_bl*(H6-H31) -> 0.585 | I106: =I31+p_ccf_bl*(I6-I31) -> 0 | J106: =J31+p_ccf_bl*(J6-J31) -> 0 | ... Z106: =Z31+p_ccf_bl*(Z6-Z31) -> 0 | AB106: =INDEX(BDC!$AA$6:$AA$39,$B6) -> 0.4404292 | AC106: =INDEX(BDC!$AB$6:$AB$39,$B6) -> 0
A107: ARCC | C107: =C32+p_ccf_bl*(C7-C32) -> 0 | D107: =D32+p_ccf_bl*(D7-D32) -> 0.4504267 | E107: =E32+p_ccf_bl*(E7-E32) -> 0 | F107: =F32+p_ccf_bl*(F7-F32) -> 1.0905067 | G107: =G32+p_ccf_bl*(G7-G32) -> 0 | H107: =H32+p_ccf_bl*(H7-H32) -> 0 | I107: =I32+p_ccf_bl*(I7-I32) -> 0 | J107: =J32+p_ccf_bl*(J7-J32) -> 0 | ... Z107: =Z32+p_ccf_bl*(Z7-Z32) -> 0 | AB107: =INDEX(BDC!$AA$6:$AA$39,$B7) -> 0.34568151 | AC107: =INDEX(BDC!$AB$6:$AB$39,$B7) -> 0
A108: ASIF | C108: =C33+p_ccf_bl*(C8-C33) -> 0 | D108: =D33+p_ccf_bl*(D8-D33) -> 0 | E108: =E33+p_ccf_bl*(E8-E33) -> 0 | F108: =F33+p_ccf_bl*(F8-F33) -> 0 | G108: =G33+p_ccf_bl*(G8-G33) -> 0 | H108: =H33+p_ccf_bl*(H8-H33) -> 0 | I108: =I33+p_ccf_bl*(I8-I33) -> 0 | J108: =J33+p_ccf_bl*(J8-J33) -> 0 | ... Z108: =Z33+p_ccf_bl*(Z8-Z33) -> 0 | AB108: =INDEX(BDC!$AA$6:$AA$39,$B8) -> 0.47336689 | AC108: =INDEX(BDC!$AB$6:$AB$39,$B8) -> 0
A109: BBDC | C109: =C34+p_ccf_bl*(C9-C34) -> 0 | D109: =D34+p_ccf_bl*(D9-D34) -> 0 | E109: =E34+p_ccf_bl*(E9-E34) -> 0 | F109: =F34+p_ccf_bl*(F9-F34) -> 0 | G109: =G34+p_ccf_bl*(G9-G34) -> 0 | H109: =H34+p_ccf_bl*(H9-H34) -> 0 | I109: =I34+p_ccf_bl*(I9-I34) -> 0 | J109: =J34+p_ccf_bl*(J9-J34) -> 0 | ... Z109: =Z34+p_ccf_bl*(Z9-Z34) -> 0 | AB109: =INDEX(BDC!$AA$6:$AA$39,$B9) -> 0.4229744 | AC109: =INDEX(BDC!$AB$6:$AB$39,$B9) -> 0
A110: BCRED | C110: =C35+p_ccf_bl*(C10-C35) -> 0 | D110: =D35+p_ccf_bl*(D10-D35) -> 2.91805 | E110: =E35+p_ccf_bl*(E10-E35) -> 2.4266931 | F110: =F35+p_ccf_bl*(F10-F35) -> 2.2237519 | G110: =G35+p_ccf_bl*(G10-G35) -> 0.975 | H110: =H35+p_ccf_bl*(H10-H35) -> 1.423 | I110: =I35+p_ccf_bl*(I10-I35) -> 0 | J110: =J35+p_ccf_bl*(J10-J35) -> 0 | ... Z110: =Z35+p_ccf_bl*(Z10-Z35) -> 0 | AB110: =INDEX(BDC!$AA$6:$AA$39,$B10) -> 0.48734988 | AC110: =INDEX(BDC!$AB$6:$AB$39,$B10) -> 0
A111: BXSL | C111: =C36+p_ccf_bl*(C11-C36) -> 0 | D111: =D36+p_ccf_bl*(D11-D36) -> 0.75574 | E111: =E36+p_ccf_bl*(E11-E36) -> 0 | F111: =F36+p_ccf_bl*(F11-F36) -> 0 | G111: =G36+p_ccf_bl*(G11-G36) -> 0 | H111: =H36+p_ccf_bl*(H11-H36) -> 0 | I111: =I36+p_ccf_bl*(I11-I36) -> 0 | J111: =J36+p_ccf_bl*(J11-J36) -> 0 | ... Z111: =Z36+p_ccf_bl*(Z11-Z36) -> 0 | AB111: =INDEX(BDC!$AA$6:$AA$39,$B11) -> 0.35227306 | AC111: =INDEX(BDC!$AB$6:$AB$39,$B11) -> 0
A112: CGBD | C112: =C37+p_ccf_bl*(C12-C37) -> 0 | D112: =D37+p_ccf_bl*(D12-D37) -> 0 | E112: =E37+p_ccf_bl*(E12-E37) -> 0 | F112: =F37+p_ccf_bl*(F12-F37) -> 0 | G112: =G37+p_ccf_bl*(G12-G37) -> 0 | H112: =H37+p_ccf_bl*(H12-H37) -> 0 | I112: =I37+p_ccf_bl*(I12-I37) -> 0 | J112: =J37+p_ccf_bl*(J12-J37) -> 0 | ... Z112: =Z37+p_ccf_bl*(Z12-Z37) -> 0 | AB112: =INDEX(BDC!$AA$6:$AA$39,$B12) -> 0.51167028 | AC112: =INDEX(BDC!$AB$6:$AB$39,$B12) -> 0
A113: FSK | C113: =C38+p_ccf_bl*(C13-C38) -> 0 | D113: =D38+p_ccf_bl*(D13-D38) -> 0 | E113: =E38+p_ccf_bl*(E13-E38) -> 0 | F113: =F38+p_ccf_bl*(F13-F38) -> 0 | G113: =G38+p_ccf_bl*(G13-G38) -> 0 | H113: =H38+p_ccf_bl*(H13-H38) -> 0 | I113: =I38+p_ccf_bl*(I13-I38) -> 0 | J113: =J38+p_ccf_bl*(J13-J38) -> 0 | ... Z113: =Z38+p_ccf_bl*(Z13-Z38) -> 0 | AB113: =INDEX(BDC!$AA$6:$AA$39,$B13) -> 0.58012533 | AC113: =INDEX(BDC!$AB$6:$AB$39,$B13) -> 0
A114: GBDC | C114: =C39+p_ccf_bl*(C14-C39) -> 0 | D114: =D39+p_ccf_bl*(D14-D39) -> 0 | E114: =E39+p_ccf_bl*(E14-E39) -> 0 | F114: =F39+p_ccf_bl*(F14-F39) -> 0 | G114: =G39+p_ccf_bl*(G14-G39) -> 0 | H114: =H39+p_ccf_bl*(H14-H39) -> 0 | I114: =I39+p_ccf_bl*(I14-I39) -> 0 | J114: =J39+p_ccf_bl*(J14-J39) -> 0 | ... Z114: =Z39+p_ccf_bl*(Z14-Z39) -> 0 | AB114: =INDEX(BDC!$AA$6:$AA$39,$B14) -> 0.42138503 | AC114: =INDEX(BDC!$AB$6:$AB$39,$B14) -> 0
A115: GSBD | C115: =C40+p_ccf_bl*(C15-C40) -> 0 | D115: =D40+p_ccf_bl*(D15-D40) -> 0 | E115: =E40+p_ccf_bl*(E15-E40) -> 0 | F115: =F40+p_ccf_bl*(F15-F40) -> 0 | G115: =G40+p_ccf_bl*(G15-G40) -> 0 | H115: =H40+p_ccf_bl*(H15-H40) -> 0 | I115: =I40+p_ccf_bl*(I15-I40) -> 0 | J115: =J40+p_ccf_bl*(J15-J40) -> 0 | ... Z115: =Z40+p_ccf_bl*(Z15-Z40) -> 0 | AB115: =INDEX(BDC!$AA$6:$AA$39,$B15) -> 0.4759669 | AC115: =INDEX(BDC!$AB$6:$AB$39,$B15) -> 0
A116: HLEND | C116: =C41+p_ccf_bl*(C16-C41) -> 0 | D116: =D41+p_ccf_bl*(D16-D41) -> 1.4068143 | E116: =E41+p_ccf_bl*(E16-E41) -> 0 | F116: =F41+p_ccf_bl*(F16-F41) -> 0.9096539 | G116: =G41+p_ccf_bl*(G16-G41) -> 0 | H116: =H41+p_ccf_bl*(H16-H41) -> 1.5125788 | I116: =I41+p_ccf_bl*(I16-I41) -> 0 | J116: =J41+p_ccf_bl*(J16-J41) -> 0 | ... Z116: =Z41+p_ccf_bl*(Z16-Z41) -> 0 | AB116: =INDEX(BDC!$AA$6:$AA$39,$B16) -> 0.46186977 | AC116: =INDEX(BDC!$AB$6:$AB$39,$B16) -> 0
A117: HTGC | C117: =C42+p_ccf_bl*(C17-C42) -> 0 | D117: =D42+p_ccf_bl*(D17-D42) -> 0 | E117: =E42+p_ccf_bl*(E17-E42) -> 0 | F117: =F42+p_ccf_bl*(F17-F42) -> 0 | G117: =G42+p_ccf_bl*(G17-G42) -> 0.069 | H117: =H42+p_ccf_bl*(H17-H42) -> 0 | I117: =I42+p_ccf_bl*(I17-I42) -> 0 | J117: =J42+p_ccf_bl*(J17-J42) -> 0 | ... Z117: =Z42+p_ccf_bl*(Z17-Z42) -> 0 | AB117: =INDEX(BDC!$AA$6:$AA$39,$B17) -> 0.34386017 | AC117: =INDEX(BDC!$AB$6:$AB$39,$B17) -> 0
... A127: TSLX | C127: =C52+p_ccf_bl*(C27-C52) -> 0 | D127: =D52+p_ccf_bl*(D27-D52) -> 0 | E127: =E52+p_ccf_bl*(E27-E52) -> 0 | F127: =F52+p_ccf_bl*(F27-F52) -> 0 | G127: =G52+p_ccf_bl*(G27-G52) -> 0 | H127: =H52+p_ccf_bl*(H27-H52) -> 0 | I127: =I52+p_ccf_bl*(I27-I52) -> 0 | J127: =J52+p_ccf_bl*(J27-J52) -> 0 | ... Z127: =Z52+p_ccf_bl*(Z27-Z52) -> 0 | AB127: =INDEX(BDC!$AA$6:$AA$39,$B27) -> 0.30097901 | AC127: =INDEX(BDC!$AB$6:$AB$39,$B27) -> 0
A130: Stressed EAD, revolver (100% drawn if BDC loses IG) | C130: JPM | D130: BAC | E130: C | F130: WFC | G130: GS | H130: MS | I130: PNC | J130: USB | K130: TFC | L130: STT | M130: BK | N130: FCNCA | O130: CFG | P130: BARC | Q130: HSBA | R130: DBK | S130: BNP | T130: GLE | U130: UBS | V130: MUFG | W130: SMFG | X130: MFG | Y130: RY | Z130: JEF | AB130: Revolver CCF
A131: ADS | C131: =C81+$AB131*(C56-C81) -> 0.15312 | D131: =D81+$AB131*(D56-D81) -> 0.15312 | E131: =E81+$AB131*(E56-E81) -> 0.15312 | F131: =F81+$AB131*(F56-F81) -> 0.15312 | G131: =G81+$AB131*(G56-G81) -> 0.15312 | H131: =H81+$AB131*(H56-H81) -> 0.15312 | I131: =I81+$AB131*(I56-I81) -> 0.15312 | J131: =J81+$AB131*(J56-J81) -> 0.15312 | ... Z131: =Z81+$AB131*(Z56-Z81) -> 0 | AB131: =MAX(p_ccf_bl,INDEX(BDC!$U$6:$U$39,$B6)*p_ccf_dg) -> 1
A132: ARCC | C132: =C82+$AB132*(C57-C82) -> 0.137025 | D132: =D82+$AB132*(D57-D82) -> 0.137025 | E132: =E82+$AB132*(E57-E82) -> 0.137025 | F132: =F82+$AB132*(F57-F82) -> 0.137025 | G132: =G82+$AB132*(G57-G82) -> 0.137025 | H132: =H82+$AB132*(H57-H82) -> 0.137025 | I132: =I82+$AB132*(I57-I82) -> 0 | J132: =J82+$AB132*(J57-J82) -> 0.137025 | ... Z132: =Z82+$AB132*(Z57-Z82) -> 0 | AB132: =MAX(p_ccf_bl,INDEX(BDC!$U$6:$U$39,$B7)*p_ccf_dg) -> 1
A133: ASIF | C133: =C83+$AB133*(C58-C83) -> 0.172417 | D133: =D83+$AB133*(D58-D83) -> 0.172417 | E133: =E83+$AB133*(E58-E83) -> 0.172417 | F133: =F83+$AB133*(F58-F83) -> 0.172417 | G133: =G83+$AB133*(G58-G83) -> 0.172417 | H133: =H83+$AB133*(H58-H83) -> 0.172417 | I133: =I83+$AB133*(I58-I83) -> 0 | J133: =J83+$AB133*(J58-J83) -> 0.172417 | ... Z133: =Z83+$AB133*(Z58-Z83) -> 0 | AB133: =MAX(p_ccf_bl,INDEX(BDC!$U$6:$U$39,$B8)*p_ccf_dg) -> 1
A134: BBDC | C134: =C84+$AB134*(C59-C84) -> 0.051388 | D134: =D84+$AB134*(D59-D84) -> 0.051388 | E134: =E84+$AB134*(E59-E84) -> 0.051388 | F134: =F84+$AB134*(F59-F84) -> 0.051388 | G134: =G84+$AB134*(G59-G84) -> 0 | H134: =H84+$AB134*(H59-H84) -> 0 | I134: =I84+$AB134*(I59-I84) -> 0 | J134: =J84+$AB134*(J59-J84) -> 0 | ... Z134: =Z84+$AB134*(Z59-Z84) -> 0 | AB134: =MAX(p_ccf_bl,INDEX(BDC!$U$6:$U$39,$B9)*p_ccf_dg) -> 1
A135: BCRED | C135: =C85+$AB135*(C60-C85) -> 0.2125 | D135: =D85+$AB135*(D60-D85) -> 0.2125 | E135: =E85+$AB135*(E60-E85) -> 0.2125 | F135: =F85+$AB135*(F60-F85) -> 0.2125 | G135: =G85+$AB135*(G60-G85) -> 0.2125 | H135: =H85+$AB135*(H60-H85) -> 0.2125 | I135: =I85+$AB135*(I60-I85) -> 0.2125 | J135: =J85+$AB135*(J60-J85) -> 0.2125 | ... Z135: =Z85+$AB135*(Z60-Z85) -> 0 | AB135: =MAX(p_ccf_bl,INDEX(BDC!$U$6:$U$39,$B10)*p_ccf_dg) -> 1
A136: BXSL | C136: =C86+$AB136*(C61-C86) -> 0.115649 | D136: =D86+$AB136*(D61-D86) -> 0.115649 | E136: =E86+$AB136*(E61-E86) -> 0.115649 | F136: =F86+$AB136*(F61-F86) -> 0.115649 | G136: =G86+$AB136*(G61-G86) -> 0.115649 | H136: =H86+$AB136*(H61-H86) -> 0 | I136: =I86+$AB136*(I61-I86) -> 0 | J136: =J86+$AB136*(J61-J86) -> 0.115649 | ... Z136: =Z86+$AB136*(Z61-Z86) -> 0 | AB136: =MAX(p_ccf_bl,INDEX(BDC!$U$6:$U$39,$B11)*p_ccf_dg) -> 1
A137: CGBD | C137: =C87+$AB137*(C62-C87) -> 0.125 | D137: =D87+$AB137*(D62-D87) -> 0.075 | E137: =E87+$AB137*(E62-E87) -> 0.075 | F137: =F87+$AB137*(F62-F87) -> 0 | G137: =G87+$AB137*(G62-G87) -> 0.05 | H137: =H87+$AB137*(H62-H87) -> 0.075 | I137: =I87+$AB137*(I62-I87) -> 0 | J137: =J87+$AB137*(J62-J87) -> 0 | ... Z137: =Z87+$AB137*(Z62-Z87) -> 0 | AB137: =MAX(p_ccf_bl,INDEX(BDC!$U$6:$U$39,$B12)*p_ccf_dg) -> 1
A138: FSK | C138: =C88+$AB138*(C63-C88) -> 0.275862 | D138: =D88+$AB138*(D63-D88) -> 0.301724 | E138: =E88+$AB138*(E63-E88) -> 0.12931 | F138: =F88+$AB138*(F63-F88) -> 0 | G138: =G88+$AB138*(G63-G88) -> 0.107759 | H138: =H88+$AB138*(H63-H88) -> 0.086207 | I138: =I88+$AB138*(I63-I88) -> 0 | J138: =J88+$AB138*(J63-J88) -> 0.043103 | ... Z138: =Z88+$AB138*(Z63-Z88) -> 0 | AB138: =MAX(p_ccf_bl,INDEX(BDC!$U$6:$U$39,$B13)*p_ccf_dg) -> 1
A139: GBDC | C139: =C89+$AB139*(C64-C89) -> 0.110972 | D139: =D89+$AB139*(D64-D89) -> 0 | E139: =E89+$AB139*(E64-E89) -> 0 | F139: =F89+$AB139*(F64-F89) -> 0.110972 | G139: =G89+$AB139*(G64-G89) -> 0.110972 | H139: =H89+$AB139*(H64-H89) -> 0.110972 | I139: =I89+$AB139*(I64-I89) -> 0 | J139: =J89+$AB139*(J64-J89) -> 0.110972 | ... Z139: =Z89+$AB139*(Z64-Z89) -> 0 | AB139: =MAX(p_ccf_bl,INDEX(BDC!$U$6:$U$39,$B14)*p_ccf_dg) -> 1
A140: GSBD | C140: =C90+$AB140*(C65-C90) -> 0 | D140: =D90+$AB140*(D65-D90) -> 0.122917 | E140: =E90+$AB140*(E65-E90) -> 0 | F140: =F90+$AB140*(F65-F90) -> 0 | G140: =G90+$AB140*(G65-G90) -> 0 | H140: =H90+$AB140*(H65-H90) -> 0.122917 | I140: =I90+$AB140*(I65-I90) -> 0 | J140: =J90+$AB140*(J65-J90) -> 0 | ... Z140: =Z90+$AB140*(Z65-Z90) -> 0 | AB140: =MAX(p_ccf_bl,INDEX(BDC!$U$6:$U$39,$B15)*p_ccf_dg) -> 1
A141: HLEND | C141: =C91+$AB141*(C66-C91) -> 0.12619 | D141: =D91+$AB141*(D66-D91) -> 0.12619 | E141: =E91+$AB141*(E66-E91) -> 0.12619 | F141: =F91+$AB141*(F66-F91) -> 0.12619 | G141: =G91+$AB141*(G66-G91) -> 0.12619 | H141: =H91+$AB141*(H66-H91) -> 0.12619 | I141: =I91+$AB141*(I66-I91) -> 0 | J141: =J91+$AB141*(J66-J91) -> 0.12619 | ... Z141: =Z91+$AB141*(Z66-Z91) -> 0 | AB141: =MAX(p_ccf_bl,INDEX(BDC!$U$6:$U$39,$B16)*p_ccf_dg) -> 1
A142: HTGC | C142: =C92+$AB142*(C67-C92) -> 0 | D142: =D92+$AB142*(D67-D92) -> 0 | E142: =E92+$AB142*(E67-E92) -> 0 | F142: =F92+$AB142*(F67-F92) -> 0 | G142: =G92+$AB142*(G67-G92) -> 0 | H142: =H92+$AB142*(H67-H92) -> 0 | I142: =I92+$AB142*(I67-I92) -> 0 | J142: =J92+$AB142*(J67-J92) -> 0 | ... Z142: =Z92+$AB142*(Z67-Z92) -> 0 | AB142: =MAX(p_ccf_bl,INDEX(BDC!$U$6:$U$39,$B17)*p_ccf_dg) -> 1
... A152: TSLX | C152: =C102+$AB152*(C77-C102) -> 0.080263 | D152: =D102+$AB152*(D77-D102) -> 0.080263 | E152: =E102+$AB152*(E77-E102) -> 0.080263 | F152: =F102+$AB152*(F77-F102) -> 0.080263 | G152: =G102+$AB152*(G77-G102) -> 0.080263 | H152: =H102+$AB152*(H77-H102) -> 0.080263 | I152: =I102+$AB152*(I77-I102) -> 0 | J152: =J102+$AB152*(J77-J102) -> 0 | ... Z152: =Z102+$AB152*(Z77-Z102) -> 0 | AB152: =MAX(p_ccf_bl,INDEX(BDC!$U$6:$U$39,$B27)*p_ccf_dg) -> 1
A154: Undrawn BDC commitments drawn in stress ($bn) | C154: =SUM(C106:C127)-SUM(C31:C52)+SUM(C131:C152)-SUM(C81:C102) -> 2.2342052 | D154: =SUM(D106:D127)-SUM(D31:D52)+SUM(D131:D152)-SUM(D81:D102) -> 4.806813 | E154: =SUM(E106:E127)-SUM(E31:E52)+SUM(E131:E152)-SUM(E81:E102) -> 2.7687279 | F154: =SUM(F106:F127)-SUM(F31:F52)+SUM(F131:F152)-SUM(F81:F102) -> 4.6608101 | G154: =SUM(G106:G127)-SUM(G31:G52)+SUM(G131:G152)-SUM(G81:G102) -> 1.653726 | H154: =SUM(H106:H127)-SUM(H31:H52)+SUM(H131:H152)-SUM(H81:H102) -> 2.9527958 | I154: =SUM(I106:I127)-SUM(I31:I52)+SUM(I131:I152)-SUM(I81:I102) -> 0.404874 | J154: =SUM(J106:J127)-SUM(J31:J52)+SUM(J131:J152)-SUM(J81:J102) -> 1.115604 | ... Z154: =SUM(Z106:Z127)-SUM(Z31:Z52)+SUM(Z131:Z152)-SUM(Z81:Z102) -> 0

Sheet AI_Deals
A1: AI / GPU / data-centre deals: per-deal loss rate and estimated bank holds (USD bn)
A2: GPU loans: LGD = max(0, 1 - (1 - liquidation cost) x collateral(t) / balance(t)), collateral(t) = (1 - annual decline)^t, balance(t) = LTV x (1 - share repaid). Holds are deal-role estimates (pre-sell-down), not disclosed positions.
A5: # | B5: Deal | C5: Category | D5: Lessee key | E5: PD 3-yr | F5: PD | AI factor | G5: LTV / cost | H5: Share repaid by t | I5: Cash-collat. share | J5: LGD (non-GPU) | K5: In syndication (1/0) | L5: Senior backstopped share | M5: MTM already quoted (pts) | N5: Balance(t) / cost | O5: Collateral(t) / cost | P5: LGD GPU | Q5: Loss rate | R5: RCF (1/0) | S5: Size ($bn) | T5: JPM | U5: BAC | V5: C | W5: WFC | X5: GS | Y5: MS | Z5: PNC | AA5: USB | AB5: TFC | AC5: STT | AD5: BK | AE5: FCNCA | AF5: CFG | AG5: BARC | AH5: HSBA | AI5: DBK | AJ5: BNP | AK5: GLE | AL5: UBS | AM5: MUFG | AN5: SMFG | AO5: MFG | AP5: RY | AQ5: JEF | AR5: Rating / lessee | AS5: Model note
A6: 0 | B6: CoreWeave DDTL 1.0 | C6: NONE | E6: =IF(C6="NONE",0,IFERROR(INDEX(rng_lessee_pd,MATCH(D6,rng_lessee_key,0)),g_pd_unrated)) -> 0 | F6: =IF(E6<=0,0,NORMSDIST((NORMSINV(E6)-SQRT(g_rho_ai)*p_z_ai)/SQRT(1-g_rho_ai))) -> 0 | G6: 0 | H6: 0 | I6: 0 | J6: 0 | K6: 0 | L6: 0 | M6: 0 | N6: =G6*(1-H6) -> 0 | O6: =(1-p_gpu_r)^g_t_def -> 0.2809 | P6: =IF(N6>0,MAX(0,1-(1-g_c_gpu)*O6/N6)*(1-I6),0) -> 0 | Q6: =IF(C6="GPU",F6*P6+K6*p_uw_drop,IF(C6="RCF",p_ccf_ai*F6*J6,IF(C6="DC",F6*J6+K6*p_uw_drop+M6/100,IF(C6="UNSEC",F6*J6,IF(C6="MARGIN",F6*MAX(0,G6-(1-p_oai_drop)*(1-g_c_gpu))/G6,IF(C6="ANTH",F6*(L6*0.1+(1-L6)*0.7)+p_uw_drop,0)))))) -> 0 | R6: =IF(C6="RCF",1,0) -> 0 | S6: 2.3 | T6: 0 | U6: 0 | V6: 0 | W6: 0 | X6: 0 | Y6: 0 | Z6: 0 | AA6: 0 | AB6: 0 | AC6: 0 | AD6: 0 | AE6: 0 | AF6: 0 | AG6: 0 | AH6: 0 | AI6: 0 | AJ6: 0 | AK6: 0 | AL6: 0 | AM6: 0 | AN6: 0 | AO6: 0 | AP6: 0 | AQ6: 0 | AR6: CoreWeave: S&P B+ (May-2025; B unsecured, recovery 5); Fitch BB- (notes, RR4) | AS6: no bank hold attributed (non-bank, distributed or n.d.)
A7: 1 | B7: CoreWeave DDTL 2.0 | C7: NONE | E7: =IF(C7="NONE",0,IFERROR(INDEX(rng_lessee_pd,MATCH(D7,rng_lessee_key,0)),g_pd_unrated)) -> 0 | F7: =IF(E7<=0,0,NORMSDIST((NORMSINV(E7)-SQRT(g_rho_ai)*p_z_ai)/SQRT(1-g_rho_ai))) -> 0 | G7: 0 | H7: 0 | I7: 0 | J7: 0 | K7: 0 | L7: 0 | M7: 0 | N7: =G7*(1-H7) -> 0 | O7: =(1-p_gpu_r)^g_t_def -> 0.2809 | P7: =IF(N7>0,MAX(0,1-(1-g_c_gpu)*O7/N7)*(1-I7),0) -> 0 | Q7: =IF(C7="GPU",F7*P7+K7*p_uw_drop,IF(C7="RCF",p_ccf_ai*F7*J7,IF(C7="DC",F7*J7+K7*p_uw_drop+M7/100,IF(C7="UNSEC",F7*J7,IF(C7="MARGIN",F7*MAX(0,G7-(1-p_oai_drop)*(1-g_c_gpu))/G7,IF(C7="ANTH",F7*(L7*0.1+(1-L7)*0.7)+p_uw_drop,0)))))) -> 0 | R7: =IF(C7="RCF",1,0) -> 0 | S7: 7.6 | T7: 0 | U7: 0 | V7: 0 | W7: 0 | X7: 0 | Y7: 0 | Z7: 0 | AA7: 0 | AB7: 0 | AC7: 0 | AD7: 0 | AE7: 0 | AF7: 0 | AG7: 0 | AH7: 0 | AI7: 0 | AJ7: 0 | AK7: 0 | AL7: 0 | AM7: 0 | AN7: 0 | AO7: 0 | AP7: 0 | AQ7: 0 | AR7: CoreWeave: S&P B+ (May-2025; B unsecured, recovery 5); Fitch BB- (notes, RR4) | AS7: no bank hold attributed (non-bank, distributed or n.d.)
A8: 2 | B8: CoreWeave DDTL 2.1 (tranche of 2.0) | C8: NONE | E8: =IF(C8="NONE",0,IFERROR(INDEX(rng_lessee_pd,MATCH(D8,rng_lessee_key,0)),g_pd_unrated)) -> 0 | F8: =IF(E8<=0,0,NORMSDIST((NORMSINV(E8)-SQRT(g_rho_ai)*p_z_ai)/SQRT(1-g_rho_ai))) -> 0 | G8: 0 | H8: 0 | I8: 0 | J8: 0 | K8: 0 | L8: 0 | M8: 0 | N8: =G8*(1-H8) -> 0 | O8: =(1-p_gpu_r)^g_t_def -> 0.2809 | P8: =IF(N8>0,MAX(0,1-(1-g_c_gpu)*O8/N8)*(1-I8),0) -> 0 | Q8: =IF(C8="GPU",F8*P8+K8*p_uw_drop,IF(C8="RCF",p_ccf_ai*F8*J8,IF(C8="DC",F8*J8+K8*p_uw_drop+M8/100,IF(C8="UNSEC",F8*J8,IF(C8="MARGIN",F8*MAX(0,G8-(1-p_oai_drop)*(1-g_c_gpu))/G8,IF(C8="ANTH",F8*(L8*0.1+(1-L8)*0.7)+p_uw_drop,0)))))) -> 0 | R8: =IF(C8="RCF",1,0) -> 0 | S8: 3 | T8: 0 | U8: 0 | V8: 0 | W8: 0 | X8: 0 | Y8: 0 | Z8: 0 | AA8: 0 | AB8: 0 | AC8: 0 | AD8: 0 | AE8: 0 | AF8: 0 | AG8: 0 | AH8: 0 | AI8: 0 | AJ8: 0 | AK8: 0 | AL8: 0 | AM8: 0 | AN8: 0 | AO8: 0 | AP8: 0 | AQ8: 0 | AR8: CoreWeave: S&P B+ (May-2025; B unsecured, recovery 5); Fitch BB- (notes, RR4) | AS8: no bank hold attributed (non-bank, distributed or n.d.)
A9: 3 | B9: CoreWeave DDTL 3.0 (OpenAI contract) | C9: GPU | D9: CRWV | E9: =IF(C9="NONE",0,IFERROR(INDEX(rng_lessee_pd,MATCH(D9,rng_lessee_key,0)),g_pd_unrated)) -> 0.0805 | F9: =IF(E9<=0,0,NORMSDIST((NORMSINV(E9)-SQRT(g_rho_ai)*p_z_ai)/SQRT(1-g_rho_ai))) -> 0.48454997 | G9: 0.7 | H9: 0.4 | I9: 0 | J9: 0 | K9: 0 | L9: 0 | M9: 0 | N9: =G9*(1-H9) -> 0.42 | O9: =(1-p_gpu_r)^g_t_def -> 0.2809 | P9: =IF(N9>0,MAX(0,1-(1-g_c_gpu)*O9/N9)*(1-I9),0) -> 0.46495238 | Q9: =IF(C9="GPU",F9*P9+K9*p_uw_drop,IF(C9="RCF",p_ccf_ai*F9*J9,IF(C9="DC",F9*J9+K9*p_uw_drop+M9/100,IF(C9="UNSEC",F9*J9,IF(C9="MARGIN",F9*MAX(0,G9-(1-p_oai_drop)*(1-g_c_gpu))/G9,IF(C9="ANTH",F9*(L9*0.1+(1-L9)*0.7)+p_uw_drop,0)))))) -> 0.22529266 | R9: =IF(C9="RCF",1,0) -> 0 | S9: 2.6 | T9: 0.177 | U9: 0 | V9: 0 | W9: 0.177 | X9: 0.266 | Y9: 0.354 | Z9: 0.177 | AA9: 0 | AB9: 0 | AC9: 0 | AD9: 0 | AE9: 0 | AF9: 0 | AG9: 0 | AH9: 0 | AI9: 0 | AJ9: 0 | AK9: 0.177 | AL9: 0 | AM9: 0.354 | AN9: 0.177 | AO9: 0 | AP9: 0 | AQ9: 0 | AR9: OpenAI: unrated; CoreWeave: S&P B+ (May-2025; B unsecured, recovery 5); Fitch BB | AS9: DDTL 3.0: OpenAI contract; monthly amort Apr-26..Aug-30 (40% repaid by t=2 EST, sculpted)
A10: 4 | B10: CoreWeave DDTL 4.0 (CCAC VIII; IG GPU loan) | C10: GPU | D10: META | E10: =IF(C10="NONE",0,IFERROR(INDEX(rng_lessee_pd,MATCH(D10,rng_lessee_key,0)),g_pd_unrated)) -> 0.0015 | F10: =IF(E10<=0,0,NORMSDIST((NORMSINV(E10)-SQRT(g_rho_ai)*p_z_ai)/SQRT(1-g_rho_ai))) -> 0.028035006 | G10: 0.7 | H10: 0.28 | I10: 0 | J10: 0 | K10: 0 | L10: 0 | M10: 0 | N10: =G10*(1-H10) -> 0.504 | O10: =(1-p_gpu_r)^g_t_def -> 0.2809 | P10: =IF(N10>0,MAX(0,1-(1-g_c_gpu)*O10/N10)*(1-I10),0) -> 0.55412698 | Q10: =IF(C10="GPU",F10*P10+K10*p_uw_drop,IF(C10="RCF",p_ccf_ai*F10*J10,IF(C10="DC",F10*J10+K10*p_uw_drop+M10/100,IF(C10="UNSEC",F10*J10,IF(C10="MARGIN",F10*MAX(0,G10-(1-p_oai_drop)*(1-g_c_gpu))/G10,IF(C10="ANTH",F10*(L10*0.1+(1-L10)*0.7)+p_uw_drop,0)))))) -> 0.015534953 | R10: =IF(C10="RCF",1,0) -> 0 | S10: 8.5 | T10: 0 | U10: 0 | V10: 0 | W10: 0 | X10: 0 | Y10: 1.417 | Z10: 0 | AA10: 1.417 | AB10: 0 | AC10: 0 | AD10: 0 | AE10: 0 | AF10: 0 | AG10: 0 | AH10: 0 | AI10: 0 | AJ10: 0 | AK10: 0 | AL10: 0 | AM10: 1.417 | AN10: 0 | AO10: 0 | AP10: 0 | AQ10: 0 | AR10: Meta: Aa3/AA- (FWP 30-Apr-2026); facility A3 (Moody's)/A(low) (DBRS) | AS10: DDTL 4.0: Meta MSA, non-recourse; amort after Jun-27 (16/57 months by t=2)
A11: 5 | B11: CoreWeave DDTL 5.0 | C11: GPU | D11: CRWV | E11: =IF(C11="NONE",0,IFERROR(INDEX(rng_lessee_pd,MATCH(D11,rng_lessee_key,0)),g_pd_unrated)) -> 0.0805 | F11: =IF(E11<=0,0,NORMSDIST((NORMSINV(E11)-SQRT(g_rho_ai)*p_z_ai)/SQRT(1-g_rho_ai))) -> 0.48454997 | G11: 0.7 | H11: 0.38 | I11: 0 | J11: 0 | K11: 0 | L11: 0 | M11: 0 | N11: =G11*(1-H11) -> 0.434 | O11: =(1-p_gpu_r)^g_t_def -> 0.2809 | P11: =IF(N11>0,MAX(0,1-(1-g_c_gpu)*O11/N11)*(1-I11),0) -> 0.48221198 | Q11: =IF(C11="GPU",F11*P11+K11*p_uw_drop,IF(C11="RCF",p_ccf_ai*F11*J11,IF(C11="DC",F11*J11+K11*p_uw_drop+M11/100,IF(C11="UNSEC",F11*J11,IF(C11="MARGIN",F11*MAX(0,G11-(1-p_oai_drop)*(1-g_c_gpu))/G11,IF(C11="ANTH",F11*(L11*0.1+(1-L11)*0.7)+p_uw_drop,0)))))) -> 0.2336558 | R11: =IF(C11="RCF",1,0) -> 0 | S11: 3.1 | T11: 0 | U11: 0 | V11: 0 | W11: 0 | X11: 0 | Y11: 1.55 | Z11: 0 | AA11: 0 | AB11: 0 | AC11: 0 | AD11: 0 | AE11: 0 | AF11: 0 | AG11: 0 | AH11: 0 | AI11: 0 | AJ11: 0 | AK11: 0 | AL11: 0 | AM11: 1.55 | AN11: 0 | AO11: 0 | AP11: 0 | AQ11: 0 | AR11: CoreWeave: S&P B+ (May-2025; B unsecured, recovery 5); Fitch BB- (notes, RR4); f | AS11: DDTL 5.0: two non-IG customers; monthly Nov-26..Nov-31
A12: 6 | B12: CoreWeave DDTL 5.5 | C12: GPU | D12: CRWV | E12: =IF(C12="NONE",0,IFERROR(INDEX(rng_lessee_pd,MATCH(D12,rng_lessee_key,0)),g_pd_unrated)) -> 0.0805 | F12: =IF(E12<=0,0,NORMSDIST((NORMSINV(E12)-SQRT(g_rho_ai)*p_z_ai)/SQRT(1-g_rho_ai))) -> 0.48454997 | G12: 0.75 | H12: 0.2 | I12: 0 | J12: 0 | K12: 0 | L12: 0 | M12: 0 | N12: =G12*(1-H12) -> 0.6 | O12: =(1-p_gpu_r)^g_t_def -> 0.2809 | P12: =IF(N12>0,MAX(0,1-(1-g_c_gpu)*O12/N12)*(1-I12),0) -> 0.62546667 | Q12: =IF(C12="GPU",F12*P12+K12*p_uw_drop,IF(C12="RCF",p_ccf_ai*F12*J12,IF(C12="DC",F12*J12+K12*p_uw_drop+M12/100,IF(C12="UNSEC",F12*J12,IF(C12="MARGIN",F12*MAX(0,G12-(1-p_oai_drop)*(1-g_c_gpu))/G12,IF(C12="ANTH",F12*(L12*0.1+(1-L12)*0.7)+p_uw_drop,0)))))) -> 0.30306985 | R12: =IF(C12="RCF",1,0) -> 0 | S12: 2.6 | T12: 1.3 | U12: 0 | V12: 0 | W12: 0 | X12: 0 | Y12: 0 | Z12: 0 | AA12: 0 | AB12: 0 | AC12: 0 | AD12: 0 | AE12: 0 | AF12: 0 | AG12: 0 | AH12: 0 | AI12: 0 | AJ12: 0 | AK12: 0 | AL12: 0 | AM12: 1.3 | AN12: 0 | AO12: 0 | AP12: 0 | AQ12: 0 | AR12: CoreWeave: S&P B+ (May-2025; B unsecured, recovery 5); Fitch BB- (notes, RR4); f | AS12: DDTL 5.5: no LTV/borrowing base found; ~3y contracts vs 5y debt (EST LTV 75%, 20% repaid)
A13: 7 | B13: CoreWeave revolving credit facility | C13: RCF | D13: CRWV | E13: =IF(C13="NONE",0,IFERROR(INDEX(rng_lessee_pd,MATCH(D13,rng_lessee_key,0)),g_pd_unrated)) -> 0.0805 | F13: =IF(E13<=0,0,NORMSDIST((NORMSINV(E13)-SQRT(g_rho_ai)*p_z_ai)/SQRT(1-g_rho_ai))) -> 0.48454997 | G13: 0 | H13: 0 | I13: 0 | J13: 0.5 | K13: 0 | L13: 0 | M13: 0 | N13: =G13*(1-H13) -> 0 | O13: =(1-p_gpu_r)^g_t_def -> 0.2809 | P13: =IF(N13>0,MAX(0,1-(1-g_c_gpu)*O13/N13)*(1-I13),0) -> 0 | Q13: =IF(C13="GPU",F13*P13+K13*p_uw_drop,IF(C13="RCF",p_ccf_ai*F13*J13,IF(C13="DC",F13*J13+K13*p_uw_drop+M13/100,IF(C13="UNSEC",F13*J13,IF(C13="MARGIN",F13*MAX(0,G13-(1-p_oai_drop)*(1-g_c_gpu))/G13,IF(C13="ANTH",F13*(L13*0.1+(1-L13)*0.7)+p_uw_drop,0)))))) -> 0.24227498 | R13: =IF(C13="RCF",1,0) -> 1 | S13: 2.5 | T13: 0.385 | U13: 0 | V13: 0.192 | W13: 0.192 | X13: 0.385 | Y13: 0.385 | Z13: 0 | AA13: 0 | AB13: 0 | AC13: 0 | AD13: 0 | AE13: 0 | AF13: 0 | AG13: 0 | AH13: 0 | AI13: 0.192 | AJ13: 0 | AK13: 0 | AL13: 0 | AM13: 0.385 | AN13: 0.192 | AO13: 0 | AP13: 0 | AQ13: 0 | AR13: CoreWeave: S&P B+ (May-2025; B unsecured, recovery 5); Fitch BB- (notes, RR4) | AS13: CoreWeave secured RCF (undrawn): drawn in stress, LGD 50% EST
A14: 8 | B14: CoreWeave OEM equipment financing | C14: NONE | E14: =IF(C14="NONE",0,IFERROR(INDEX(rng_lessee_pd,MATCH(D14,rng_lessee_key,0)),g_pd_unrated)) -> 0 | F14: =IF(E14<=0,0,NORMSDIST((NORMSINV(E14)-SQRT(g_rho_ai)*p_z_ai)/SQRT(1-g_rho_ai))) -> 0 | G14: 0 | H14: 0 | I14: 0 | J14: 0 | K14: 0 | L14: 0 | M14: 0 | N14: =G14*(1-H14) -> 0 | O14: =(1-p_gpu_r)^g_t_def -> 0.2809 | P14: =IF(N14>0,MAX(0,1-(1-g_c_gpu)*O14/N14)*(1-I14),0) -> 0 | Q14: =IF(C14="GPU",F14*P14+K14*p_uw_drop,IF(C14="RCF",p_ccf_ai*F14*J14,IF(C14="DC",F14*J14+K14*p_uw_drop+M14/100,IF(C14="UNSEC",F14*J14,IF(C14="MARGIN",F14*MAX(0,G14-(1-p_oai_drop)*(1-g_c_gpu))/G14,IF(C14="ANTH",F14*(L14*0.1+(1-L14)*0.7)+p_uw_drop,0)))))) -> 0 | R14: =IF(C14="RCF",1,0) -> 0 | S14: 4.8 | T14: 0 | U14: 0 | V14: 0 | W14: 0 | X14: 0 | Y14: 0 | Z14: 0 | AA14: 0 | AB14: 0 | AC14: 0 | AD14: 0 | AE14: 0 | AF14: 0 | AG14: 0 | AH14: 0 | AI14: 0 | AJ14: 0 | AK14: 0 | AL14: 0 | AM14: 0 | AN14: 0 | AO14: 0 | AP14: 0 | AQ14: 0 | AR14: CoreWeave: S&P B+ (May-2025; B unsecured, recovery 5); Fitch BB- (notes, RR4) | AS14: no bank hold attributed (non-bank, distributed or n.d.)
A15: 9 | B15: Lambda GPU-backed facility (Macquarie) | C15: NONE | E15: =IF(C15="NONE",0,IFERROR(INDEX(rng_lessee_pd,MATCH(D15,rng_lessee_key,0)),g_pd_unrated)) -> 0 | F15: =IF(E15<=0,0,NORMSDIST((NORMSINV(E15)-SQRT(g_rho_ai)*p_z_ai)/SQRT(1-g_rho_ai))) -> 0 | G15: 0 | H15: 0 | I15: 0 | J15: 0 | K15: 0 | L15: 0 | M15: 0 | N15: =G15*(1-H15) -> 0 | O15: =(1-p_gpu_r)^g_t_def -> 0.2809 | P15: =IF(N15>0,MAX(0,1-(1-g_c_gpu)*O15/N15)*(1-I15),0) -> 0 | Q15: =IF(C15="GPU",F15*P15+K15*p_uw_drop,IF(C15="RCF",p_ccf_ai*F15*J15,IF(C15="DC",F15*J15+K15*p_uw_drop+M15/100,IF(C15="UNSEC",F15*J15,IF(C15="MARGIN",F15*MAX(0,G15-(1-p_oai_drop)*(1-g_c_gpu))/G15,IF(C15="ANTH",F15*(L15*0.1+(1-L15)*0.7)+p_uw_drop,0)))))) -> 0 | R15: =IF(C15="RCF",1,0) -> 0 | S15: 0.5 | T15: 0 | U15: 0 | V15: 0 | W15: 0 | X15: 0 | Y15: 0 | Z15: 0 | AA15: 0 | AB15: 0 | AC15: 0 | AD15: 0 | AE15: 0 | AF15: 0 | AG15: 0 | AH15: 0 | AI15: 0 | AJ15: 0 | AK15: 0 | AL15: 0 | AM15: 0 | AN15: 0 | AO15: 0 | AP15: 0 | AQ15: 0 | AR15: Lambda: corporate unrated (not found) | AS15: no bank hold attributed (non-bank, distributed or n.d.)
A16: 10 | B16: Lambda $926m senior secured TLB | C16: NONE | E16: =IF(C16="NONE",0,IFERROR(INDEX(rng_lessee_pd,MATCH(D16,rng_lessee_key,0)),g_pd_unrated)) -> 0 | F16: =IF(E16<=0,0,NORMSDIST((NORMSINV(E16)-SQRT(g_rho_ai)*p_z_ai)/SQRT(1-g_rho_ai))) -> 0 | G16: 0 | H16: 0 | I16: 0 | J16: 0 | K16: 0 | L16: 0 | M16: 0 | N16: =G16*(1-H16) -> 0 | O16: =(1-p_gpu_r)^g_t_def -> 0.2809 | P16: =IF(N16>0,MAX(0,1-(1-g_c_gpu)*O16/N16)*(1-I16),0) -> 0 | Q16: =IF(C16="GPU",F16*P16+K16*p_uw_drop,IF(C16="RCF",p_ccf_ai*F16*J16,IF(C16="DC",F16*J16+K16*p_uw_drop+M16/100,IF(C16="UNSEC",F16*J16,IF(C16="MARGIN",F16*MAX(0,G16-(1-p_oai_drop)*(1-g_c_gpu))/G16,IF(C16="ANTH",F16*(L16*0.1+(1-L16)*0.7)+p_uw_drop,0)))))) -> 0 | R16: =IF(C16="RCF",1,0) -> 0 | S16: 0.926 | T16: 0 | U16: 0 | V16: 0 | W16: 0 | X16: 0 | Y16: 0 | Z16: 0 | AA16: 0 | AB16: 0 | AC16: 0 | AD16: 0 | AE16: 0 | AF16: 0 | AG16: 0 | AH16: 0 | AI16: 0 | AJ16: 0 | AK16: 0 | AL16: 0 | AM16: 0 | AN16: 0 | AO16: 0 | AP16: 0 | AQ16: 0 | AR16: facility Baa2 (Moody's); offtaker IG (unnamed) | AS16: no bank hold attributed (non-bank, distributed or n.d.)
A17: 11 | B17: Lambda $1.008bn fixed-rate DDTL | C17: NONE | E17: =IF(C17="NONE",0,IFERROR(INDEX(rng_lessee_pd,MATCH(D17,rng_lessee_key,0)),g_pd_unrated)) -> 0 | F17: =IF(E17<=0,0,NORMSDIST((NORMSINV(E17)-SQRT(g_rho_ai)*p_z_ai)/SQRT(1-g_rho_ai))) -> 0 | G17: 0 | H17: 0 | I17: 0 | J17: 0 | K17: 0 | L17: 0 | M17: 0 | N17: =G17*(1-H17) -> 0 | O17: =(1-p_gpu_r)^g_t_def -> 0.2809 | P17: =IF(N17>0,MAX(0,1-(1-g_c_gpu)*O17/N17)*(1-I17),0) -> 0 | Q17: =IF(C17="GPU",F17*P17+K17*p_uw_drop,IF(C17="RCF",p_ccf_ai*F17*J17,IF(C17="DC",F17*J17+K17*p_uw_drop+M17/100,IF(C17="UNSEC",F17*J17,IF(C17="MARGIN",F17*MAX(0,G17-(1-p_oai_drop)*(1-g_c_gpu))/G17,IF(C17="ANTH",F17*(L17*0.1+(1-L17)*0.7)+p_uw_drop,0)))))) -> 0 | R17: =IF(C17="RCF",1,0) -> 0 | S17: 1.008 | T17: 0 | U17: 0 | V17: 0 | W17: 0 | X17: 0 | Y17: 0 | Z17: 0 | AA17: 0 | AB17: 0 | AC17: 0 | AD17: 0 | AE17: 0 | AF17: 0 | AG17: 0 | AH17: 0 | AI17: 0 | AJ17: 0 | AK17: 0 | AL17: 0 | AM17: 0 | AN17: 0 | AO17: 0 | AP17: 0 | AQ17: 0 | AR17: facility Baa1 (Moody's) / A(low) (DBRS) | AS17: no bank hold attributed (non-bank, distributed or n.d.)
A18: 12 | B18: Nebius GPU-backed loan | C18: GPU | D18: NBIS | E18: =IF(C18="NONE",0,IFERROR(INDEX(rng_lessee_pd,MATCH(D18,rng_lessee_key,0)),g_pd_unrated)) -> 0.0267 | F18: =IF(E18<=0,0,NORMSDIST((NORMSINV(E18)-SQRT(g_rho_ai)*p_z_ai)/SQRT(1-g_rho_ai))) -> 0.25074236 | G18: 0.7 | H18: 0.4 | I18: 0 | J18: 0 | K18: 0 | L18: 0 | M18: 0 | N18: =G18*(1-H18) -> 0.42 | O18: =(1-p_gpu_r)^g_t_def -> 0.2809 | P18: =IF(N18>0,MAX(0,1-(1-g_c_gpu)*O18/N18)*(1-I18),0) -> 0.46495238 | Q18: =IF(C18="GPU",F18*P18+K18*p_uw_drop,IF(C18="RCF",p_ccf_ai*F18*J18,IF(C18="DC",F18*J18+K18*p_uw_drop+M18/100,IF(C18="UNSEC",F18*J18,IF(C18="MARGIN",F18*MAX(0,G18-(1-p_oai_drop)*(1-g_c_gpu))/G18,IF(C18="ANTH",F18*(L18*0.1+(1-L18)*0.7)+p_uw_drop,0)))))) -> 0.11658326 | R18: =IF(C18="RCF",1,0) -> 0 | S18: 0.775 | T18: 0 | U18: 0.092 | V18: 0.055 | W18: 0 | X18: 0.037 | Y18: 0.055 | Z18: 0 | AA18: 0 | AB18: 0 | AC18: 0 | AD18: 0 | AE18: 0 | AF18: 0 | AG18: 0 | AH18: 0.092 | AI18: 0.092 | AJ18: 0 | AK18: 0 | AL18: 0 | AM18: 0.148 | AN18: 0 | AO18: 0 | AP18: 0 | AQ18: 0 | AR18: Nebius: unrated (not found); Microsoft AAA/Aaa | AS18: Nebius: Microsoft offtake; to Oct-2030
A19: 13 | B19: Crusoe GPU DDTL (IS AN03 LLC, Iceland) | C19: GPU | D19: CRUSOE | E19: =IF(C19="NONE",0,IFERROR(INDEX(rng_lessee_pd,MATCH(D19,rng_lessee_key,0)),g_pd_unrated)) -> 0.0968 | F19: =IF(E19<=0,0,NORMSDIST((NORMSINV(E19)-SQRT(g_rho_ai)*p_z_ai)/SQRT(1-g_rho_ai))) -> 0.53300808 | G19: 0.75 | H19: 0.45 | I19: 0 | J19: 0 | K19: 1 | L19: 0 | M19: 0 | N19: =G19*(1-H19) -> 0.4125 | O19: =(1-p_gpu_r)^g_t_def -> 0.2809 | P19: =IF(N19>0,MAX(0,1-(1-g_c_gpu)*O19/N19)*(1-I19),0) -> 0.45522424 | Q19: =IF(C19="GPU",F19*P19+K19*p_uw_drop,IF(C19="RCF",p_ccf_ai*F19*J19,IF(C19="DC",F19*J19+K19*p_uw_drop+M19/100,IF(C19="UNSEC",F19*J19,IF(C19="MARGIN",F19*MAX(0,G19-(1-p_oai_drop)*(1-g_c_gpu))/G19,IF(C19="ANTH",F19*(L19*0.1+(1-L19)*0.7)+p_uw_drop,0)))))) -> 0.3926382 | R19: =IF(C19="RCF",1,0) -> 0 | S19: 0.509 | T19: 0 | U19: 0 | V19: 0 | W19: 0 | X19: 0.509 | Y19: 0 | Z19: 0 | AA19: 0 | AB19: 0 | AC19: 0 | AD19: 0 | AE19: 0 | AF19: 0 | AG19: 0 | AH19: 0 | AI19: 0 | AJ19: 0 | AK19: 0 | AL19: 0 | AM19: 0 | AN19: 0 | AO19: 0 | AP19: 0 | AQ19: 0 | AR19: Crusoe: unrated (not found) | AS19: Crusoe Iceland DDTL: min(75% LTC, 1.30x DSCR); GS sole arranger, in syndication
A20: 14 | B20: Crusoe credit facility (Upper90) | C20: NONE | E20: =IF(C20="NONE",0,IFERROR(INDEX(rng_lessee_pd,MATCH(D20,rng_lessee_key,0)),g_pd_unrated)) -> 0 | F20: =IF(E20<=0,0,NORMSDIST((NORMSINV(E20)-SQRT(g_rho_ai)*p_z_ai)/SQRT(1-g_rho_ai))) -> 0 | G20: 0 | H20: 0 | I20: 0 | J20: 0 | K20: 0 | L20: 0 | M20: 0 | N20: =G20*(1-H20) -> 0 | O20: =(1-p_gpu_r)^g_t_def -> 0.2809 | P20: =IF(N20>0,MAX(0,1-(1-g_c_gpu)*O20/N20)*(1-I20),0) -> 0 | Q20: =IF(C20="GPU",F20*P20+K20*p_uw_drop,IF(C20="RCF",p_ccf_ai*F20*J20,IF(C20="DC",F20*J20+K20*p_uw_drop+M20/100,IF(C20="UNSEC",F20*J20,IF(C20="MARGIN",F20*MAX(0,G20-(1-p_oai_drop)*(1-g_c_gpu))/G20,IF(C20="ANTH",F20*(L20*0.1+(1-L20)*0.7)+p_uw_drop,0)))))) -> 0 | R20: =IF(C20="RCF",1,0) -> 0 | S20: 0.225 | T20: 0 | U20: 0 | V20: 0 | W20: 0 | X20: 0 | Y20: 0 | Z20: 0 | AA20: 0 | AB20: 0 | AC20: 0 | AD20: 0 | AE20: 0 | AF20: 0 | AG20: 0 | AH20: 0 | AI20: 0 | AJ20: 0 | AK20: 0 | AL20: 0 | AM20: 0 | AN20: 0 | AO20: 0 | AP20: 0 | AQ20: 0 | AR20: unrated | AS20: no bank hold attributed (non-bank, distributed or n.d.)
A21: 15 | B21: Fluidstack GPU senior facility (Macquarie) | C21: NONE | E21: =IF(C21="NONE",0,IFERROR(INDEX(rng_lessee_pd,MATCH(D21,rng_lessee_key,0)),g_pd_unrated)) -> 0 | F21: =IF(E21<=0,0,NORMSDIST((NORMSINV(E21)-SQRT(g_rho_ai)*p_z_ai)/SQRT(1-g_rho_ai))) -> 0 | G21: 0 | H21: 0 | I21: 0 | J21: 0 | K21: 0 | L21: 0 | M21: 0 | N21: =G21*(1-H21) -> 0 | O21: =(1-p_gpu_r)^g_t_def -> 0.2809 | P21: =IF(N21>0,MAX(0,1-(1-g_c_gpu)*O21/N21)*(1-I21),0) -> 0 | Q21: =IF(C21="GPU",F21*P21+K21*p_uw_drop,IF(C21="RCF",p_ccf_ai*F21*J21,IF(C21="DC",F21*J21+K21*p_uw_drop+M21/100,IF(C21="UNSEC",F21*J21,IF(C21="MARGIN",F21*MAX(0,G21-(1-p_oai_drop)*(1-g_c_gpu))/G21,IF(C21="ANTH",F21*(L21*0.1+(1-L21)*0.7)+p_uw_drop,0)))))) -> 0 | R21: =IF(C21="RCF",1,0) -> 0 | T21: 0 | U21: 0 | V21: 0 | W21: 0 | X21: 0 | Y21: 0 | Z21: 0 | AA21: 0 | AB21: 0 | AC21: 0 | AD21: 0 | AE21: 0 | AF21: 0 | AG21: 0 | AH21: 0 | AI21: 0 | AJ21: 0 | AK21: 0 | AL21: 0 | AM21: 0 | AN21: 0 | AO21: 0 | AP21: 0 | AQ21: 0 | AR21: Fluidstack: unrated | AS21: no bank hold attributed (non-bank, distributed or n.d.)
A22: 16 | B22: Volta Infrastructure / Anthropic, Tydal Norway | C22: GPU | D22: ANTH | E22: =IF(C22="NONE",0,IFERROR(INDEX(rng_lessee_pd,MATCH(D22,rng_lessee_key,0)),g_pd_unrated)) -> 0.0805 | F22: =IF(E22<=0,0,NORMSDIST((NORMSINV(E22)-SQRT(g_rho_ai)*p_z_ai)/SQRT(1-g_rho_ai))) -> 0.48454997 | G22: 0.75 | H22: 0.1 | I22: 0.26 | J22: 0 | K22: 1 | L22: 0 | M22: 0 | N22: =G22*(1-H22) -> 0.675 | O22: =(1-p_gpu_r)^g_t_def -> 0.2809 | P22: =IF(N22>0,MAX(0,1-(1-g_c_gpu)*O22/N22)*(1-I22),0) -> 0.4936403 | Q22: =IF(C22="GPU",F22*P22+K22*p_uw_drop,IF(C22="RCF",p_ccf_ai*F22*J22,IF(C22="DC",F22*J22+K22*p_uw_drop+M22/100,IF(C22="UNSEC",F22*J22,IF(C22="MARGIN",F22*MAX(0,G22-(1-p_oai_drop)*(1-g_c_gpu))/G22,IF(C22="ANTH",F22*(L22*0.1+(1-L22)*0.7)+p_uw_drop,0)))))) -> 0.38919339 | R22: =IF(C22="RCF",1,0) -> 0 | S22: 5 | T22: 5 | U22: 0 | V22: 0 | W22: 0 | X22: 0 | Y22: 0 | Z22: 0 | AA22: 0 | AB22: 0 | AC22: 0 | AD22: 0 | AE22: 0 | AF22: 0 | AG22: 0 | AH22: 0 | AI22: 0 | AJ22: 0 | AK22: 0 | AL22: 0 | AM22: 0 | AN22: 0 | AO22: 0 | AP22: 0 | AQ22: 0 | AR22: Anthropic: unrated (seeking IG post-IPO, Sep-2026) | AS22: Volta/Tydal: $3.7bn chip loan + $1.3bn cash-collateralised LC; JPM in syndication
A23: 17 | B23: xAI Colossus 2 GPU SPV (Valor) | C23: NONE | E23: =IF(C23="NONE",0,IFERROR(INDEX(rng_lessee_pd,MATCH(D23,rng_lessee_key,0)),g_pd_unrated)) -> 0 | F23: =IF(E23<=0,0,NORMSDIST((NORMSINV(E23)-SQRT(g_rho_ai)*p_z_ai)/SQRT(1-g_rho_ai))) -> 0 | G23: 0 | H23: 0 | I23: 0 | J23: 0 | K23: 0 | L23: 0 | M23: 0 | N23: =G23*(1-H23) -> 0 | O23: =(1-p_gpu_r)^g_t_def -> 0.2809 | P23: =IF(N23>0,MAX(0,1-(1-g_c_gpu)*O23/N23)*(1-I23),0) -> 0 | Q23: =IF(C23="GPU",F23*P23+K23*p_uw_drop,IF(C23="RCF",p_ccf_ai*F23*J23,IF(C23="DC",F23*J23+K23*p_uw_drop+M23/100,IF(C23="UNSEC",F23*J23,IF(C23="MARGIN",F23*MAX(0,G23-(1-p_oai_drop)*(1-g_c_gpu))/G23,IF(C23="ANTH",F23*(L23*0.1+(1-L23)*0.7)+p_uw_drop,0)))))) -> 0 | R23: =IF(C23="RCF",1,0) -> 0 | S23: 20 | T23: 0 | U23: 0 | V23: 0 | W23: 0 | X23: 0 | Y23: 0 | Z23: 0 | AA23: 0 | AB23: 0 | AC23: 0 | AD23: 0 | AE23: 0 | AF23: 0 | AG23: 0 | AH23: 0 | AI23: 0 | AJ23: 0 | AK23: 0 | AL23: 0 | AM23: 0 | AN23: 0 | AO23: 0 | AP23: 0 | AQ23: 0 | AR23: SpaceX (incl. xAI): Baa1/BBB/BBB+ stable (19-Jun-2026) (xAI unrated at signing) | AS23: no bank hold attributed (non-bank, distributed or n.d.)
A24: 18 | B24: Apollo/xAI triple-net GPU leases | C24: NONE | E24: =IF(C24="NONE",0,IFERROR(INDEX(rng_lessee_pd,MATCH(D24,rng_lessee_key,0)),g_pd_unrated)) -> 0 | F24: =IF(E24<=0,0,NORMSDIST((NORMSINV(E24)-SQRT(g_rho_ai)*p_z_ai)/SQRT(1-g_rho_ai))) -> 0 | G24: 0 | H24: 0 | I24: 0 | J24: 0 | K24: 0 | L24: 0 | M24: 0 | N24: =G24*(1-H24) -> 0 | O24: =(1-p_gpu_r)^g_t_def -> 0.2809 | P24: =IF(N24>0,MAX(0,1-(1-g_c_gpu)*O24/N24)*(1-I24),0) -> 0 | Q24: =IF(C24="GPU",F24*P24+K24*p_uw_drop,IF(C24="RCF",p_ccf_ai*F24*J24,IF(C24="DC",F24*J24+K24*p_uw_drop+M24/100,IF(C24="UNSEC",F24*J24,IF(C24="MARGIN",F24*MAX(0,G24-(1-p_oai_drop)*(1-g_c_gpu))/G24,IF(C24="ANTH",F24*(L24*0.1+(1-L24)*0.7)+p_uw_drop,0)))))) -> 0 | R24: =IF(C24="RCF",1,0) -> 0 | S24: 6.9 | T24: 0 | U24: 0 | V24: 0 | W24: 0 | X24: 0 | Y24: 0 | Z24: 0 | AA24: 0 | AB24: 0 | AC24: 0 | AD24: 0 | AE24: 0 | AF24: 0 | AG24: 0 | AH24: 0 | AI24: 0 | AJ24: 0 | AK24: 0 | AL24: 0 | AM24: 0 | AN24: 0 | AO24: 0 | AP24: 0 | AQ24: 0 | AR24: SpaceX (incl. xAI): Baa1/BBB/BBB+ stable (19-Jun-2026) | AS24: no bank hold attributed (non-bank, distributed or n.d.)
A25: 19 | B25: SpaceX/xAI Nvidia chip financing | C25: NONE | E25: =IF(C25="NONE",0,IFERROR(INDEX(rng_lessee_pd,MATCH(D25,rng_lessee_key,0)),g_pd_unrated)) -> 0 | F25: =IF(E25<=0,0,NORMSDIST((NORMSINV(E25)-SQRT(g_rho_ai)*p_z_ai)/SQRT(1-g_rho_ai))) -> 0 | G25: 0 | H25: 0 | I25: 0 | J25: 0 | K25: 0 | L25: 0 | M25: 0 | N25: =G25*(1-H25) -> 0 | O25: =(1-p_gpu_r)^g_t_def -> 0.2809 | P25: =IF(N25>0,MAX(0,1-(1-g_c_gpu)*O25/N25)*(1-I25),0) -> 0 | Q25: =IF(C25="GPU",F25*P25+K25*p_uw_drop,IF(C25="RCF",p_ccf_ai*F25*J25,IF(C25="DC",F25*J25+K25*p_uw_drop+M25/100,IF(C25="UNSEC",F25*J25,IF(C25="MARGIN",F25*MAX(0,G25-(1-p_oai_drop)*(1-g_c_gpu))/G25,IF(C25="ANTH",F25*(L25*0.1+(1-L25)*0.7)+p_uw_drop,0)))))) -> 0 | R25: =IF(C25="RCF",1,0) -> 0 | S25: 40 | T25: 0 | U25: 0 | V25: 0 | W25: 0 | X25: 0 | Y25: 0 | Z25: 0 | AA25: 0 | AB25: 0 | AC25: 0 | AD25: 0 | AE25: 0 | AF25: 0 | AG25: 0 | AH25: 0 | AI25: 0 | AJ25: 0 | AK25: 0 | AL25: 0 | AM25: 0 | AN25: 0 | AO25: 0 | AP25: 0 | AQ25: 0 | AR25: SpaceX (incl. xAI): Baa1/BBB/BBB+ stable (19-Jun-2026) | AS25: no bank hold attributed (non-bank, distributed or n.d.)
A26: 20 | B26: Broadcom AI XPV / Anthropic TPU SPV ($35bn) | C26: NONE | E26: =IF(C26="NONE",0,IFERROR(INDEX(rng_lessee_pd,MATCH(D26,rng_lessee_key,0)),g_pd_unrated)) -> 0 | F26: =IF(E26<=0,0,NORMSDIST((NORMSINV(E26)-SQRT(g_rho_ai)*p_z_ai)/SQRT(1-g_rho_ai))) -> 0 | G26: 0 | H26: 0 | I26: 0 | J26: 0 | K26: 0 | L26: 0 | M26: 0 | N26: =G26*(1-H26) -> 0 | O26: =(1-p_gpu_r)^g_t_def -> 0.2809 | P26: =IF(N26>0,MAX(0,1-(1-g_c_gpu)*O26/N26)*(1-I26),0) -> 0 | Q26: =IF(C26="GPU",F26*P26+K26*p_uw_drop,IF(C26="RCF",p_ccf_ai*F26*J26,IF(C26="DC",F26*J26+K26*p_uw_drop+M26/100,IF(C26="UNSEC",F26*J26,IF(C26="MARGIN",F26*MAX(0,G26-(1-p_oai_drop)*(1-g_c_gpu))/G26,IF(C26="ANTH",F26*(L26*0.1+(1-L26)*0.7)+p_uw_drop,0)))))) -> 0 | R26: =IF(C26="RCF",1,0) -> 0 | S26: 35 | T26: 0 | U26: 0 | V26: 0 | W26: 0 | X26: 0 | Y26: 0 | Z26: 0 | AA26: 0 | AB26: 0 | AC26: 0 | AD26: 0 | AE26: 0 | AF26: 0 | AG26: 0 | AH26: 0 | AI26: 0 | AJ26: 0 | AK26: 0 | AL26: 0 | AM26: 0 | AN26: 0 | AO26: 0 | AP26: 0 | AQ26: 0 | AR26: Anthropic: unrated (seeking IG post-IPO, Sep-2026); Broadcom IG (senior notes re | AS26: no bank hold attributed (non-bank, distributed or n.d.)
A27: 21 | B27: Broadcom/Anthropic TPU lease package ($60bn) | C27: ANTH | D27: ANTH | E27: =IF(C27="NONE",0,IFERROR(INDEX(rng_lessee_pd,MATCH(D27,rng_lessee_key,0)),g_pd_unrated)) -> 0.0805 | F27: =IF(E27<=0,0,NORMSDIST((NORMSINV(E27)-SQRT(g_rho_ai)*p_z_ai)/SQRT(1-g_rho_ai))) -> 0.48454997 | G27: 0 | H27: 0 | I27: 0 | J27: 0 | K27: 1 | L27: 0.82352941 | M27: 0 | N27: =G27*(1-H27) -> 0 | O27: =(1-p_gpu_r)^g_t_def -> 0.2809 | P27: =IF(N27>0,MAX(0,1-(1-g_c_gpu)*O27/N27)*(1-I27),0) -> 0 | Q27: =IF(C27="GPU",F27*P27+K27*p_uw_drop,IF(C27="RCF",p_ccf_ai*F27*J27,IF(C27="DC",F27*J27+K27*p_uw_drop+M27/100,IF(C27="UNSEC",F27*J27,IF(C27="MARGIN",F27*MAX(0,G27-(1-p_oai_drop)*(1-g_c_gpu))/G27,IF(C27="ANTH",F27*(L27*0.1+(1-L27)*0.7)+p_uw_drop,0)))))) -> 0.24976029 | R27: =IF(C27="RCF",1,0) -> 0 | S27: 60 | T27: 0 | U27: 17 | V27: 17 | W27: 0 | X27: 0 | Y27: 17 | Z27: 0 | AA27: 0 | AB27: 0 | AC27: 0 | AD27: 0 | AE27: 0 | AF27: 0 | AG27: 0 | AH27: 0 | AI27: 0 | AJ27: 0 | AK27: 0 | AL27: 0 | AM27: 0 | AN27: 0 | AO27: 0 | AP27: 0 | AQ27: 0 | AR27: Anthropic: unrated (seeking IG post-IPO, Sep-2026); Broadcom IG (5y CDS 122bp Au | AS27: $60bn Anthropic TPU package: $42bn senior Broadcom-backstopped, $18bn junior (BX $9bn); leads hold pre-sell-down
A28: 22 | B28: Broadcom -> Anthropic convertible note facility | C28: NONE | E28: =IF(C28="NONE",0,IFERROR(INDEX(rng_lessee_pd,MATCH(D28,rng_lessee_key,0)),g_pd_unrated)) -> 0 | F28: =IF(E28<=0,0,NORMSDIST((NORMSINV(E28)-SQRT(g_rho_ai)*p_z_ai)/SQRT(1-g_rho_ai))) -> 0 | G28: 0 | H28: 0 | I28: 0 | J28: 0 | K28: 0 | L28: 0 | M28: 0 | N28: =G28*(1-H28) -> 0 | O28: =(1-p_gpu_r)^g_t_def -> 0.2809 | P28: =IF(N28>0,MAX(0,1-(1-g_c_gpu)*O28/N28)*(1-I28),0) -> 0 | Q28: =IF(C28="GPU",F28*P28+K28*p_uw_drop,IF(C28="RCF",p_ccf_ai*F28*J28,IF(C28="DC",F28*J28+K28*p_uw_drop+M28/100,IF(C28="UNSEC",F28*J28,IF(C28="MARGIN",F28*MAX(0,G28-(1-p_oai_drop)*(1-g_c_gpu))/G28,IF(C28="ANTH",F28*(L28*0.1+(1-L28)*0.7)+p_uw_drop,0)))))) -> 0 | R28: =IF(C28="RCF",1,0) -> 0 | S28: 42 | T28: 0 | U28: 0 | V28: 0 | W28: 0 | X28: 0 | Y28: 0 | Z28: 0 | AA28: 0 | AB28: 0 | AC28: 0 | AD28: 0 | AE28: 0 | AF28: 0 | AG28: 0 | AH28: 0 | AI28: 0 | AJ28: 0 | AK28: 0 | AL28: 0 | AM28: 0 | AN28: 0 | AO28: 0 | AP28: 0 | AQ28: 0 | AR28: Anthropic: unrated (seeking IG post-IPO, Sep-2026) | AS28: no bank hold attributed (non-bank, distributed or n.d.)
A29: 23 | B29: Anthropic corporate revolver | C29: RCF | D29: ANTH | E29: =IF(C29="NONE",0,IFERROR(INDEX(rng_lessee_pd,MATCH(D29,rng_lessee_key,0)),g_pd_unrated)) -> 0.0805 | F29: =IF(E29<=0,0,NORMSDIST((NORMSINV(E29)-SQRT(g_rho_ai)*p_z_ai)/SQRT(1-g_rho_ai))) -> 0.48454997 | G29: 0 | H29: 0 | I29: 0 | J29: 0.75 | K29: 0 | L29: 0 | M29: 0 | N29: =G29*(1-H29) -> 0 | O29: =(1-p_gpu_r)^g_t_def -> 0.2809 | P29: =IF(N29>0,MAX(0,1-(1-g_c_gpu)*O29/N29)*(1-I29),0) -> 0 | Q29: =IF(C29="GPU",F29*P29+K29*p_uw_drop,IF(C29="RCF",p_ccf_ai*F29*J29,IF(C29="DC",F29*J29+K29*p_uw_drop+M29/100,IF(C29="UNSEC",F29*J29,IF(C29="MARGIN",F29*MAX(0,G29-(1-p_oai_drop)*(1-g_c_gpu))/G29,IF(C29="ANTH",F29*(L29*0.1+(1-L29)*0.7)+p_uw_drop,0)))))) -> 0.36341248 | R29: =IF(C29="RCF",1,0) -> 1 | S29: 15 | T29: 1.25 | U29: 1 | V29: 1.25 | W29: 1 | X29: 1.25 | Y29: 1.25 | Z29: 0 | AA29: 0 | AB29: 0 | AC29: 0 | AD29: 0 | AE29: 0 | AF29: 0 | AG29: 1 | AH29: 0 | AI29: 1 | AJ29: 0.625 | AK29: 0 | AL29: 0.625 | AM29: 0.625 | AN29: 0.625 | AO29: 0.625 | AP29: 1 | AQ29: 0 | AR29: Anthropic: unrated (seeking IG post-IPO, Sep-2026) | AS29: Anthropic unsecured RCF (undrawn)
A30: 24 | B30: Nexus Data Centers, Hubbard TX (Anthropic) | C30: DC | D30: ANTH | E30: =IF(C30="NONE",0,IFERROR(INDEX(rng_lessee_pd,MATCH(D30,rng_lessee_key,0)),g_pd_unrated)) -> 0.0805 | F30: =IF(E30<=0,0,NORMSDIST((NORMSINV(E30)-SQRT(g_rho_ai)*p_z_ai)/SQRT(1-g_rho_ai))) -> 0.48454997 | G30: 0 | H30: 0 | I30: 0 | J30: 0.4 | K30: 1 | L30: 0 | M30: 0 | N30: =G30*(1-H30) -> 0 | O30: =(1-p_gpu_r)^g_t_def -> 0.2809 | P30: =IF(N30>0,MAX(0,1-(1-g_c_gpu)*O30/N30)*(1-I30),0) -> 0 | Q30: =IF(C30="GPU",F30*P30+K30*p_uw_drop,IF(C30="RCF",p_ccf_ai*F30*J30,IF(C30="DC",F30*J30+K30*p_uw_drop+M30/100,IF(C30="UNSEC",F30*J30,IF(C30="MARGIN",F30*MAX(0,G30-(1-p_oai_drop)*(1-g_c_gpu))/G30,IF(C30="ANTH",F30*(L30*0.1+(1-L30)*0.7)+p_uw_drop,0)))))) -> 0.34381999 | R30: =IF(C30="RCF",1,0) -> 0 | S30: 15 | T30: 0 | U30: 0 | V30: 0 | W30: 0 | X30: 0 | Y30: 5 | Z30: 0 | AA30: 0 | AB30: 0 | AC30: 0 | AD30: 0 | AE30: 0 | AF30: 0 | AG30: 0 | AH30: 0 | AI30: 0 | AJ30: 0 | AK30: 0 | AL30: 0 | AM30: 0 | AN30: 0 | AO30: 0 | AP30: 0 | AQ30: 0 | AR30: Anthropic: unrated (seeking IG post-IPO, Sep-2026); Alphabet: Aa2/AA+ stable (FW | AS30: Nexus TX construction bridge; Google guarantee only post-completion
A31: 25 | B31: Meta Hyperion (Beignet Investor LLC) bonds | C31: NONE | E31: =IF(C31="NONE",0,IFERROR(INDEX(rng_lessee_pd,MATCH(D31,rng_lessee_key,0)),g_pd_unrated)) -> 0 | F31: =IF(E31<=0,0,NORMSDIST((NORMSINV(E31)-SQRT(g_rho_ai)*p_z_ai)/SQRT(1-g_rho_ai))) -> 0 | G31: 0 | H31: 0 | I31: 0 | J31: 0 | K31: 0 | L31: 0 | M31: 0 | N31: =G31*(1-H31) -> 0 | O31: =(1-p_gpu_r)^g_t_def -> 0.2809 | P31: =IF(N31>0,MAX(0,1-(1-g_c_gpu)*O31/N31)*(1-I31),0) -> 0 | Q31: =IF(C31="GPU",F31*P31+K31*p_uw_drop,IF(C31="RCF",p_ccf_ai*F31*J31,IF(C31="DC",F31*J31+K31*p_uw_drop+M31/100,IF(C31="UNSEC",F31*J31,IF(C31="MARGIN",F31*MAX(0,G31-(1-p_oai_drop)*(1-g_c_gpu))/G31,IF(C31="ANTH",F31*(L31*0.1+(1-L31)*0.7)+p_uw_drop,0)))))) -> 0 | R31: =IF(C31="RCF",1,0) -> 0 | S31: 27.3 | T31: 0 | U31: 0 | V31: 0 | W31: 0 | X31: 0 | Y31: 0 | Z31: 0 | AA31: 0 | AB31: 0 | AC31: 0 | AD31: 0 | AE31: 0 | AF31: 0 | AG31: 0 | AH31: 0 | AI31: 0 | AJ31: 0 | AK31: 0 | AL31: 0 | AM31: 0 | AN31: 0 | AO31: 0 | AP31: 0 | AQ31: 0 | AR31: Meta: Aa3/AA- (FWP 30-Apr-2026); bonds A+ (S&P) | AS31: no bank hold attributed (non-bank, distributed or n.d.)
A32: 26 | B32: Meta El Paso (Sopaipilla Investor LLC) notes | C32: NONE | E32: =IF(C32="NONE",0,IFERROR(INDEX(rng_lessee_pd,MATCH(D32,rng_lessee_key,0)),g_pd_unrated)) -> 0 | F32: =IF(E32<=0,0,NORMSDIST((NORMSINV(E32)-SQRT(g_rho_ai)*p_z_ai)/SQRT(1-g_rho_ai))) -> 0 | G32: 0 | H32: 0 | I32: 0 | J32: 0 | K32: 0 | L32: 0 | M32: 0 | N32: =G32*(1-H32) -> 0 | O32: =(1-p_gpu_r)^g_t_def -> 0.2809 | P32: =IF(N32>0,MAX(0,1-(1-g_c_gpu)*O32/N32)*(1-I32),0) -> 0 | Q32: =IF(C32="GPU",F32*P32+K32*p_uw_drop,IF(C32="RCF",p_ccf_ai*F32*J32,IF(C32="DC",F32*J32+K32*p_uw_drop+M32/100,IF(C32="UNSEC",F32*J32,IF(C32="MARGIN",F32*MAX(0,G32-(1-p_oai_drop)*(1-g_c_gpu))/G32,IF(C32="ANTH",F32*(L32*0.1+(1-L32)*0.7)+p_uw_drop,0)))))) -> 0 | R32: =IF(C32="RCF",1,0) -> 0 | S32: 12.3 | T32: 0 | U32: 0 | V32: 0 | W32: 0 | X32: 0 | Y32: 0 | Z32: 0 | AA32: 0 | AB32: 0 | AC32: 0 | AD32: 0 | AE32: 0 | AF32: 0 | AG32: 0 | AH32: 0 | AI32: 0 | AJ32: 0 | AK32: 0 | AL32: 0 | AM32: 0 | AN32: 0 | AO32: 0 | AP32: 0 | AQ32: 0 | AR32: Meta: Aa3/AA- (FWP 30-Apr-2026); notes S&P A+, Fitch AA-(EXP) | AS32: no bank hold attributed (non-bank, distributed or n.d.)
A33: 27 | B33: Vantage Frontier TX + Port Washington WI (Oracle/OpenAI) | C33: DC | D33: ORCL | E33: =IF(C33="NONE",0,IFERROR(INDEX(rng_lessee_pd,MATCH(D33,rng_lessee_key,0)),g_pd_unrated)) -> 0.0117 | F33: =IF(E33<=0,0,NORMSDIST((NORMSINV(E33)-SQRT(g_rho_ai)*p_z_ai)/SQRT(1-g_rho_ai))) -> 0.14168988 | G33: 0 | H33: 0 | I33: 0 | J33: 0.35 | K33: 0 | L33: 0 | M33: 0 | N33: =G33*(1-H33) -> 0 | O33: =(1-p_gpu_r)^g_t_def -> 0.2809 | P33: =IF(N33>0,MAX(0,1-(1-g_c_gpu)*O33/N33)*(1-I33),0) -> 0 | Q33: =IF(C33="GPU",F33*P33+K33*p_uw_drop,IF(C33="RCF",p_ccf_ai*F33*J33,IF(C33="DC",F33*J33+K33*p_uw_drop+M33/100,IF(C33="UNSEC",F33*J33,IF(C33="MARGIN",F33*MAX(0,G33-(1-p_oai_drop)*(1-g_c_gpu))/G33,IF(C33="ANTH",F33*(L33*0.1+(1-L33)*0.7)+p_uw_drop,0)))))) -> 0.049591459 | R33: =IF(C33="RCF",1,0) -> 0 | S33: 38 | T33: 1.45 | U33: 0 | V33: 0 | W33: 0 | X33: 0 | Y33: 0 | Z33: 0 | AA33: 0 | AB33: 0 | AC33: 0 | AD33: 0 | AE33: 0 | AF33: 0 | AG33: 0 | AH33: 0 | AI33: 0 | AJ33: 0 | AK33: 0 | AL33: 0 | AM33: 1.45 | AN33: 0 | AO33: 0 | AP33: 0 | AQ33: 0 | AR33: Oracle: S&P BBB- stable (9-Jul-2026, from BBB); Moody's Baa2 neg (affirmed 2-Feb | AS33: Vantage (Oracle/OpenAI) construction loan; leads retain
A34: 28 | B34: Oracle Project Jupiter, Dona Ana NM (Stack/Blue Owl) | C34: DC | D34: ORCL | E34: =IF(C34="NONE",0,IFERROR(INDEX(rng_lessee_pd,MATCH(D34,rng_lessee_key,0)),g_pd_unrated)) -> 0.0117 | F34: =IF(E34<=0,0,NORMSDIST((NORMSINV(E34)-SQRT(g_rho_ai)*p_z_ai)/SQRT(1-g_rho_ai))) -> 0.14168988 | G34: 0 | H34: 0 | I34: 0 | J34: 0.35 | K34: 1 | L34: 0 | M34: 10 | N34: =G34*(1-H34) -> 0 | O34: =(1-p_gpu_r)^g_t_def -> 0.2809 | P34: =IF(N34>0,MAX(0,1-(1-g_c_gpu)*O34/N34)*(1-I34),0) -> 0 | Q34: =IF(C34="GPU",F34*P34+K34*p_uw_drop,IF(C34="RCF",p_ccf_ai*F34*J34,IF(C34="DC",F34*J34+K34*p_uw_drop+M34/100,IF(C34="UNSEC",F34*J34,IF(C34="MARGIN",F34*MAX(0,G34-(1-p_oai_drop)*(1-g_c_gpu))/G34,IF(C34="ANTH",F34*(L34*0.1+(1-L34)*0.7)+p_uw_drop,0)))))) -> 0.29959146 | R34: =IF(C34="RCF",1,0) -> 0 | S34: 18 | T34: 0 | U34: 0 | V34: 0 | W34: 0 | X34: 1.5 | Y34: 0 | Z34: 0 | AA34: 0 | AB34: 0 | AC34: 0 | AD34: 0 | AE34: 0 | AF34: 0 | AG34: 0 | AH34: 0 | AI34: 0 | AJ34: 1.5 | AK34: 0 | AL34: 0 | AM34: 1.5 | AN34: 1.5 | AO34: 0 | AP34: 0 | AQ34: 0.75 | AR34: Oracle: S&P BBB- stable (9-Jul-2026, from BBB); Moody's Baa2 neg (affirmed 2-Feb | AS34: Jupiter (Oracle) quoted 89-91; Oracle force-majeure notice 24-Sep-26; banks hold
A35: 29 | B35: Stargate Abilene (Crusoe/Blue Owl/Primary Digital) | C35: DC | D35: ORCL | E35: =IF(C35="NONE",0,IFERROR(INDEX(rng_lessee_pd,MATCH(D35,rng_lessee_key,0)),g_pd_unrated)) -> 0.0117 | F35: =IF(E35<=0,0,NORMSDIST((NORMSINV(E35)-SQRT(g_rho_ai)*p_z_ai)/SQRT(1-g_rho_ai))) -> 0.14168988 | G35: 0 | H35: 0 | I35: 0 | J35: 0.35 | K35: 0 | L35: 0 | M35: 0 | N35: =G35*(1-H35) -> 0 | O35: =(1-p_gpu_r)^g_t_def -> 0.2809 | P35: =IF(N35>0,MAX(0,1-(1-g_c_gpu)*O35/N35)*(1-I35),0) -> 0 | Q35: =IF(C35="GPU",F35*P35+K35*p_uw_drop,IF(C35="RCF",p_ccf_ai*F35*J35,IF(C35="DC",F35*J35+K35*p_uw_drop+M35/100,IF(C35="UNSEC",F35*J35,IF(C35="MARGIN",F35*MAX(0,G35-(1-p_oai_drop)*(1-g_c_gpu))/G35,IF(C35="ANTH",F35*(L35*0.1+(1-L35)*0.7)+p_uw_drop,0)))))) -> 0.049591459 | R35: =IF(C35="RCF",1,0) -> 0 | S35: 9.4 | T35: 4.075 | U35: 0 | V35: 0 | W35: 0 | X35: 0 | Y35: 0 | Z35: 0 | AA35: 0 | AB35: 0 | AC35: 0 | AD35: 0 | AE35: 0 | AF35: 0 | AG35: 0 | AH35: 0 | AI35: 0 | AJ35: 0 | AK35: 0 | AL35: 0 | AM35: 0 | AN35: 0 | AO35: 0 | AP35: 0 | AQ35: 0 | AR35: Oracle: S&P BBB- stable (9-Jul-2026, from BBB); Moody's Baa2 neg (affirmed 2-Feb | AS35: Abilene: Oracle 15-yr lease, ~65% LTC
A36: 30 | B36: Related Digital 'The Barn', Saline Twp MI (Oracle) | C36: NONE | E36: =IF(C36="NONE",0,IFERROR(INDEX(rng_lessee_pd,MATCH(D36,rng_lessee_key,0)),g_pd_unrated)) -> 0 | F36: =IF(E36<=0,0,NORMSDIST((NORMSINV(E36)-SQRT(g_rho_ai)*p_z_ai)/SQRT(1-g_rho_ai))) -> 0 | G36: 0 | H36: 0 | I36: 0 | J36: 0 | K36: 0 | L36: 0 | M36: 0 | N36: =G36*(1-H36) -> 0 | O36: =(1-p_gpu_r)^g_t_def -> 0.2809 | P36: =IF(N36>0,MAX(0,1-(1-g_c_gpu)*O36/N36)*(1-I36),0) -> 0 | Q36: =IF(C36="GPU",F36*P36+K36*p_uw_drop,IF(C36="RCF",p_ccf_ai*F36*J36,IF(C36="DC",F36*J36+K36*p_uw_drop+M36/100,IF(C36="UNSEC",F36*J36,IF(C36="MARGIN",F36*MAX(0,G36-(1-p_oai_drop)*(1-g_c_gpu))/G36,IF(C36="ANTH",F36*(L36*0.1+(1-L36)*0.7)+p_uw_drop,0)))))) -> 0 | R36: =IF(C36="RCF",1,0) -> 0 | S36: 16.3 | T36: 0 | U36: 0 | V36: 0 | W36: 0 | X36: 0 | Y36: 0 | Z36: 0 | AA36: 0 | AB36: 0 | AC36: 0 | AD36: 0 | AE36: 0 | AF36: 0 | AG36: 0 | AH36: 0 | AI36: 0 | AJ36: 0 | AK36: 0 | AL36: 0 | AM36: 0 | AN36: 0 | AO36: 0 | AP36: 0 | AQ36: 0 | AR36: Oracle: S&P BBB- stable (9-Jul-2026, from BBB); Moody's Baa2 neg (affirmed 2-Feb | AS36: no bank hold attributed (non-bank, distributed or n.d.)
A37: 31 | B37: SB Energy PORTS-Pike Ohio (OpenAI) - Nvidia RVG (guarantee cap, not debt) | C37: NONE | E37: =IF(C37="NONE",0,IFERROR(INDEX(rng_lessee_pd,MATCH(D37,rng_lessee_key,0)),g_pd_unrated)) -> 0 | F37: =IF(E37<=0,0,NORMSDIST((NORMSINV(E37)-SQRT(g_rho_ai)*p_z_ai)/SQRT(1-g_rho_ai))) -> 0 | G37: 0 | H37: 0 | I37: 0 | J37: 0 | K37: 0 | L37: 0 | M37: 0 | N37: =G37*(1-H37) -> 0 | O37: =(1-p_gpu_r)^g_t_def -> 0.2809 | P37: =IF(N37>0,MAX(0,1-(1-g_c_gpu)*O37/N37)*(1-I37),0) -> 0 | Q37: =IF(C37="GPU",F37*P37+K37*p_uw_drop,IF(C37="RCF",p_ccf_ai*F37*J37,IF(C37="DC",F37*J37+K37*p_uw_drop+M37/100,IF(C37="UNSEC",F37*J37,IF(C37="MARGIN",F37*MAX(0,G37-(1-p_oai_drop)*(1-g_c_gpu))/G37,IF(C37="ANTH",F37*(L37*0.1+(1-L37)*0.7)+p_uw_drop,0)))))) -> 0 | R37: =IF(C37="RCF",1,0) -> 0 | S37: 105 | T37: 0 | U37: 0 | V37: 0 | W37: 0 | X37: 0 | Y37: 0 | Z37: 0 | AA37: 0 | AB37: 0 | AC37: 0 | AD37: 0 | AE37: 0 | AF37: 0 | AG37: 0 | AH37: 0 | AI37: 0 | AJ37: 0 | AK37: 0 | AL37: 0 | AM37: 0 | AN37: 0 | AO37: 0 | AP37: 0 | AQ37: 0 | AR37: OpenAI: unrated | AS37: no bank hold attributed (non-bank, distributed or n.d.)
A38: 32 | B38: TeraWulf WULF Compute senior secured notes (Fluidstack/Google) | C38: NONE | E38: =IF(C38="NONE",0,IFERROR(INDEX(rng_lessee_pd,MATCH(D38,rng_lessee_key,0)),g_pd_unrated)) -> 0 | F38: =IF(E38<=0,0,NORMSDIST((NORMSINV(E38)-SQRT(g_rho_ai)*p_z_ai)/SQRT(1-g_rho_ai))) -> 0 | G38: 0 | H38: 0 | I38: 0 | J38: 0 | K38: 0 | L38: 0 | M38: 0 | N38: =G38*(1-H38) -> 0 | O38: =(1-p_gpu_r)^g_t_def -> 0.2809 | P38: =IF(N38>0,MAX(0,1-(1-g_c_gpu)*O38/N38)*(1-I38),0) -> 0 | Q38: =IF(C38="GPU",F38*P38+K38*p_uw_drop,IF(C38="RCF",p_ccf_ai*F38*J38,IF(C38="DC",F38*J38+K38*p_uw_drop+M38/100,IF(C38="UNSEC",F38*J38,IF(C38="MARGIN",F38*MAX(0,G38-(1-p_oai_drop)*(1-g_c_gpu))/G38,IF(C38="ANTH",F38*(L38*0.1+(1-L38)*0.7)+p_uw_drop,0)))))) -> 0 | R38: =IF(C38="RCF",1,0) -> 0 | S38: 3.2 | T38: 0 | U38: 0 | V38: 0 | W38: 0 | X38: 0 | Y38: 0 | Z38: 0 | AA38: 0 | AB38: 0 | AC38: 0 | AD38: 0 | AE38: 0 | AF38: 0 | AG38: 0 | AH38: 0 | AI38: 0 | AJ38: 0 | AK38: 0 | AL38: 0 | AM38: 0 | AN38: 0 | AO38: 0 | AP38: 0 | AQ38: 0 | AR38: Fluidstack unrated; Alphabet: Aa2/AA+ stable (FWP 7-Aug-2026) | AS38: no bank hold attributed (non-bank, distributed or n.d.)
A39: 33 | B39: Tract Capital HY bonds | C39: NONE | E39: =IF(C39="NONE",0,IFERROR(INDEX(rng_lessee_pd,MATCH(D39,rng_lessee_key,0)),g_pd_unrated)) -> 0 | F39: =IF(E39<=0,0,NORMSDIST((NORMSINV(E39)-SQRT(g_rho_ai)*p_z_ai)/SQRT(1-g_rho_ai))) -> 0 | G39: 0 | H39: 0 | I39: 0 | J39: 0 | K39: 0 | L39: 0 | M39: 0 | N39: =G39*(1-H39) -> 0 | O39: =(1-p_gpu_r)^g_t_def -> 0.2809 | P39: =IF(N39>0,MAX(0,1-(1-g_c_gpu)*O39/N39)*(1-I39),0) -> 0 | Q39: =IF(C39="GPU",F39*P39+K39*p_uw_drop,IF(C39="RCF",p_ccf_ai*F39*J39,IF(C39="DC",F39*J39+K39*p_uw_drop+M39/100,IF(C39="UNSEC",F39*J39,IF(C39="MARGIN",F39*MAX(0,G39-(1-p_oai_drop)*(1-g_c_gpu))/G39,IF(C39="ANTH",F39*(L39*0.1+(1-L39)*0.7)+p_uw_drop,0)))))) -> 0 | R39: =IF(C39="RCF",1,0) -> 0 | S39: 3.8 | T39: 0 | U39: 0 | V39: 0 | W39: 0 | X39: 0 | Y39: 0 | Z39: 0 | AA39: 0 | AB39: 0 | AC39: 0 | AD39: 0 | AE39: 0 | AF39: 0 | AG39: 0 | AH39: 0 | AI39: 0 | AJ39: 0 | AK39: 0 | AL39: 0 | AM39: 0 | AN39: 0 | AO39: 0 | AP39: 0 | AQ39: 0 | AR39: just below IG | AS39: no bank hold attributed (non-bank, distributed or n.d.)
A40: 34 | B40: SoftBank bridge for OpenAI follow-on | C40: UNSEC | D40: SBG | E40: =IF(C40="NONE",0,IFERROR(INDEX(rng_lessee_pd,MATCH(D40,rng_lessee_key,0)),g_pd_unrated)) -> 0.015 | F40: =IF(E40<=0,0,NORMSDIST((NORMSINV(E40)-SQRT(g_rho_ai)*p_z_ai)/SQRT(1-g_rho_ai))) -> 0.16925336 | G40: 0 | H40: 0 | I40: 0 | J40: 0.45 | K40: 0 | L40: 0 | M40: 0 | N40: =G40*(1-H40) -> 0 | O40: =(1-p_gpu_r)^g_t_def -> 0.2809 | P40: =IF(N40>0,MAX(0,1-(1-g_c_gpu)*O40/N40)*(1-I40),0) -> 0 | Q40: =IF(C40="GPU",F40*P40+K40*p_uw_drop,IF(C40="RCF",p_ccf_ai*F40*J40,IF(C40="DC",F40*J40+K40*p_uw_drop+M40/100,IF(C40="UNSEC",F40*J40,IF(C40="MARGIN",F40*MAX(0,G40-(1-p_oai_drop)*(1-g_c_gpu))/G40,IF(C40="ANTH",F40*(L40*0.1+(1-L40)*0.7)+p_uw_drop,0)))))) -> 0.076164013 | R40: =IF(C40="RCF",1,0) -> 0 | S40: 40 | T40: 4 | U40: 0 | V40: 0 | W40: 0 | X40: 4 | Y40: 0 | Z40: 0 | AA40: 0 | AB40: 0 | AC40: 0 | AD40: 0 | AE40: 0 | AF40: 0 | AG40: 0 | AH40: 1.5 | AI40: 0 | AJ40: 1.5 | AK40: 0 | AL40: 0 | AM40: 4 | AN40: 4 | AO40: 4 | AP40: 0 | AQ40: 0 | AR40: SoftBank: S&P BB+ neg (3-Mar-2026); Moody's unsolicited (level n/f) | AS40: SoftBank $40bn unsecured bridge due Mar-27 (LGD 45% EST: SBG LTV 13-33%)
A41: 35 | B41: SoftBank margin loan on OpenAI preferred shares | C41: MARGIN | D41: SBG | E41: =IF(C41="NONE",0,IFERROR(INDEX(rng_lessee_pd,MATCH(D41,rng_lessee_key,0)),g_pd_unrated)) -> 0.015 | F41: =IF(E41<=0,0,NORMSDIST((NORMSINV(E41)-SQRT(g_rho_ai)*p_z_ai)/SQRT(1-g_rho_ai))) -> 0.16925336 | G41: 0.112 | H41: 0 | I41: 0 | J41: 0 | K41: 0 | L41: 0 | M41: 0 | N41: =G41*(1-H41) -> 0.112 | O41: =(1-p_gpu_r)^g_t_def -> 0.2809 | P41: =IF(N41>0,MAX(0,1-(1-g_c_gpu)*O41/N41)*(1-I41),0) -> 0 | Q41: =IF(C41="GPU",F41*P41+K41*p_uw_drop,IF(C41="RCF",p_ccf_ai*F41*J41,IF(C41="DC",F41*J41+K41*p_uw_drop+M41/100,IF(C41="UNSEC",F41*J41,IF(C41="MARGIN",F41*MAX(0,G41-(1-p_oai_drop)*(1-g_c_gpu))/G41,IF(C41="ANTH",F41*(L41*0.1+(1-L41)*0.7)+p_uw_drop,0)))))) -> 0 | R41: =IF(C41="RCF",1,0) -> 0 | S41: 10 | T41: 2 | U41: 0 | V41: 0 | W41: 0 | X41: 2 | Y41: 0 | Z41: 0 | AA41: 0 | AB41: 0 | AC41: 0 | AD41: 0 | AE41: 0 | AF41: 0 | AG41: 0 | AH41: 0 | AI41: 0 | AJ41: 0 | AK41: 0 | AL41: 0 | AM41: 0 | AN41: 2 | AO41: 2 | AP41: 0 | AQ41: 0 | AR41: SoftBank: S&P BB+ neg (3-Mar-2026); Moody's unsolicited (level n/f) | AS41: SoftBank margin loan on OpenAI prefs; LTV <=11.2% of stake
A42: 36 | B42: SpaceX/xAI acquisition bridge (precedent) | C42: NONE | E42: =IF(C42="NONE",0,IFERROR(INDEX(rng_lessee_pd,MATCH(D42,rng_lessee_key,0)),g_pd_unrated)) -> 0 | F42: =IF(E42<=0,0,NORMSDIST((NORMSINV(E42)-SQRT(g_rho_ai)*p_z_ai)/SQRT(1-g_rho_ai))) -> 0 | G42: 0 | H42: 0 | I42: 0 | J42: 0 | K42: 0 | L42: 0 | M42: 0 | N42: =G42*(1-H42) -> 0 | O42: =(1-p_gpu_r)^g_t_def -> 0.2809 | P42: =IF(N42>0,MAX(0,1-(1-g_c_gpu)*O42/N42)*(1-I42),0) -> 0 | Q42: =IF(C42="GPU",F42*P42+K42*p_uw_drop,IF(C42="RCF",p_ccf_ai*F42*J42,IF(C42="DC",F42*J42+K42*p_uw_drop+M42/100,IF(C42="UNSEC",F42*J42,IF(C42="MARGIN",F42*MAX(0,G42-(1-p_oai_drop)*(1-g_c_gpu))/G42,IF(C42="ANTH",F42*(L42*0.1+(1-L42)*0.7)+p_uw_drop,0)))))) -> 0 | R42: =IF(C42="RCF",1,0) -> 0 | S42: 20 | T42: 0 | U42: 0 | V42: 0 | W42: 0 | X42: 0 | Y42: 0 | Z42: 0 | AA42: 0 | AB42: 0 | AC42: 0 | AD42: 0 | AE42: 0 | AF42: 0 | AG42: 0 | AH42: 0 | AI42: 0 | AJ42: 0 | AK42: 0 | AL42: 0 | AM42: 0 | AN42: 0 | AO42: 0 | AP42: 0 | AQ42: 0 | AR42: SpaceX (incl. xAI): Baa1/BBB/BBB+ stable (19-Jun-2026) | AS42: no bank hold attributed (non-bank, distributed or n.d.)
A43: 37 | B43: Stonebriar equipment ABS (15% GPU) | C43: NONE | E43: =IF(C43="NONE",0,IFERROR(INDEX(rng_lessee_pd,MATCH(D43,rng_lessee_key,0)),g_pd_unrated)) -> 0 | F43: =IF(E43<=0,0,NORMSDIST((NORMSINV(E43)-SQRT(g_rho_ai)*p_z_ai)/SQRT(1-g_rho_ai))) -> 0 | G43: 0 | H43: 0 | I43: 0 | J43: 0 | K43: 0 | L43: 0 | M43: 0 | N43: =G43*(1-H43) -> 0 | O43: =(1-p_gpu_r)^g_t_def -> 0.2809 | P43: =IF(N43>0,MAX(0,1-(1-g_c_gpu)*O43/N43)*(1-I43),0) -> 0 | Q43: =IF(C43="GPU",F43*P43+K43*p_uw_drop,IF(C43="RCF",p_ccf_ai*F43*J43,IF(C43="DC",F43*J43+K43*p_uw_drop+M43/100,IF(C43="UNSEC",F43*J43,IF(C43="MARGIN",F43*MAX(0,G43-(1-p_oai_drop)*(1-g_c_gpu))/G43,IF(C43="ANTH",F43*(L43*0.1+(1-L43)*0.7)+p_uw_drop,0)))))) -> 0 | R43: =IF(C43="RCF",1,0) -> 0 | S43: 0.869 | T43: 0 | U43: 0 | V43: 0 | W43: 0 | X43: 0 | Y43: 0 | Z43: 0 | AA43: 0 | AB43: 0 | AC43: 0 | AD43: 0 | AE43: 0 | AF43: 0 | AG43: 0 | AH43: 0 | AI43: 0 | AJ43: 0 | AK43: 0 | AL43: 0 | AM43: 0 | AN43: 0 | AO43: 0 | AP43: 0 | AQ43: 0 | AR43: ABS expected AAA to BBB- (KBRA collateral report) | AS43: no bank hold attributed (non-bank, distributed or n.d.)
A44: 38 | B44: Wingspire equipment ABS (20% GPU) | C44: NONE | E44: =IF(C44="NONE",0,IFERROR(INDEX(rng_lessee_pd,MATCH(D44,rng_lessee_key,0)),g_pd_unrated)) -> 0 | F44: =IF(E44<=0,0,NORMSDIST((NORMSINV(E44)-SQRT(g_rho_ai)*p_z_ai)/SQRT(1-g_rho_ai))) -> 0 | G44: 0 | H44: 0 | I44: 0 | J44: 0 | K44: 0 | L44: 0 | M44: 0 | N44: =G44*(1-H44) -> 0 | O44: =(1-p_gpu_r)^g_t_def -> 0.2809 | P44: =IF(N44>0,MAX(0,1-(1-g_c_gpu)*O44/N44)*(1-I44),0) -> 0 | Q44: =IF(C44="GPU",F44*P44+K44*p_uw_drop,IF(C44="RCF",p_ccf_ai*F44*J44,IF(C44="DC",F44*J44+K44*p_uw_drop+M44/100,IF(C44="UNSEC",F44*J44,IF(C44="MARGIN",F44*MAX(0,G44-(1-p_oai_drop)*(1-g_c_gpu))/G44,IF(C44="ANTH",F44*(L44*0.1+(1-L44)*0.7)+p_uw_drop,0)))))) -> 0 | R44: =IF(C44="RCF",1,0) -> 0 | S44: 0.407 | T44: 0 | U44: 0 | V44: 0 | W44: 0 | X44: 0 | Y44: 0 | Z44: 0 | AA44: 0 | AB44: 0 | AC44: 0 | AD44: 0 | AE44: 0 | AF44: 0 | AG44: 0 | AH44: 0 | AI44: 0 | AJ44: 0 | AK44: 0 | AL44: 0 | AM44: 0 | AN44: 0 | AO44: 0 | AP44: 0 | AQ44: 0 | AR44: ABS rated up to AAA | AS44: no bank hold attributed (non-bank, distributed or n.d.)
B46: Total holds by bank ($bn) | T46: =SUM(T6:T44) -> 19.637 | U46: =SUM(U6:U44) -> 18.092 | V46: =SUM(V6:V44) -> 18.497 | W46: =SUM(W6:W44) -> 1.369 | X46: =SUM(X6:X44) -> 9.947 | Y46: =SUM(Y6:Y44) -> 27.011 | Z46: =SUM(Z6:Z44) -> 0.177 | AA46: =SUM(AA6:AA44) -> 1.417 | ... AQ46: =SUM(AQ6:AQ44) -> 0.75
B47: Category codes: GPU = GPU-collateralised loan; DC = data-centre real estate / construction; RCF = revolver (drawn in stress); UNSEC = unsecured corporate bridge; MARGIN = share-backed margin loan; ANTH = $60bn Anthropic package (senior Broadcom-backstopped LGD 10%, junior LGD 70%); NONE = no bank hold attributed.

Sheet CreditEngine
A1: Credit engine: look-through pool (bank -> IG intermediary -> junk loans), rating migration, fund finance
A2: Vasicek one-factor 3-yr conditional PD: PD(z) = N[(N^-1(PD3 + hidden) - sqrt(rho) z) / sqrt(1-rho)]. Only the increase over the base case (z=0, base LGD) is a loss: carrying values already embed base expected loss.
A5: Rating | B5: Pool weight | C5: PD 3-yr (S&P avg) | D5: PD + hidden | E5: PD(z) generic | F5: PD(z) software | G5: PD base (z=0) | H5: T avg ->CCC | I5: T avg ->D | J5: T 2009 ->CCC | K5: T 2009 ->D
A6: B+ | B6: 0.07 | C6: 0.0805 | D6: =MIN(0.999,C6+p_hid) -> 0.1425 | E6: =NORMSDIST((NORMSINV(D6)-SQRT(g_rho)*p_z)/SQRT(1-g_rho)) -> 0.52179087 | F6: =NORMSDIST((NORMSINV(MIN(0.999,D6*p_m_sw))-SQRT(g_rho)*p_z)/SQRT(1-g_rho)) -> 0.73068933 | G6: =NORMSDIST(NORMSINV(C6)/SQRT(1-g_rho)) -> 0.058537901 | H6: 0.019 | I6: 0.021 | J6: 0.043 | K6: 0.039
A7: B | B7: 0.24 | C7: 0.0968 | D7: =MIN(0.999,C7+p_hid) -> 0.1588 | E7: =NORMSDIST((NORMSINV(D7)-SQRT(g_rho)*p_z)/SQRT(1-g_rho)) -> 0.55275882 | F7: =NORMSDIST((NORMSINV(MIN(0.999,D7*p_m_sw))-SQRT(g_rho)*p_z)/SQRT(1-g_rho)) -> 0.76410869 | G7: =NORMSDIST(NORMSINV(C7)/SQRT(1-g_rho)) -> 0.073049794 | H7: 0.043 | I7: 0.031 | J7: 0.127 | K7: 0.089
A8: B- | B8: 0.44 | C8: 0.1594 | D8: =MIN(0.999,C8+p_hid) -> 0.2214 | E8: =NORMSDIST((NORMSINV(D8)-SQRT(g_rho)*p_z)/SQRT(1-g_rho)) -> 0.65244816 | F8: =NORMSDIST((NORMSINV(MIN(0.999,D8*p_m_sw))-SQRT(g_rho)*p_z)/SQRT(1-g_rho)) -> 0.86195481 | G8: =NORMSDIST(NORMSINV(C8)/SQRT(1-g_rho)) -> 0.13251133 | H8: 0.135 | I8: 0.06 | J8: 0.237 | K8: 0.089
A9: CCC+ | B9: 0.09 | C9: 0.4132 | D9: =MIN(0.999,C9+p_hid) -> 0.4752 | E9: =NORMSDIST((NORMSINV(D9)-SQRT(g_rho)*p_z)/SQRT(1-g_rho)) -> 0.88109001 | F9: =NORMSDIST((NORMSINV(MIN(0.999,D9*p_m_sw))-SQRT(g_rho)*p_z)/SQRT(1-g_rho)) -> 0.99901045 | G9: =NORMSDIST(NORMSINV(C9)/SQRT(1-g_rho)) -> 0.40314756 | H9: 0.53 | I9: 0.307 | J9: 0.607 | K9: 0.309
A10: CCC | B10: 0.16 | C10: 0.4132 | D10: =MIN(0.999,C10+p_hid) -> 0.4752 | E10: =NORMSDIST((NORMSINV(D10)-SQRT(g_rho)*p_z)/SQRT(1-g_rho)) -> 0.88109001 | F10: =NORMSDIST((NORMSINV(MIN(0.999,D10*p_m_sw))-SQRT(g_rho)*p_z)/SQRT(1-g_rho)) -> 0.99901045 | G10: =NORMSDIST(NORMSINV(C10)/SQRT(1-g_rho)) -> 0.40314756 | H10: 0.53 | I10: 0.307 | J10: 0.607 | K10: 0.309
A12: Sources: pool weights = Fitch private-credit rating distribution Q3-25 via FSB May-26; PD 3-yr = S&P 2024 study Table 26; transitions = S&P 1981-2024 (NR-adj) and Moody's 2009.
A14: Name | B14: Item | C14: Value
A15: CE_PDg | B15: Pool PD 3-yr, generic | C15: =SUMPRODUCT(B6:B10,E6:E10) -> 0.67653717
A16: CE_PDs | B16: Pool PD 3-yr, software | C16: =SUMPRODUCT(B6:B10,F6:F10) -> 0.86354707
A17: CE_PDb | B17: Pool PD 3-yr, base case (embedded in marks) | C17: =SUMPRODUCT(B6:B10,G6:G10) -> 0.18072148
A18: CE_Lg | B18: Incremental credit loss, generic | C18: =CE_PDg*p_lgd_gen-CE_PDb*g_lgd_gen_b -> 0.27501607
A19: CE_Ls | B19: Incremental credit loss, software | C19: =CE_PDs*p_lgd_sw-CE_PDb*g_lgd_sw_b -> 0.51412221
A20: CE_MTMg | B20: Spread MTM on performing, generic | C20: =(1-CE_PDg)*p_ds/10000*g_dur_s -> 0.067927194
A21: CE_MTMs | B21: Spread MTM on performing, software | C21: =(1-CE_PDs)*(p_ds+p_ds_sw)/10000*g_dur_s -> 0.040935879
A22: CE_sw_sys | B22: System software share (asset-weighted BDC) | C22: =SUMPRODUCT(BDC!C6:C39,BDC!D6:D39)/SUM(BDC!C6:C39) -> 0.19620044
A23: CE_mk_sys | B23: System market-implied mark (asset-weighted BDC) | C23: =SUMPRODUCT(BDC!C6:C39,BDC!M6:M39)/SUM(BDC!C6:C39) -> 0.88433128
A24: CE_Vh_g | B24: Generic pool value, hold / workout | C24: =1-((1-CE_sw_sys)*CE_Lg+CE_sw_sys*CE_Ls)-p_gap-p_w_mkt*(1-CE_mk_sys) -> 0.46240249
A25: CE_MTM_sys | B25: Generic pool spread MTM | C25: =(1-CE_sw_sys)*CE_MTMg+CE_sw_sys*CE_MTMs -> 0.062631486
A26: CE_Vh_a | B26: ABF / SE pool value, hold | C26: =1-p_abf_loss -> 0.75
A27: CE_Vl_g0 | B27: Generic pool value, liquidated (no fire-sale) | C27: =CE_Vh_g-CE_MTM_sys-p_c_liq -> 0.349771
A28: CE_LRg0 | B28: Loss rate on generic SPV back-leverage (standalone) | C28: =p_phi*MAX(0,p_a_spv-CE_Vl_g0)/p_a_spv+(1-p_phi)*MAX(0,p_a_spv-CE_Vh_g)/p_a_spv -> 0.46814672
A29: CE_LRa0 | B29: Loss rate on ABF / SE warehouses (standalone) | C29: =p_phi*MAX(0,g_a_abf-(CE_Vh_a-p_c_liq))/g_a_abf+(1-p_phi)*MAX(0,g_a_abf-CE_Vh_a)/g_a_abf -> 0.1125
A30: CE_LRtrs0 | B30: Loss rate on written sub-IG TRS (standalone) | C30: =p_phi*MAX(0,g_trs_adv-CE_Vl_g0)/g_trs_adv+(1-p_phi)*MAX(0,g_trs_adv-CE_Vh_g)/g_trs_adv -> 0.53462838
A31: CE_ccc_avg | B31: Pool share to CCC/D in 1 yr, average matrix | C31: =SUMPRODUCT(B6:B10,H6:H10)+SUMPRODUCT(B6:B10,I6:I10) -> 0.31561
A32: CE_ccc_09 | B32: Pool share to CCC/D in 1 yr, 2009 matrix | C32: =SUMPRODUCT(B6:B10,J6:J10)+SUMPRODUCT(B6:B10,K6:K10) -> 0.43002
A33: CE_ccc_new | B33: Pool share to CCC/D, scenario | C33: =CE_ccc_avg+p_w_mig*(CE_ccc_09-CE_ccc_avg) -> 0.487225
A34: CE_mig_hc | B34: Borrowing-base haircut from migration | C34: =MAX(0,CE_ccc_new-g_ccc0)*(g_adv_perf-g_adv_np)/g_adv_perf -> 0.12558971
A35: CE_LRnav | B35: Loss rate, NAV loans | C35: =g_tail_share*MAX(0,g_nav_ltv-(1-MIN(0.99,p_dnav*g_tail_mult)))/g_nav_ltv+(1-g_tail_share)*MAX(0,g_nav_ltv-(1-p_dnav))/g_nav_ltv -> 0.19
A36: CE_LRff | B36: Loss rate, fund finance (sub lines + NAV) | C36: =(1-g_nav_share)*p_lp_dr*g_lgd_lp+g_nav_share*CE_LRnav -> 0.04125
A37: CE_nonbank_pcl | B37: Private-credit loans sold by non-banks ($bn) | C37: =p_pc_scale*SUM(BDC!Y6:Y39) -> 147.39917
A38: CE_ins_sales | B38: Insurer forced sales ($bn) | C38: =p_ins_run*(g_fabr+g_fabn_6m) -> 29.5625
A40: AI lessee 3-yr PDs (S&P Table 26, 3-yr column)
A41: Key | B41: PD 3-yr | C41: Basis
A42: CRWV | B42: 0.0805 | C42: CoreWeave S&P B+
A43: META | B43: 0.0015 | C43: Meta AA-
A44: NBIS | B44: 0.0267 | C44: Nebius unrated w/ Microsoft offtake ~BB (judgment)
A45: CRUSOE | B45: 0.0968 | C45: Crusoe unrated ~B (judgment)
A46: ANTH | B46: =g_pd_unrated -> 0.0805 | C46: Anthropic unrated -> pd_unrated
A47: ORCL | B47: 0.0117 | C47: Oracle S&P BBB-
A48: SBG | B48: 0.015 | C48: SoftBank S&P BB+

Sheet Modules
A1: Standalone module losses by bank (USD bn, pre-tax) - each module can be switched off in Scenarios (sw_M*)
A2: M1 back-leverage look-through | M2 fund finance | M3 ABF / structured entities | M4 PE-owned insurers | M5 AI / GPU | M6 trading & HFS MTM | M7 CRE | M8 rates (AFS + forced HTM sales) | M9 SRT relief loss | M10 written sub-IG TRS | M11 prime / margin gap risk.
A5: Id | B5: Institution | C5: M1a named BDC facilities | D5: M1b generic back-leverage | E5: M1c collateral fraud | F5: M1 back-leverage | G5: M2 fund finance | H5: M3 ABF / SE | I5: M4 insurers | J5: M5 AI / GPU | K5: M6 trading / HFS | L5: M7 CRE | M5: AFS MTM (rates) | N5: HTM / opt-out AFS loss pool | O5: M8 rates | P5: M9 SRT | Q5: M10 TRS | R5: M11 prime | S5: Total standalone loss | T5: Contagion-invariant losses | U5: Capital base (CET1 + PPNR credit) | V5: Stressed RWA | W5: CET1 after standalone | X5: CET1 ratio after standalone | Y5: Committed lines drawn ($bn, liquidity) | Z5: AI RCF draws ($bn)
A6: JPM | B6: JPMorgan | C6: =SUMPRODUCT(BDC_EAD!C$106:C$127,BDC_EAD!$AB$106:$AB$127)+SUMPRODUCT(BDC_EAD!C$131:C$152,BDC_EAD!$AC$106:$AC$127) -> 0.92251523 | D6: =(Inputs_Banks!$Y6+p_ccf_bl*Inputs_Banks!$Z6)*CE_LRg0 -> 34.275445 | E6: =p_fraud*(Inputs_Banks!$Q6+Inputs_Banks!$S6+Inputs_Banks!$U6) -> 1.245 | F6: =p_sw_M1*(C6+D6+E6) -> 36.44296 | G6: =p_sw_M2*(Inputs_Banks!$S6+p_ccf_ff*Inputs_Banks!$T6)*CE_LRff -> 3.7356 | H6: =p_sw_M3*(Inputs_Banks!$U6+p_ccf_abf*Inputs_Banks!$V6)*CE_LRa0 -> 0 | I6: =p_sw_M4*(Inputs_Banks!$AD6*p_ccf_ins+Inputs_Banks!$AE6)*p_pd_ins*g_lgd_ins -> 0.273 | J6: =p_sw_M5*SUMPRODUCT(AI_Deals!T$6:T$44,AI_Deals!$Q$6:$Q$44) -> 3.5060249 | K6: =p_sw_M6*(SUMPRODUCT(Holdings!$C6:$O6,Holdings!$C$32:$O$32,Holdings!$C$35:$O$35)+Inputs_Banks!$P6*(-p_dp_EQ)) -> 17.68396 | L6: =p_sw_M7*Inputs_Banks!$AF6*p_cre_lr -> 12.6217 | M6: =Inputs_Banks!$E6*Inputs_Banks!$K6*Inputs_Banks!$O6*p_dy -> 13.4012 | N6: =MAX(0,-Inputs_Banks!$N6+Inputs_Banks!$M6*g_dur_htm*p_dy)+(1-Inputs_Banks!$E6)*MAX(0,-Inputs_Banks!$L6+Inputs_Banks!$K6*Inputs_Banks!$O6*p_dy) -> 34.27244 | O6: =p_sw_M8*(M6+N6*p_htm_forced) -> 13.4012 | P6: =p_sw_M9*p_srt_lost*Inputs_Banks!$AA6/10000*Inputs_Banks!$H6 -> 0 | Q6: =p_sw_M10*Inputs_Banks!$AC6*CE_LRtrs0 -> 0 | R6: =p_sw_M11*Inputs_Banks!$AB6*p_pb_pd*MAX(0,p_pb_shock*g_pb_conc-g_pb_margin) -> 2.877105 | S6: =F6+G6+H6+I6+J6+K6+L6+O6+P6+Q6+R6 -> 90.54155 | T6: =G6+I6+J6+K6+L6+P6+R6 -> 40.69739 | U6: =Inputs_Banks!$G6+p_ppnr_q*Inputs_Banks!$J6 -> 304.1 | V6: =Inputs_Banks!$H6*(1+p_rwa_infl) -> 2358.18 | W6: =U6-(1-p_tax)*S6 -> 213.55845 | X6: =W6/V6 -> 0.090560708 | Y6: =p_sw_M1*(p_ccf_bl*Inputs_Banks!$Z6+BDC_EAD!C$154)+p_sw_M2*p_ccf_ff*Inputs_Banks!$T6+p_sw_M3*p_ccf_abf*Inputs_Banks!$V6+p_sw_M5*Z6+p_sw_M4*p_ccf_ins*Inputs_Banks!$AD6 -> 45.160097 | Z6: =p_ccf_ai*SUMPRODUCT(AI_Deals!T$6:T$44,AI_Deals!$R$6:$R$44) -> 1.635
A7: BAC | B7: Bank of America | C7: =SUMPRODUCT(BDC_EAD!D$106:D$127,BDC_EAD!$AB$106:$AB$127)+SUMPRODUCT(BDC_EAD!D$131:D$152,BDC_EAD!$AC$106:$AC$127) -> 2.9794608 | D7: =(Inputs_Banks!$Y7+p_ccf_bl*Inputs_Banks!$Z7)*CE_LRg0 -> 13.343444 | E7: =p_fraud*(Inputs_Banks!$Q7+Inputs_Banks!$S7+Inputs_Banks!$U7) -> 0.688 | F7: =p_sw_M1*(C7+D7+E7) -> 17.010904 | G7: =p_sw_M2*(Inputs_Banks!$S7+p_ccf_ff*Inputs_Banks!$T7)*CE_LRff -> 2.31825 | H7: =p_sw_M3*(Inputs_Banks!$U7+p_ccf_abf*Inputs_Banks!$V7)*CE_LRa0 -> 0 | I7: =p_sw_M4*(Inputs_Banks!$AD7*p_ccf_ins+Inputs_Banks!$AE7)*p_pd_ins*g_lgd_ins -> 0.273 | J7: =p_sw_M5*SUMPRODUCT(AI_Deals!U$6:U$44,AI_Deals!$Q$6:$Q$44) -> 4.620063 | K7: =p_sw_M6*(SUMPRODUCT(Holdings!$C7:$O7,Holdings!$C$32:$O$32,Holdings!$C$35:$O$35)+Inputs_Banks!$P7*(-p_dp_EQ)) -> 7.077 | L7: =p_sw_M7*Inputs_Banks!$AF7*p_cre_lr -> 5.8317 | M7: =Inputs_Banks!$E7*Inputs_Banks!$K7*Inputs_Banks!$O7*p_dy -> 8.7135 | N7: =MAX(0,-Inputs_Banks!$N7+Inputs_Banks!$M7*g_dur_htm*p_dy)+(1-Inputs_Banks!$E7)*MAX(0,-Inputs_Banks!$L7+Inputs_Banks!$K7*Inputs_Banks!$O7*p_dy) -> 112.44194 | O7: =p_sw_M8*(M7+N7*p_htm_forced) -> 8.7135 | P7: =p_sw_M9*p_srt_lost*Inputs_Banks!$AA7/10000*Inputs_Banks!$H7 -> 0 | Q7: =p_sw_M10*Inputs_Banks!$AC7*CE_LRtrs0 -> 26.660313 | R7: =p_sw_M11*Inputs_Banks!$AB7*p_pb_pd*MAX(0,p_pb_shock*g_pb_conc-g_pb_margin) -> 0 | S7: =F7+G7+H7+I7+J7+K7+L7+O7+P7+Q7+R7 -> 72.504731 | T7: =G7+I7+J7+K7+L7+P7+R7 -> 20.120013 | U7: =Inputs_Banks!$G7+p_ppnr_q*Inputs_Banks!$J7 -> 198.4 | V7: =Inputs_Banks!$H7*(1+p_rwa_infl) -> 1969.812 | W7: =U7-(1-p_tax)*S7 -> 125.89527 | X7: =W7/V7 -> 0.063912327 | Y7: =p_sw_M1*(p_ccf_bl*Inputs_Banks!$Z7+BDC_EAD!D$154)+p_sw_M2*p_ccf_ff*Inputs_Banks!$T7+p_sw_M3*p_ccf_abf*Inputs_Banks!$V7+p_sw_M5*Z7+p_sw_M4*p_ccf_ins*Inputs_Banks!$AD7 -> 25.538609 | Z7: =p_ccf_ai*SUMPRODUCT(AI_Deals!U$6:U$44,AI_Deals!$R$6:$R$44) -> 1
A8: C | B8: Citigroup | C8: =SUMPRODUCT(BDC_EAD!E$106:E$127,BDC_EAD!$AB$106:$AB$127)+SUMPRODUCT(BDC_EAD!E$131:E$152,BDC_EAD!$AC$106:$AC$127) -> 1.7362179 | D8: =(Inputs_Banks!$Y8+p_ccf_bl*Inputs_Banks!$Z8)*CE_LRg0 -> 30.0399 | E8: =p_fraud*(Inputs_Banks!$Q8+Inputs_Banks!$S8+Inputs_Banks!$U8) -> 0.71 | F8: =p_sw_M1*(C8+D8+E8) -> 32.486118 | G8: =p_sw_M2*(Inputs_Banks!$S8+p_ccf_ff*Inputs_Banks!$T8)*CE_LRff -> 0.4752 | H8: =p_sw_M3*(Inputs_Banks!$U8+p_ccf_abf*Inputs_Banks!$V8)*CE_LRa0 -> 1.1925 | I8: =p_sw_M4*(Inputs_Banks!$AD8*p_ccf_ins+Inputs_Banks!$AE8)*p_pd_ins*g_lgd_ins -> 0.453 | J8: =p_sw_M5*SUMPRODUCT(AI_Deals!V$6:V$44,AI_Deals!$Q$6:$Q$44) -> 4.7531194 | K8: =p_sw_M6*(SUMPRODUCT(Holdings!$C8:$O8,Holdings!$C$32:$O$32,Holdings!$C$35:$O$35)+Inputs_Banks!$P8*(-p_dp_EQ)) -> 5.86777 | L8: =p_sw_M7*Inputs_Banks!$AF8*p_cre_lr -> 2.6033 | M8: =Inputs_Banks!$E8*Inputs_Banks!$K8*Inputs_Banks!$O8*p_dy -> 7.169125 | N8: =MAX(0,-Inputs_Banks!$N8+Inputs_Banks!$M8*g_dur_htm*p_dy)+(1-Inputs_Banks!$E8)*MAX(0,-Inputs_Banks!$L8+Inputs_Banks!$K8*Inputs_Banks!$O8*p_dy) -> 20.44258 | O8: =p_sw_M8*(M8+N8*p_htm_forced) -> 7.169125 | P8: =p_sw_M9*p_srt_lost*Inputs_Banks!$AA8/10000*Inputs_Banks!$H8 -> 0 | Q8: =p_sw_M10*Inputs_Banks!$AC8*CE_LRtrs0 -> 0 | R8: =p_sw_M11*Inputs_Banks!$AB8*p_pb_pd*MAX(0,p_pb_shock*g_pb_conc-g_pb_margin) -> 2.91627 | S8: =F8+G8+H8+I8+J8+K8+L8+O8+P8+Q8+R8 -> 57.916402 | T8: =G8+I8+J8+K8+L8+P8+R8 -> 17.068659 | U8: =Inputs_Banks!$G8+p_ppnr_q*Inputs_Banks!$J8 -> 157.4 | V8: =Inputs_Banks!$H8*(1+p_rwa_infl) -> 1330.452 | W8: =U8-(1-p_tax)*S8 -> 99.483598 | X8: =W8/V8 -> 0.074774286 | Y8: =p_sw_M1*(p_ccf_bl*Inputs_Banks!$Z8+BDC_EAD!E$154)+p_sw_M2*p_ccf_ff*Inputs_Banks!$T8+p_sw_M3*p_ccf_abf*Inputs_Banks!$V8+p_sw_M5*Z8+p_sw_M4*p_ccf_ins*Inputs_Banks!$AD8 -> 24.886743 | Z8: =p_ccf_ai*SUMPRODUCT(AI_Deals!V$6:V$44,AI_Deals!$R$6:$R$44) -> 1.442
A9: WFC | B9: Wells Fargo | C9: =SUMPRODUCT(BDC_EAD!F$106:F$127,BDC_EAD!$AB$106:$AB$127)+SUMPRODUCT(BDC_EAD!F$131:F$152,BDC_EAD!$AC$106:$AC$127) -> 3.2922388 | D9: =(Inputs_Banks!$Y9+p_ccf_bl*Inputs_Banks!$Z9)*CE_LRg0 -> 44.804868 | E9: =p_fraud*(Inputs_Banks!$Q9+Inputs_Banks!$S9+Inputs_Banks!$U9) -> 1.287 | F9: =p_sw_M1*(C9+D9+E9) -> 49.384107 | G9: =p_sw_M2*(Inputs_Banks!$S9+p_ccf_ff*Inputs_Banks!$T9)*CE_LRff -> 3.021975 | H9: =p_sw_M3*(Inputs_Banks!$U9+p_ccf_abf*Inputs_Banks!$V9)*CE_LRa0 -> 0 | I9: =p_sw_M4*(Inputs_Banks!$AD9*p_ccf_ins+Inputs_Banks!$AE9)*p_pd_ins*g_lgd_ins -> 0.429 | J9: =p_sw_M5*SUMPRODUCT(AI_Deals!W$6:W$44,AI_Deals!$Q$6:$Q$44) -> 0.44980607 | K9: =p_sw_M6*(SUMPRODUCT(Holdings!$C9:$O9,Holdings!$C$32:$O$32,Holdings!$C$35:$O$35)+Inputs_Banks!$P9*(-p_dp_EQ)) -> 4.8184 | L9: =p_sw_M7*Inputs_Banks!$AF9*p_cre_lr -> 8.8214 | M9: =Inputs_Banks!$E9*Inputs_Banks!$K9*Inputs_Banks!$O9*p_dy -> 6.25815 | N9: =MAX(0,-Inputs_Banks!$N9+Inputs_Banks!$M9*g_dur_htm*p_dy)+(1-Inputs_Banks!$E9)*MAX(0,-Inputs_Banks!$L9+Inputs_Banks!$K9*Inputs_Banks!$O9*p_dy) -> 44.32238 | O9: =p_sw_M8*(M9+N9*p_htm_forced) -> 6.25815 | P9: =p_sw_M9*p_srt_lost*Inputs_Banks!$AA9/10000*Inputs_Banks!$H9 -> 0 | Q9: =p_sw_M10*Inputs_Banks!$AC9*CE_LRtrs0 -> 0 | R9: =p_sw_M11*Inputs_Banks!$AB9*p_pb_pd*MAX(0,p_pb_shock*g_pb_conc-g_pb_margin) -> 0 | S9: =F9+G9+H9+I9+J9+K9+L9+O9+P9+Q9+R9 -> 73.182838 | T9: =G9+I9+J9+K9+L9+P9+R9 -> 17.540581 | U9: =Inputs_Banks!$G9+p_ppnr_q*Inputs_Banks!$J9 -> 134.6 | V9: =Inputs_Banks!$H9*(1+p_rwa_infl) -> 1446.984 | W9: =U9-(1-p_tax)*S9 -> 61.417162 | X9: =W9/V9 -> 0.042444949 | Y9: =p_sw_M1*(p_ccf_bl*Inputs_Banks!$Z9+BDC_EAD!F$154)+p_sw_M2*p_ccf_ff*Inputs_Banks!$T9+p_sw_M3*p_ccf_abf*Inputs_Banks!$V9+p_sw_M5*Z9+p_sw_M4*p_ccf_ins*Inputs_Banks!$AD9 -> 53.06605 | Z9: =p_ccf_ai*SUMPRODUCT(AI_Deals!W$6:W$44,AI_Deals!$R$6:$R$44) -> 1.192
A10: GS | B10: Goldman Sachs | C10: =SUMPRODUCT(BDC_EAD!G$106:G$127,BDC_EAD!$AB$106:$AB$127)+SUMPRODUCT(BDC_EAD!G$131:G$152,BDC_EAD!$AC$106:$AC$127) -> 1.0362851 | D10: =(Inputs_Banks!$Y10+p_ccf_bl*Inputs_Banks!$Z10)*CE_LRg0 -> 17.647558 | E10: =p_fraud*(Inputs_Banks!$Q10+Inputs_Banks!$S10+Inputs_Banks!$U10) -> 0.62 | F10: =p_sw_M1*(C10+D10+E10) -> 19.303843 | G10: =p_sw_M2*(Inputs_Banks!$S10+p_ccf_ff*Inputs_Banks!$T10)*CE_LRff -> 1.7886 | H10: =p_sw_M3*(Inputs_Banks!$U10+p_ccf_abf*Inputs_Banks!$V10)*CE_LRa0 -> 0 | I10: =p_sw_M4*(Inputs_Banks!$AD10*p_ccf_ins+Inputs_Banks!$AE10)*p_pd_ins*g_lgd_ins -> 0.273 | J10: =p_sw_M5*SUMPRODUCT(AI_Deals!X$6:X$44,AI_Deals!$Q$6:$Q$44) -> 1.565679 | K10: =p_sw_M6*(SUMPRODUCT(Holdings!$C10:$O10,Holdings!$C$32:$O$32,Holdings!$C$35:$O$35)+Inputs_Banks!$P10*(-p_dp_EQ)) -> 13.3488 | L10: =p_sw_M7*Inputs_Banks!$AF10*p_cre_lr -> 2.8217 | M10: =Inputs_Banks!$E10*Inputs_Banks!$K10*Inputs_Banks!$O10*p_dy -> 3.8909 | N10: =MAX(0,-Inputs_Banks!$N10+Inputs_Banks!$M10*g_dur_htm*p_dy)+(1-Inputs_Banks!$E10)*MAX(0,-Inputs_Banks!$L10+Inputs_Banks!$K10*Inputs_Banks!$O10*p_dy) -> 4.48248 | O10: =p_sw_M8*(M10+N10*p_htm_forced) -> 3.8909 | P10: =p_sw_M9*p_srt_lost*Inputs_Banks!$AA10/10000*Inputs_Banks!$H10 -> 0 | Q10: =p_sw_M10*Inputs_Banks!$AC10*CE_LRtrs0 -> 0 | R10: =p_sw_M11*Inputs_Banks!$AB10*p_pb_pd*MAX(0,p_pb_shock*g_pb_conc-g_pb_margin) -> 5.1044 | S10: =F10+G10+H10+I10+J10+K10+L10+O10+P10+Q10+R10 -> 48.096922 | T10: =G10+I10+J10+K10+L10+P10+R10 -> 24.902179 | U10: =Inputs_Banks!$G10+p_ppnr_q*Inputs_Banks!$J10 -> 101.4 | V10: =Inputs_Banks!$H10*(1+p_rwa_infl) -> 882.36 | W10: =U10-(1-p_tax)*S10 -> 53.303078 | X10: =W10/V10 -> 0.060409672 | Y10: =p_sw_M1*(p_ccf_bl*Inputs_Banks!$Z10+BDC_EAD!G$154)+p_sw_M2*p_ccf_ff*Inputs_Banks!$T10+p_sw_M3*p_ccf_abf*Inputs_Banks!$V10+p_sw_M5*Z10+p_sw_M4*p_ccf_ins*Inputs_Banks!$AD10 -> 24.475723 | Z10: =p_ccf_ai*SUMPRODUCT(AI_Deals!X$6:X$44,AI_Deals!$R$6:$R$44) -> 1.635
A11: MS | B11: Morgan Stanley | C11: =SUMPRODUCT(BDC_EAD!H$106:H$127,BDC_EAD!$AB$106:$AB$127)+SUMPRODUCT(BDC_EAD!H$131:H$152,BDC_EAD!$AC$106:$AC$127) -> 1.8303413 | D11: =(Inputs_Banks!$Y11+p_ccf_bl*Inputs_Banks!$Z11)*CE_LRg0 -> 12.528457 | E11: =p_fraud*(Inputs_Banks!$Q11+Inputs_Banks!$S11+Inputs_Banks!$U11) -> 0.329 | F11: =p_sw_M1*(C11+D11+E11) -> 14.687798 | G11: =p_sw_M2*(Inputs_Banks!$S11+p_ccf_ff*Inputs_Banks!$T11)*CE_LRff -> 0.705375 | H11: =p_sw_M3*(Inputs_Banks!$U11+p_ccf_abf*Inputs_Banks!$V11)*CE_LRa0 -> 0 | I11: =p_sw_M4*(Inputs_Banks!$AD11*p_ccf_ins+Inputs_Banks!$AE11)*p_pd_ins*g_lgd_ins -> 0.273 | J11: =p_sw_M5*SUMPRODUCT(AI_Deals!Y$6:Y$44,AI_Deals!$Q$6:$Q$44) -> 6.9829115 | K11: =p_sw_M6*(SUMPRODUCT(Holdings!$C11:$O11,Holdings!$C$32:$O$32,Holdings!$C$35:$O$35)+Inputs_Banks!$P11*(-p_dp_EQ)) -> 10.83874 | L11: =p_sw_M7*Inputs_Banks!$AF11*p_cre_lr -> 1.148 | M11: =Inputs_Banks!$E11*Inputs_Banks!$K11*Inputs_Banks!$O11*p_dy -> 2.6383 | N11: =MAX(0,-Inputs_Banks!$N11+Inputs_Banks!$M11*g_dur_htm*p_dy)+(1-Inputs_Banks!$E11)*MAX(0,-Inputs_Banks!$L11+Inputs_Banks!$K11*Inputs_Banks!$O11*p_dy) -> 10.37382 | O11: =p_sw_M8*(M11+N11*p_htm_forced) -> 2.6383 | P11: =p_sw_M9*p_srt_lost*Inputs_Banks!$AA11/10000*Inputs_Banks!$H11 -> 0 | Q11: =p_sw_M10*Inputs_Banks!$AC11*CE_LRtrs0 -> 0 | R11: =p_sw_M11*Inputs_Banks!$AB11*p_pb_pd*MAX(0,p_pb_shock*g_pb_conc-g_pb_margin) -> 3.51148 | S11: =F11+G11+H11+I11+J11+K11+L11+O11+P11+Q11+R11 -> 40.785604 | T11: =G11+I11+J11+K11+L11+P11+R11 -> 23.459506 | U11: =Inputs_Banks!$G11+p_ppnr_q*Inputs_Banks!$J11 -> 88.8 | V11: =Inputs_Banks!$H11*(1+p_rwa_infl) -> 643.464 | W11: =U11-(1-p_tax)*S11 -> 48.014396 | X11: =W11/V11 -> 0.07461862 | Y11: =p_sw_M1*(p_ccf_bl*Inputs_Banks!$Z11+BDC_EAD!H$154)+p_sw_M2*p_ccf_ff*Inputs_Banks!$T11+p_sw_M3*p_ccf_abf*Inputs_Banks!$V11+p_sw_M5*Z11+p_sw_M4*p_ccf_ins*Inputs_Banks!$AD11 -> 18.201384 | Z11: =p_ccf_ai*SUMPRODUCT(AI_Deals!Y$6:Y$44,AI_Deals!$R$6:$R$44) -> 1.635
A12: PNC | B12: PNC | C12: =SUMPRODUCT(BDC_EAD!I$106:I$127,BDC_EAD!$AB$106:$AB$127)+SUMPRODUCT(BDC_EAD!I$131:I$152,BDC_EAD!$AC$106:$AC$127) -> 0 | D12: =(Inputs_Banks!$Y12+p_ccf_bl*Inputs_Banks!$Z12)*CE_LRg0 -> 22.641854 | E12: =p_fraud*(Inputs_Banks!$Q12+Inputs_Banks!$S12+Inputs_Banks!$U12) -> 0.619 | F12: =p_sw_M1*(C12+D12+E12) -> 23.260854 | G12: =p_sw_M2*(Inputs_Banks!$S12+p_ccf_ff*Inputs_Banks!$T12)*CE_LRff -> 1.58565 | H12: =p_sw_M3*(Inputs_Banks!$U12+p_ccf_abf*Inputs_Banks!$V12)*CE_LRa0 -> 0 | I12: =p_sw_M4*(Inputs_Banks!$AD12*p_ccf_ins+Inputs_Banks!$AE12)*p_pd_ins*g_lgd_ins -> 0 | J12: =p_sw_M5*SUMPRODUCT(AI_Deals!Z$6:Z$44,AI_Deals!$Q$6:$Q$44) -> 0.039876801 | K12: =p_sw_M6*(SUMPRODUCT(Holdings!$C12:$O12,Holdings!$C$32:$O$32,Holdings!$C$35:$O$35)+Inputs_Banks!$P12*(-p_dp_EQ)) -> 0.55757 | L12: =p_sw_M7*Inputs_Banks!$AF12*p_cre_lr -> 3.3005 | M12: =Inputs_Banks!$E12*Inputs_Banks!$K12*Inputs_Banks!$O12*p_dy -> 0 | N12: =MAX(0,-Inputs_Banks!$N12+Inputs_Banks!$M12*g_dur_htm*p_dy)+(1-Inputs_Banks!$E12)*MAX(0,-Inputs_Banks!$L12+Inputs_Banks!$K12*Inputs_Banks!$O12*p_dy) -> 11.47286 | O12: =p_sw_M8*(M12+N12*p_htm_forced) -> 0 | P12: =p_sw_M9*p_srt_lost*Inputs_Banks!$AA12/10000*Inputs_Banks!$H12 -> 0 | Q12: =p_sw_M10*Inputs_Banks!$AC12*CE_LRtrs0 -> 0 | R12: =p_sw_M11*Inputs_Banks!$AB12*p_pb_pd*MAX(0,p_pb_shock*g_pb_conc-g_pb_margin) -> 0 | S12: =F12+G12+H12+I12+J12+K12+L12+O12+P12+Q12+R12 -> 28.744451 | T12: =G12+I12+J12+K12+L12+P12+R12 -> 5.4835968 | U12: =Inputs_Banks!$G12+p_ppnr_q*Inputs_Banks!$J12 -> 49.1 | V12: =Inputs_Banks!$H12*(1+p_rwa_infl) -> 540.864 | W12: =U12-(1-p_tax)*S12 -> 20.355549 | X12: =W12/V12 -> 0.037635245 | Y12: =p_sw_M1*(p_ccf_bl*Inputs_Banks!$Z12+BDC_EAD!I$154)+p_sw_M2*p_ccf_ff*Inputs_Banks!$T12+p_sw_M3*p_ccf_abf*Inputs_Banks!$V12+p_sw_M5*Z12+p_sw_M4*p_ccf_ins*Inputs_Banks!$AD12 -> 25.420487 | Z12: =p_ccf_ai*SUMPRODUCT(AI_Deals!Z$6:Z$44,AI_Deals!$R$6:$R$44) -> 0
A13: USB | B13: U.S. Bancorp | C13: =SUMPRODUCT(BDC_EAD!J$106:J$127,BDC_EAD!$AB$106:$AB$127)+SUMPRODUCT(BDC_EAD!J$131:J$152,BDC_EAD!$AC$106:$AC$127) -> 0 | D13: =(Inputs_Banks!$Y13+p_ccf_bl*Inputs_Banks!$Z13)*CE_LRg0 -> 8.4949994 | E13: =p_fraud*(Inputs_Banks!$Q13+Inputs_Banks!$S13+Inputs_Banks!$U13) -> 0.286 | F13: =p_sw_M1*(C13+D13+E13) -> 8.7809994 | G13: =p_sw_M2*(Inputs_Banks!$S13+p_ccf_ff*Inputs_Banks!$T13)*CE_LRff -> 0.89595 | H13: =p_sw_M3*(Inputs_Banks!$U13+p_ccf_abf*Inputs_Banks!$V13)*CE_LRa0 -> 0 | I13: =p_sw_M4*(Inputs_Banks!$AD13*p_ccf_ins+Inputs_Banks!$AE13)*p_pd_ins*g_lgd_ins -> 0 | J13: =p_sw_M5*SUMPRODUCT(AI_Deals!AA$6:AA$44,AI_Deals!$Q$6:$Q$44) -> 0.022013029 | K13: =p_sw_M6*(SUMPRODUCT(Holdings!$C13:$O13,Holdings!$C$32:$O$32,Holdings!$C$35:$O$35)+Inputs_Banks!$P13*(-p_dp_EQ)) -> 0.80204 | L13: =p_sw_M7*Inputs_Banks!$AF13*p_cre_lr -> 3.5504 | M13: =Inputs_Banks!$E13*Inputs_Banks!$K13*Inputs_Banks!$O13*p_dy -> 0 | N13: =MAX(0,-Inputs_Banks!$N13+Inputs_Banks!$M13*g_dur_htm*p_dy)+(1-Inputs_Banks!$E13)*MAX(0,-Inputs_Banks!$L13+Inputs_Banks!$K13*Inputs_Banks!$O13*p_dy) -> 20.579225 | O13: =p_sw_M8*(M13+N13*p_htm_forced) -> 0 | P13: =p_sw_M9*p_srt_lost*Inputs_Banks!$AA13/10000*Inputs_Banks!$H13 -> 0 | Q13: =p_sw_M10*Inputs_Banks!$AC13*CE_LRtrs0 -> 0 | R13: =p_sw_M11*Inputs_Banks!$AB13*p_pb_pd*MAX(0,p_pb_shock*g_pb_conc-g_pb_margin) -> 0 | S13: =F13+G13+H13+I13+J13+K13+L13+O13+P13+Q13+R13 -> 14.051402 | T13: =G13+I13+J13+K13+L13+P13+R13 -> 5.270403 | U13: =Inputs_Banks!$G13+p_ppnr_q*Inputs_Banks!$J13 -> 55 | V13: =Inputs_Banks!$H13*(1+p_rwa_infl) -> 548.856 | W13: =U13-(1-p_tax)*S13 -> 40.948598 | X13: =W13/V13 -> 0.074607178 | Y13: =p_sw_M1*(p_ccf_bl*Inputs_Banks!$Z13+BDC_EAD!J$154)+p_sw_M2*p_ccf_ff*Inputs_Banks!$T13+p_sw_M3*p_ccf_abf*Inputs_Banks!$V13+p_sw_M5*Z13+p_sw_M4*p_ccf_ins*Inputs_Banks!$AD13 -> 12.74156 | Z13: =p_ccf_ai*SUMPRODUCT(AI_Deals!AA$6:AA$44,AI_Deals!$R$6:$R$44) -> 0
A14: TFC | B14: Truist | C14: =SUMPRODUCT(BDC_EAD!K$106:K$127,BDC_EAD!$AB$106:$AB$127)+SUMPRODUCT(BDC_EAD!K$131:K$152,BDC_EAD!$AC$106:$AC$127) -> 0.31621219 | D14: =(Inputs_Banks!$Y14+p_ccf_bl*Inputs_Banks!$Z14)*CE_LRg0 -> 17.391257 | E14: =p_fraud*(Inputs_Banks!$Q14+Inputs_Banks!$S14+Inputs_Banks!$U14) -> 0.281 | F14: =p_sw_M1*(C14+D14+E14) -> 17.988469 | G14: =p_sw_M2*(Inputs_Banks!$S14+p_ccf_ff*Inputs_Banks!$T14)*CE_LRff -> 0.329175 | H14: =p_sw_M3*(Inputs_Banks!$U14+p_ccf_abf*Inputs_Banks!$V14)*CE_LRa0 -> 0 | I14: =p_sw_M4*(Inputs_Banks!$AD14*p_ccf_ins+Inputs_Banks!$AE14)*p_pd_ins*g_lgd_ins -> 0 | J14: =p_sw_M5*SUMPRODUCT(AI_Deals!AB$6:AB$44,AI_Deals!$Q$6:$Q$44) -> 0 | K14: =p_sw_M6*(SUMPRODUCT(Holdings!$C14:$O14,Holdings!$C$32:$O$32,Holdings!$C$35:$O$35)+Inputs_Banks!$P14*(-p_dp_EQ)) -> 0.1841 | L14: =p_sw_M7*Inputs_Banks!$AF14*p_cre_lr -> 3.5714 | M14: =Inputs_Banks!$E14*Inputs_Banks!$K14*Inputs_Banks!$O14*p_dy -> 0 | N14: =MAX(0,-Inputs_Banks!$N14+Inputs_Banks!$M14*g_dur_htm*p_dy)+(1-Inputs_Banks!$E14)*MAX(0,-Inputs_Banks!$L14+Inputs_Banks!$K14*Inputs_Banks!$O14*p_dy) -> 17.352335 | O14: =p_sw_M8*(M14+N14*p_htm_forced) -> 0 | P14: =p_sw_M9*p_srt_lost*Inputs_Banks!$AA14/10000*Inputs_Banks!$H14 -> 0 | Q14: =p_sw_M10*Inputs_Banks!$AC14*CE_LRtrs0 -> 0 | R14: =p_sw_M11*Inputs_Banks!$AB14*p_pb_pd*MAX(0,p_pb_shock*g_pb_conc-g_pb_margin) -> 0 | S14: =F14+G14+H14+I14+J14+K14+L14+O14+P14+Q14+R14 -> 22.073144 | T14: =G14+I14+J14+K14+L14+P14+R14 -> 4.084675 | U14: =Inputs_Banks!$G14+p_ppnr_q*Inputs_Banks!$J14 -> 46.3 | V14: =Inputs_Banks!$H14*(1+p_rwa_infl) -> 466.344 | W14: =U14-(1-p_tax)*S14 -> 24.226856 | X14: =W14/V14 -> 0.051950612 | Y14: =p_sw_M1*(p_ccf_bl*Inputs_Banks!$Z14+BDC_EAD!K$154)+p_sw_M2*p_ccf_ff*Inputs_Banks!$T14+p_sw_M3*p_ccf_abf*Inputs_Banks!$V14+p_sw_M5*Z14+p_sw_M4*p_ccf_ins*Inputs_Banks!$AD14 -> 19.943942 | Z14: =p_ccf_ai*SUMPRODUCT(AI_Deals!AB$6:AB$44,AI_Deals!$R$6:$R$44) -> 0
